Workbook

Sheet 抖音账单汇总
A1: 订单号 | B1: 求和项:销售收入 | C1: 已核对收入 | D1: 差异
A2: 6923064015675489559 | B2: 6 | C2: =_xlfn.XLOOKUP(A2,已核对收入!$A:$A,已核对收入!$B:$B) -> 6 | D2: =B2-C2 -> 0
A3: 6923416114502532384 | B3: -169 | C3: =_xlfn.XLOOKUP(A3,已核对收入!$A:$A,已核对收入!$B:$B) -> -169 | D3: =B3-C3 -> 0
A4: 6923455763794263484 | B4: -179 | C4: =_xlfn.XLOOKUP(A4,已核对收入!$A:$A,已核对收入!$B:$B) -> -179 | D4: =B4-C4 -> 0
A5: 6923636505633586984 | B5: 179 | C5: =_xlfn.XLOOKUP(A5,已核对收入!$A:$A,已核对收入!$B:$B) -> 179 | D5: =B5-C5 -> 0
A6: 6923640314699284416 | B6: -179 | C6: =_xlfn.XLOOKUP(A6,已核对收入!$A:$A,已核对收入!$B:$B) -> -179 | D6: =B6-C6 -> 0
A7: 6923643815047822963 | B7: 179 | C7: =_xlfn.XLOOKUP(A7,已核对收入!$A:$A,已核对收入!$B:$B) -> 179 | D7: =B7-C7 -> 0
A8: 6923652229969313434 | B8: -179 | C8: =_xlfn.XLOOKUP(A8,已核对收入!$A:$A,已核对收入!$B:$B) -> -179 | D8: =B8-C8 -> 0
A9: 6923661839766748780 | B9: -179 | C9: =_xlfn.XLOOKUP(A9,已核对收入!$A:$A,已核对收入!$B:$B) -> -179 | D9: =B9-C9 -> 0
A10: 6923667343994027127 | B10: -20.27 | C10: =_xlfn.XLOOKUP(A10,已核对收入!$A:$A,已核对收入!$B:$B) -> -20.27 | D10: =B10-C10 -> 0
A11: 6923676186043579878 | B11: 179 | C11: =_xlfn.XLOOKUP(A11,已核对收入!$A:$A,已核对收入!$B:$B) -> 179 | D11: =B11-C11 -> 0
A12: 6923691053209255280 | B12: -179 | C12: =_xlfn.XLOOKUP(A12,已核对收入!$A:$A,已核对收入!$B:$B) -> -179 | D12: =B12-C12 -> 0
A13: 6923706623434718909 | B13: 199 | C13: =_xlfn.XLOOKUP(A13,已核对收入!$A:$A,已核对收入!$B:$B) -> 199 | D13: =B13-C13 -> 0
... A2489: 总计 | B2489: 438770.18 | C2489: =_xlfn.XLOOKUP(A2489,已核对收入!$A:$A,已核对收入!$B:$B) -> 438770.18 | D2489: =B2489-C2489 -> 0

Sheet 抖音资金账单
A1: 动账时间 | B1: 动帐流水号 | C1: 动账方向 | D1: 动账金额 | E1: 动账账户 | F1: 动账场景 | G1: 计费类型 | H1: 子订单号 | I1: 订单号 | J1: 售后编号 | K1: 下单时间 | L1: 商品ID | M1: 商品名称 | N1: 达人ID | O1: 达人名称 | P1: 订单类型 | Q1: 订单实付应结 | R1: 销售收入 | S1: 运费实付 | T1: 实际平台补贴_运费 | U1: 实际平台补贴 | V1: 其他平台补贴 | W1: 以旧换新抵扣 | X1: 政府补贴平台垫资 | Y1: 实际达人补贴 | Z1: 实际抖音支付补贴 | AA1: 实际抖音月付营销补贴 | AB1: 银行补贴 | AC1: 订单退款 | AD1: 平台服务费 | AE1: 佣金 | AF1: 服务商佣金 | AG1: 渠道分成 | AH1: 招商服务费 | AI1: 站外推广费 | AJ1: 其他分成 | AK1: 是否免佣 | AL1: 免佣金额 | AM1: 备注
A2: 46054.145 | B2: '2026020103282407146092034081 | C2: 入账 | D2: 170.05 | E2: 聚合账户 | F2: 货款结算入账 | G2: 巨量千川 | H2: '6950156655091651754 | I2: '6950156655091651754 | J2: 'SS76006819130407657300061 | K2: 46044.562 | L2: '3787311554958066065 | M2: 【小火山】雪中飞儿童羽绒服冬装外套保暖冬装X2501326322FXT | P2: 普通订单 | Q2: 179 | R2: =Q2+SUM(T2:AC2) -> 179 | S2: 0 | T2: 0 | U2: 0 | V2: 0 | W2: 0 | X2: 0 | Y2: 0 | Z2: 0 | AA2: 0 | AB2: 0 | AC2: 0 | AD2: -8.95 | AE2: 0 | AF2: 0 | AG2: 0 | AH2: 0 | AI2: 0 | AJ2: 0 | AL2: 0 | AM2: 订单结算
A3: 46054.151 | B3: '2026020103374335750874114081 | C3: 入账 | D3: 170.05 | E3: 聚合账户 | F3: 货款结算入账 | G3: 小店自卖 | H3: '6950291725161993463 | I3: '6950291725161993463 | J3: 'SS76007626285014223710075 | K3: 46049.445 | L3: '3787311554958066065 | M3: 【小火山】雪中飞儿童羽绒服冬装外套保暖冬装X2501326322FXT | P3: 普通订单 | Q3: 179 | R3: =Q3+SUM(T3:AC3) -> 179 | S3: 0 | T3: 0 | U3: 0 | V3: 0 | W3: 0 | X3: 0 | Y3: 0 | Z3: 0 | AA3: 0 | AB3: 0 | AC3: 0 | AD3: -8.95 | AE3: 0 | AF3: 0 | AG3: 0 | AH3: 0 | AI3: 0 | AJ3: 0 | AL3: 0 | AM3: 订单结算
A4: 46054.151 | B4: '2026020103374439972375134081 | C4: 入账 | D4: 170.05 | E4: 聚合账户 | F4: 货款结算入账 | G4: 小店自卖 | H4: '6950169936981530544 | I4: '6950169936981530544 | J4: 'SS76006246102660592900093 | K4: 46044.429 | L4: '3787311554958066065 | M4: 【小火山】雪中飞儿童羽绒服冬装外套保暖冬装X2501326322FXT | P4: 普通订单 | Q4: 159 | R4: =Q4+SUM(T4:AC4) -> 179 | S4: 0 | T4: 0 | U4: 20 | V4: 0 | W4: 0 | X4: 0 | Y4: 0 | Z4: 0 | AA4: 0 | AB4: 0 | AC4: 0 | AD4: -8.95 | AE4: 0 | AF4: 0 | AG4: 0 | AH4: 0 | AI4: 0 | AJ4: 0 | AL4: 0 | AM4: 订单结算
A5: 46054.151 | B5: '2026020103374320567496144081 | C5: 入账 | D5: 170.05 | E5: 聚合账户 | F5: 货款结算入账 | G5: 巨量千川 | H5: '6950003137083741790 | I5: '6950003137083741790 | J5: 'SS75980830417139146760131 | K5: 46038.894 | L5: '3787311554958066065 | M5: 【小火山】雪中飞儿童羽绒服冬装外套保暖冬装X2501326322FXT | P5: 普通订单 | Q5: 159 | R5: =Q5+SUM(T5:AC5) -> 179 | S5: 0 | T5: 0 | U5: 20 | V5: 0 | W5: 0 | X5: 0 | Y5: 0 | Z5: 0 | AA5: 0 | AB5: 0 | AC5: 0 | AD5: -8.95 | AE5: 0 | AF5: 0 | AG5: 0 | AH5: 0 | AI5: 0 | AJ5: 0 | AL5: 0 | AM5: 订单结算
A6: 46054.163 | B6: '2026020103543335945685114081 | C6: 入账 | D6: 170.05 | E6: 聚合账户 | F6: 货款结算入账 | G6: 小店自卖 | H6: '6923791599134145789 | I6: '6923791599134145789 | J6: 'SS76006142717020249700005 | K6: 46043.809 | L6: '3787311554958066065 | M6: 【小火山】雪中飞儿童羽绒服冬装外套保暖冬装X2501326322FXT | P6: 普通订单 | Q6: 155.96 | R6: =Q6+SUM(T6:AC6) -> 179 | S6: 0 | T6: 0 | U6: 23.04 | V6: 0 | W6: 0 | X6: 0 | Y6: 0 | Z6: 0 | AA6: 0 | AB6: 0 | AC6: 0 | AD6: -8.95 | AE6: 0 | AF6: 0 | AG6: 0 | AH6: 0 | AI6: 0 | AJ6: 0 | AL6: 0 | AM6: 订单结算
A7: 46054.163 | B7: '2026020103544718465595424081 | C7: 入账 | D7: 170.05 | E7: 聚合账户 | F7: 货款结算入账 | G7: 巨量千川 | H7: '6923807694818541028 | I7: '6923807694818541028 | J7: 'SS76006594379889218920080 | K7: 46044.378 | L7: '3787311554958066065 | M7: 【小火山】雪中飞儿童羽绒服冬装外套保暖冬装X2501326322FXT | P7: 普通订单 | Q7: 159 | R7: =Q7+SUM(T7:AC7) -> 179 | S7: 0 | T7: 0 | U7: 20 | V7: 0 | W7: 0 | X7: 0 | Y7: 0 | Z7: 0 | AA7: 0 | AB7: 0 | AC7: 0 | AD7: -8.95 | AE7: 0 | AF7: 0 | AG7: 0 | AH7: 0 | AI7: 0 | AJ7: 0 | AL7: 0 | AM7: 订单结算
A8: 46054.169 | B8: '2026020104035203998193104081 | C8: 入账 | D8: 170.05 | E8: 聚合账户 | F8: 货款结算入账 | G8: 巨量千川 | H8: '6950133763685553252 | I8: '6950133763685553252 | J8: 'SS76005924296449395540138 | K8: 46043.903 | L8: '3787311554958066065 | M8: 【小火山】雪中飞儿童羽绒服冬装外套保暖冬装X2501326322FXT | P8: 普通订单 | Q8: 179 | R8: =Q8+SUM(T8:AC8) -> 179 | S8: 0 | T8: 0 | U8: 0 | V8: 0 | W8: 0 | X8: 0 | Y8: 0 | Z8: 0 | AA8: 0 | AB8: 0 | AC8: 0 | AD8: -8.95 | AE8: 0 | AF8: 0 | AG8: 0 | AH8: 0 | AI8: 0 | AJ8: 0 | AL8: 0 | AM8: 订单结算
A9: 46054.174 | B9: '2026020104103339605540354081 | C9: 入账 | D9: 170.05 | E9: 聚合账户 | F9: 货款结算入账 | G9: 小店自卖 | H9: '6950136311308424819 | I9: '6950136311308424819 | J9: 'SS76006163096053233140227 | K9: 46043.898 | L9: '3787311554958066065 | M9: 【小火山】雪中飞儿童羽绒服冬装外套保暖冬装X2501326322FXT | P9: 普通订单 | Q9: 169 | R9: =Q9+SUM(T9:AC9) -> 179 | S9: 0 | T9: 0 | U9: 10 | V9: 0 | W9: 0 | X9: 0 | Y9: 0 | Z9: 0 | AA9: 0 | AB9: 0 | AC9: 0 | AD9: -8.95 | AE9: 0 | AF9: 0 | AG9: 0 | AH9: 0 | AI9: 0 | AJ9: 0 | AL9: 0 | AM9: 订单结算
A10: 46054.174 | B10: '2026020104103128911706114081 | C10: 入账 | D10: 170.05 | E10: 聚合账户 | F10: 货款结算入账 | G10: 小店自卖 | H10: '6950146457801266618 | I10: '6950146457801266618 | J10: 'SS76006023018314348040058 | K10: 46043.687 | L10: '3787311554958066065 | M10: 【小火山】雪中飞儿童羽绒服冬装外套保暖冬装X2501326322FXT | P10: 普通订单 | Q10: 159 | R10: =Q10+SUM(T10:AC10) -> 179 | S10: 0 | T10: 0 | U10: 20 | V10: 0 | W10: 0 | X10: 0 | Y10: 0 | Z10: 0 | AA10: 0 | AB10: 0 | AC10: 0 | AD10: -8.95 | AE10: 0 | AF10: 0 | AG10: 0 | AH10: 0 | AI10: 0 | AJ10: 0 | AL10: 0 | AM10: 订单结算
A11: 46054.174 | B11: '2026020104103209737997264081 | C11: 入账 | D11: 170.05 | E11: 聚合账户 | F11: 货款结算入账 | G11: 小店自卖 | H11: '6950127036689684441 | I11: '6950127036689684441 | J11: 'SS75988987804245734860034 | K11: 46043.854 | L11: '3787311554958066065 | M11: 【小火山】雪中飞儿童羽绒服冬装外套保暖冬装X2501326322FXT | P11: 普通订单 | Q11: 179 | R11: =Q11+SUM(T11:AC11) -> 179 | S11: 0 | T11: 0 | U11: 0 | V11: 0 | W11: 0 | X11: 0 | Y11: 0 | Z11: 0 | AA11: 0 | AB11: 0 | AC11: 0 | AD11: -8.95 | AE11: 0 | AF11: 0 | AG11: 0 | AH11: 0 | AI11: 0 | AJ11: 0 | AL11: 0 | AM11: 订单结算
A12: 46054.174 | B12: '2026020104103038811244024081 | C12: 入账 | D12: 66.4 | E12: 聚合账户 | F12: 货款结算入账 | G12: 小店自卖 | H12: '6950144136995607613 | I12: '6950144136995607613 | J12: 'SS76005883611909166480009 | K12: 46043.742 | L12: '3780871747608379667 | M12: 雪中飞运动冬季男女童松紧带休闲裤直筒运动裤X2509329934FXT | P12: 普通订单 | Q12: 69.9 | R12: =Q12+SUM(T12:AC12) -> 69.9 | S12: 0 | T12: 0 | U12: 0 | V12: 0 | W12: 0 | X12: 0 | Y12: 0 | Z12: 0 | AA12: 0 | AB12: 0 | AC12: 0 | AD12: -3.5 | AE12: 0 | AF12: 0 | AG12: 0 | AH12: 0 | AI12: 0 | AJ12: 0 | AL12: 0 | AM12: 订单结算
A13: 46054.174 | B13: '2026020104103210327493184081 | C13: 入账 | D13: 170.05 | E13: 聚合账户 | F13: 货款结算入账 | G13: 巨量千川 | H13: '6923799515845328002 | I13: '6923799515845328002 | J13: 'SS76007034098513021590148 | K13: 46044.54 | L13: '3787311554958066065 | M13: 【小火山】雪中飞儿童羽绒服冬装外套保暖冬装X2501326322FXT | P13: 普通订单 | Q13: 179 | R13: =Q13+SUM(T13:AC13) -> 179 | S13: 0 | T13: 0 | U13: 0 | V13: 0 | W13: 0 | X13: 0 | Y13: 0 | Z13: 0 | AA13: 0 | AB13: 0 | AC13: 0 | AD13: -8.95 | AE13: 0 | AF13: 0 | AG13: 0 | AH13: 0 | AI13: 0 | AJ13: 0 | AL13: 0 | AM13: 订单结算
... A46: 46054.366 | B46: '2026020108464713099830184081 | C46: 入账 | D46: 170.05 | E46: 聚合账户 | F46: 货款结算入账 | G46: 巨量千川 | H46: '6923789717752413593 | I46: '6923789717752413593 | J46: 'SS76006148693690949120041 | K46: 46043.898 | L46: '3787311554958066065 | M46: 【小火山】雪中飞儿童羽绒服冬装外套保暖冬装X2501326322FXT | P46: 普通订单 | Q46: 149 | R46: =Q46+SUM(T46:AC46) -> 179 | S46: 0 | T46: 0 | U46: 30 | V46: 0 | W46: 0 | X46: 0 | Y46: 0 | Z46: 0 | AA46: 0 | AB46: 0 | AC46: 0 | AD46: -8.95 | AE46: 0 | AF46: 0 | AG46: 0 | AH46: 0 | AI46: 0 | AJ46: 0 | AL46: 0 | AM46: 订单结算
A47: 46054.367 | B47: '2026020108483823615616194081 | C47: 出账 | D47: 22.86 | E47: 聚合账户 | F47: 权益保险 | P47: 普通订单 | Q47: 0 | R47: =Q47+SUM(T47:AC47) -> 0 | S47: 0 | T47: 0 | U47: 0 | V47: 0 | W47: 0 | X47: 0 | Y47: 0 | Z47: 0 | AA47: 0 | AB47: 0 | AC47: 0 | AD47: 0 | AE47: 0 | AF47: 0 | AG47: 0 | AH47: 0 | AI47: 0 | AJ47: 0 | AL47: 0 | AM47: 保费扣除（6笔保单扣费,明细详见保费扣除明细）
A48: 46054.368 | B48: '2026020108492827897530974081 | C48: 入账 | D48: 170.05 | E48: 聚合账户 | F48: 货款结算入账 | G48: 小店自卖 | H48: '6923788906860740332 | I48: '6923788906860740332 | J48: 'SS76006021674222231230234 | K48: 46043.695 | L48: '3787311554958066065 | M48: 【小火山】雪中飞儿童羽绒服冬装外套保暖冬装X2501326322FXT | P48: 普通订单 | Q48: 179 | R48: =Q48+SUM(T48:AC48) -> 179 | S48: 0 | T48: 0 | U48: 0 | V48: 0 | W48: 0 | X48: 0 | Y48: 0 | Z48: 0 | AA48: 0 | AB48: 0 | AC48: 0 | AD48: -8.95 | AE48: 0 | AF48: 0 | AG48: 0 | AH48: 0 | AI48: 0 | AJ48: 0 | AL48: 0 | AM48: 订单结算
A49: 46054.369 | B49: '2026020108515903528133664081 | C49: 出账 | D49: 41.91 | E49: 聚合账户 | F49: 权益保险 | P49: 普通订单 | Q49: 0 | R49: =Q49+SUM(T49:AC49) -> 0 | S49: 0 | T49: 0 | U49: 0 | V49: 0 | W49: 0 | X49: 0 | Y49: 0 | Z49: 0 | AA49: 0 | AB49: 0 | AC49: 0 | AD49: 0 | AE49: 0 | AF49: 0 | AG49: 0 | AH49: 0 | AI49: 0 | AJ49: 0 | AL49: 0 | AM49: 保费扣除（11笔保单扣费,明细详见保费扣除明细）
A50: 46054.374 | B50: '2026020108574713056740384081 | C50: 出账 | D50: 83.82 | E50: 聚合账户 | F50: 权益保险 | P50: 普通订单 | Q50: 0 | R50: =Q50+SUM(T50:AC50) -> 0 | S50: 0 | T50: 0 | U50: 0 | V50: 0 | W50: 0 | X50: 0 | Y50: 0 | Z50: 0 | AA50: 0 | AB50: 0 | AC50: 0 | AD50: 0 | AE50: 0 | AF50: 0 | AG50: 0 | AH50: 0 | AI50: 0 | AJ50: 0 | AL50: 0 | AM50: 保费扣除（22笔保单扣费,明细详见保费扣除明细）
A51: 46054.375 | B51: '2026020108591505691684244081 | C51: 入账 | D51: 170.05 | E51: 聚合账户 | F51: 货款结算入账 | G51: 小店自卖 | H51: '6950144687867631409 | I51: '6950144687867631409 | J51: 'SS76006637625213793470131 | K51: 46043.905 | L51: '3787311554958066065 | M51: 【小火山】雪中飞儿童羽绒服冬装外套保暖冬装X2501326322FXT | P51: 普通订单 | Q51: 179 | R51: =Q51+SUM(T51:AC51) -> 179 | S51: 0 | T51: 0 | U51: 0 | V51: 0 | W51: 0 | X51: 0 | Y51: 0 | Z51: 0 | AA51: 0 | AB51: 0 | AC51: 0 | AD51: -8.95 | AE51: 0 | AF51: 0 | AG51: 0 | AH51: 0 | AI51: 0 | AJ51: 0 | AL51: 0 | AM51: 订单结算
A52: 46054.375 | B52: '2026020109003026230175064081 | C52: 入账 | D52: 170.05 | E52: 聚合账户 | F52: 货款结算入账 | G52: 小店自卖 | H52: '6923799730393349772 | I52: '6923799730393349772 | J52: 'SS76007076490467292500168 | K52: 46044.605 | L52: '3787311554958066065 | M52: 【小火山】雪中飞儿童羽绒服冬装外套保暖冬装X2501326322FXT | P52: 普通订单 | Q52: 157 | R52: =Q52+SUM(T52:AC52) -> 179 | S52: 0 | T52: 0 | U52: 22 | V52: 0 | W52: 0 | X52: 0 | Y52: 0 | Z52: 0 | AA52: 0 | AB52: 0 | AC52: 0 | AD52: -8.95 | AE52: 0 | AF52: 0 | AG52: 0 | AH52: 0 | AI52: 0 | AJ52: 0 | AL52: 0 | AM52: 订单结算
A53: 46054.376 | B53: '2026020109014438187382174081 | C53: 入账 | D53: 170.05 | E53: 聚合账户 | F53: 货款结算入账 | G53: 巨量千川 | H53: '6950222987647325297 | I53: '6950222987647325297 | J53: 'SS76007661157975662600080 | K53: 46046.79 | L53: '3787311554958066065 | M53: 【小火山】雪中飞儿童羽绒服冬装外套保暖冬装X2501326322FXT | P53: 普通订单 | Q53: 179 | R53: =Q53+SUM(T53:AC53) -> 179 | S53: 0 | T53: 0 | U53: 0 | V53: 0 | W53: 0 | X53: 0 | Y53: 0 | Z53: 0 | AA53: 0 | AB53: 0 | AC53: 0 | AD53: -8.95 | AE53: 0 | AF53: 0 | AG53: 0 | AH53: 0 | AI53: 0 | AJ53: 0 | AL53: 0 | AM53: 订单结算
A54: 46054.376 | B54: '2026020109014526472167034081 | C54: 入账 | D54: 170.05 | E54: 聚合账户 | F54: 货款结算入账 | G54: 小店自卖 | H54: '6923912871185054953 | I54: '6923912871185054953 | J54: 'SS76007393266327391120092 | K54: 46048.709 | L54: '3787311554958066065 | M54: 【小火山】雪中飞儿童羽绒服冬装外套保暖冬装X2501326322FXT | P54: 普通订单 | Q54: 159 | R54: =Q54+SUM(T54:AC54) -> 179 | S54: 0 | T54: 0 | U54: 20 | V54: 0 | W54: 0 | X54: 0 | Y54: 0 | Z54: 0 | AA54: 0 | AB54: 0 | AC54: 0 | AD54: -8.95 | AE54: 0 | AF54: 0 | AG54: 0 | AH54: 0 | AI54: 0 | AJ54: 0 | AL54: 0 | AM54: 订单结算
A55: 46054.377 | B55: '2026020109022229868362624081 | C55: 出账 | D55: 110.53 | E55: 聚合账户 | F55: 权益保险 | P55: 普通订单 | Q55: 0 | R55: =Q55+SUM(T55:AC55) -> 0 | S55: 0 | T55: 0 | U55: 0 | V55: 0 | W55: 0 | X55: 0 | Y55: 0 | Z55: 0 | AA55: 0 | AB55: 0 | AC55: 0 | AD55: 0 | AE55: 0 | AF55: 0 | AG55: 0 | AH55: 0 | AI55: 0 | AJ55: 0 | AL55: 0 | AM55: 保费扣除（29笔保单扣费,明细详见保费扣除明细）
A56: 46054.38 | B56: '2026020109070726386931564081 | C56: 入账 | D56: 170.05 | E56: 聚合账户 | F56: 货款结算入账 | G56: 巨量千川 | H56: '6950133795404059748 | I56: '6950133795404059748 | J56: 'SS76005923880551555080171 | K56: 46043.904 | L56: '3787311554958066065 | M56: 【小火山】雪中飞儿童羽绒服冬装外套保暖冬装X2501326322FXT | P56: 普通订单 | Q56: 179 | R56: =Q56+SUM(T56:AC56) -> 179 | S56: 0 | T56: 0 | U56: 0 | V56: 0 | W56: 0 | X56: 0 | Y56: 0 | Z56: 0 | AA56: 0 | AB56: 0 | AC56: 0 | AD56: -8.95 | AE56: 0 | AF56: 0 | AG56: 0 | AH56: 0 | AI56: 0 | AJ56: 0 | AL56: 0 | AM56: 订单结算
A57: 46054.384 | B57: '2026020109133229780707994081 | C57: 入账 | D57: 340.1 | E57: 聚合账户 | F57: 货款结算入账 | G57: 巨量千川 | H57: '6950131334658135954 | I57: '6950131334658135954 | J57: 'SS76006115132255936000047 | K57: 46043.791 | L57: '3787311554958066065 | M57: 【小火山】雪中飞儿童羽绒服冬装外套保暖冬装X2501326322FXT | P57: 普通订单 | Q57: 358 | R57: =Q57+SUM(T57:AC57) -> 358 | S57: 0 | T57: 0 | U57: 0 | V57: 0 | W57: 0 | X57: 0 | Y57: 0 | Z57: 0 | AA57: 0 | AB57: 0 | AC57: 0 | AD57: -17.9 | AE57: 0 | AF57: 0 | AG57: 0 | AH57: 0 | AI57: 0 | AJ57: 0 | AL57: 0 | AM57: 订单结算
A58: 46054.385 | B58: '2026020109135021712123344081 | C58: 出账 | D58: 26.67 | E58: 聚合账户 | F58: 权益保险 | P58: 普通订单 | Q58: 0 | R58: =Q58+SUM(T58:AC58) -> 0 | S58: 0 | T58: 0 | U58: 0 | V58: 0 | W58: 0 | X58: 0 | Y58: 0 | Z58: 0 | AA58: 0 | AB58: 0 | AC58: 0 | AD58: 0 | AE58: 0 | AF58: 0 | AG58: 0 | AH58: 0 | AI58: 0 | AJ58: 0 | AL58: 0 | AM58: 保费扣除（7笔保单扣费,明细详见保费扣除明细）
A59: 46054.385 | B59: '2026020109135327726157204081 | C59: 入账 | D59: 170.05 | E59: 聚合账户 | F59: 货款结算入账 | G59: 小店自卖 | H59: '6950154462153742086 | I59: '6950154462153742086 | J59: 'SS76006607469052441950098 | K59: 46044.44 | L59: '3787311554958066065 | M59: 【小火山】雪中飞儿童羽绒服冬装外套保暖冬装X2501326322FXT | P59: 普通订单 | Q59: 159 | R59: =Q59+SUM(T59:AC59) -> 179 | S59: 0 | T59: 0 | U59: 20 | V59: 0 | W59: 0 | X59: 0 | Y59: 0 | Z59: 0 | AA59: 0 | AB59: 0 | AC59: 0 | AD59: -8.95 | AE59: 0 | AF59: 0 | AG59: 0 | AH59: 0 | AI59: 0 | AJ59: 0 | AL59: 0 | AM59: 订单结算
A60: 46054.387 | B60: '2026020109173306125161594081 | C60: 出账 | D60: 64.77 | E60: 聚合账户 | F60: 权益保险 | P60: 普通订单 | Q60: 0 | R60: =Q60+SUM(T60:AC60) -> 0 | S60: 0 | T60: 0 | U60: 0 | V60: 0 | W60: 0 | X60: 0 | Y60: 0 | Z60: 0 | AA60: 0 | AB60: 0 | AC60: 0 | AD60: 0 | AE60: 0 | AF60: 0 | AG60: 0 | AH60: 0 | AI60: 0 | AJ60: 0 | AL60: 0 | AM60: 保费扣除（17笔保单扣费,明细详见保费扣除明细）
A61: 46054.391 | B61: '2026020109223404539520274081 | C61: 出账 | D61: 3.81 | E61: 聚合账户 | F61: 权益保险 | P61: 普通订单 | Q61: 0 | R61: =Q61+SUM(T61:AC61) -> 0 | S61: 0 | T61: 0 | U61: 0 | V61: 0 | W61: 0 | X61: 0 | Y61: 0 | Z61: 0 | AA61: 0 | AB61: 0 | AC61: 0 | AD61: 0 | AE61: 0 | AF61: 0 | AG61: 0 | AH61: 0 | AI61: 0 | AJ61: 0 | AL61: 0 | AM61: 保费扣除（1笔保单扣费,明细详见保费扣除明细）
A62: 46054.395 | B62: '2026020109281326175452704081 | C62: 出账 | D62: 11.43 | E62: 聚合账户 | F62: 权益保险 | P62: 普通订单 | Q62: 0 | R62: =Q62+SUM(T62:AC62) -> 0 | S62: 0 | T62: 0 | U62: 0 | V62: 0 | W62: 0 | X62: 0 | Y62: 0 | Z62: 0 | AA62: 0 | AB62: 0 | AC62: 0 | AD62: 0 | AE62: 0 | AF62: 0 | AG62: 0 | AH62: 0 | AI62: 0 | AJ62: 0 | AL62: 0 | AM62: 保费扣除（3笔保单扣费,明细详见保费扣除明细）
A63: 46054.399 | B63: '2026020109342537972549394081 | C63: 出账 | D63: 15.24 | E63: 聚合账户 | F63: 权益保险 | P63: 普通订单 | Q63: 0 | R63: =Q63+SUM(T63:AC63) -> 0 | S63: 0 | T63: 0 | U63: 0 | V63: 0 | W63: 0 | X63: 0 | Y63: 0 | Z63: 0 | AA63: 0 | AB63: 0 | AC63: 0 | AD63: 0 | AE63: 0 | AF63: 0 | AG63: 0 | AH63: 0 | AI63: 0 | AJ63: 0 | AL63: 0 | AM63: 保费扣除（4笔保单扣费,明细详见保费扣除明细）
A64: 46054.4 | B64: '2026020109355515334159744081 | C64: 入账 | D64: 170.05 | E64: 聚合账户 | F64: 货款结算入账 | G64: 巨量千川 | H64: '6950142026667857878 | I64: '6950142026667857878 | J64: 'SS76006028566273233980180 | K64: 46043.731 | L64: '3779048132244013371 | M64: 【升级款】雪中飞亲子儿童连帽羽绒服秋冬加厚外套X2501326322FXT | P64: 普通订单 | Q64: 179 | R64: =Q64+SUM(T64:AC64) -> 179 | S64: 0 | T64: 0 | U64: 0 | V64: 0 | W64: 0 | X64: 0 | Y64: 0 | Z64: 0 | AA64: 0 | AB64: 0 | AC64: 0 | AD64: -8.95 | AE64: 0 | AF64: 0 | AG64: 0 | AH64: 0 | AI64: 0 | AJ64: 0 | AL64: 0 | AM64: 订单结算
A65: 46054.403 | B65: '2026020109393606473324024081 | C65: 出账 | D65: 15.24 | E65: 聚合账户 | F65: 权益保险 | P65: 普通订单 | Q65: 0 | R65: =Q65+SUM(T65:AC65) -> 0 | S65: 0 | T65: 0 | U65: 0 | V65: 0 | W65: 0 | X65: 0 | Y65: 0 | Z65: 0 | AA65: 0 | AB65: 0 | AC65: 0 | AD65: 0 | AE65: 0 | AF65: 0 | AG65: 0 | AH65: 0 | AI65: 0 | AJ65: 0 | AL65: 0 | AM65: 保费扣除（4笔保单扣费,明细详见保费扣除明细）
A66: 46054.403 | B66: '2026020109401036960220594081 | C66: 入账 | D66: 170.05 | E66: 聚合账户 | F66: 货款结算入账 | G66: 巨量千川 | H66: '6923814437093408339 | I66: '6923814437093408339 | J66: 'SS75999834784197353470029 | K66: 46044.458 | L66: '3787311554958066065 | M66: 【小火山】雪中飞儿童羽绒服冬装外套保暖冬装X2501326322FXT | P66: 普通订单 | Q66: 159 | R66: =Q66+SUM(T66:AC66) -> 179 | S66: 0 | T66: 0 | U66: 20 | V66: 0 | W66: 0 | X66: 0 | Y66: 0 | Z66: 0 | AA66: 0 | AB66: 0 | AC66: 0 | AD66: -8.95 | AE66: 0 | AF66: 0 | AG66: 0 | AH66: 0 | AI66: 0 | AJ66: 0 | AL66: 0 | AM66: 订单结算
A67: 46054.403 | B67: '2026020109401433933276584081 | C67: 入账 | D67: 170.05 | E67: 聚合账户 | F67: 货款结算入账 | G67: 巨量千川 | H67: '6923808667715402752 | I67: '6923808667715402752 | J67: 'SS76007076616169231630137 | K67: 46044.603 | L67: '3787311554958066065 | M67: 【小火山】雪中飞儿童羽绒服冬装外套保暖冬装X2501326322FXT | P67: 普通订单 | Q67: 159 | R67: =Q67+SUM(T67:AC67) -> 179 | S67: 0 | T67: 0 | U67: 20 | V67: 0 | W67: 0 | X67: 0 | Y67: 0 | Z67: 0 | AA67: 0 | AB67: 0 | AC67: 0 | AD67: -8.95 | AE67: 0 | AF67: 0 | AG67: 0 | AH67: 0 | AI67: 0 | AJ67: 0 | AL67: 0 | AM67: 订单结算
A68: 46054.404 | B68: '2026020109414032974484894081 | C68: 出账 | D68: 3.81 | E68: 聚合账户 | F68: 权益保险 | P68: 普通订单 | Q68: 0 | R68: =Q68+SUM(T68:AC68) -> 0 | S68: 0 | T68: 0 | U68: 0 | V68: 0 | W68: 0 | X68: 0 | Y68: 0 | Z68: 0 | AA68: 0 | AB68: 0 | AC68: 0 | AD68: 0 | AE68: 0 | AF68: 0 | AG68: 0 | AH68: 0 | AI68: 0 | AJ68: 0 | AL68: 0 | AM68: 保费扣除（1笔保单扣费,明细详见保费扣除明细）
A69: 46054.406 | B69: '2026020109445916618622074081 | C69: 入账 | D69: 170.05 | E69: 聚合账户 | F69: 货款结算入账 | G69: 小店自卖 | H69: '6950140312541206208 | I69: '6950140312541206208 | J69: 'SS76006245325042161050090 | K69: 46043.806 | L69: '3787311554958066065 | M69: 【小火山】雪中飞儿童羽绒服冬装外套保暖冬装X2501326322FXT | P69: 普通订单 | Q69: 159 | R69: =Q69+SUM(T69:AC69) -> 179 | S69: 0 | T69: 0 | U69: 20 | V69: 0 | W69: 0 | X69: 0 | Y69: 0 | Z69: 0 | AA69: 0 | AB69: 0 | AC69: 0 | AD69: -8.95 | AE69: 0 | AF69: 0 | AG69: 0 | AH69: 0 | AI69: 0 | AJ69: 0 | AL69: 0 | AM69: 订单结算
A70: 46054.407 | B70: '2026020109452802487587944081 | C70: 入账 | D70: 170.05 | E70: 聚合账户 | F70: 货款结算入账 | G70: 巨量千川 | H70: '6923792997693357699 | I70: '6923792997693357699 | J70: 'SS76005791226157473800081 | K70: 46043.746 | L70: '3787311554958066065 | M70: 【小火山】雪中飞儿童羽绒服冬装外套保暖冬装X2501326322FXT | P70: 普通订单 | Q70: 159 | R70: =Q70+SUM(T70:AC70) -> 179 | S70: 0 | T70: 0 | U70: 20 | V70: 0 | W70: 0 | X70: 0 | Y70: 0 | Z70: 0 | AA70: 0 | AB70: 0 | AC70: 0 | AD70: -8.95 | AE70: 0 | AF70: 0 | AG70: 0 | AH70: 0 | AI70: 0 | AJ70: 0 | AL70: 0 | AM70: 订单结算
A71: 46054.408 | B71: '2026020109465434444249754081 | C71: 入账 | D71: 170.05 | E71: 聚合账户 | F71: 货款结算入账 | G71: 小店自卖 | H71: '6950154459920143427 | I71: '6950154459920143427 | J71: 'SS76006251940912663540127 | K71: 46044.437 | L71: '3787311554958066065 | M71: 【小火山】雪中飞儿童羽绒服冬装外套保暖冬装X2501326322FXT | P71: 普通订单 | Q71: 159 | R71: =Q71+SUM(T71:AC71) -> 179 | S71: 0 | T71: 0 | U71: 20 | V71: 0 | W71: 0 | X71: 0 | Y71: 0 | Z71: 0 | AA71: 0 | AB71: 0 | AC71: 0 | AD71: -8.95 | AE71: 0 | AF71: 0 | AG71: 0 | AH71: 0 | AI71: 0 | AJ71: 0 | AL71: 0 | AM71: 订单结算
A72: 46054.408 | B72: '2026020109465225086533534081 | C72: 入账 | D72: 159.35 | E72: 聚合账户 | F72: 货款结算入账 | G72: 巨量千川 | H72: '6923785819948612970 | I72: '6923785819948612970 | J72: 'SS75988564273186081540026 | K72: 46043.956 | L72: '3787311554958066065 | M72: 【小火山】雪中飞儿童羽绒服冬装外套保暖冬装X2501326322FXT | P72: 普通订单 | Q72: 159 | R72: =Q72+SUM(T72:AC72) -> 167.74 | S72: 0 | T72: 0 | U72: 18.74 | V72: 0 | W72: 0 | X72: 0 | Y72: 0 | Z72: 0 | AA72: 0 | AB72: 0 | AC72: -10 | AD72: -8.39 | AE72: 0 | AF72: 0 | AG72: 0 | AH72: 0 | AI72: 0 | AJ72: 0 | AL72: 0 | AM72: 订单结算
A73: 46054.408 | B73: '2026020109465420649255034081 | C73: 入账 | D73: 170.05 | E73: 聚合账户 | F73: 货款结算入账 | G73: 小店自卖 | H73: '6923797258405772721 | I73: '6923797258405772721 | J73: 'SS76006976112427671560111 | K73: 46044.531 | L73: '3787311554958066065 | M73: 【小火山】雪中飞儿童羽绒服冬装外套保暖冬装X2501326322FXT | P73: 普通订单 | Q73: 159 | R73: =Q73+SUM(T73:AC73) -> 179 | S73: 0 | T73: 0 | U73: 20 | V73: 0 | W73: 0 | X73: 0 | Y73: 0 | Z73: 0 | AA73: 0 | AB73: 0 | AC73: 0 | AD73: -8.95 | AE73: 0 | AF73: 0 | AG73: 0 | AH73: 0 | AI73: 0 | AJ73: 0 | AL73: 0 | AM73: 订单结算
A74: 46054.408 | B74: '2026020109465434359710724081 | C74: 入账 | D74: 170.05 | E74: 聚合账户 | F74: 货款结算入账 | G74: 巨量千川 | H74: '6950137651779277982 | I74: '6950137651779277982 | J74: 'SS76006120105021279100175 | K74: 46043.735 | L74: '3787311554958066065 | M74: 【小火山】雪中飞儿童羽绒服冬装外套保暖冬装X2501326322FXT | P74: 普通订单 | Q74: 177 | R74: =Q74+SUM(T74:AC74) -> 179 | S74: 0 | T74: 0 | U74: 2 | V74: 0 | W74: 0 | X74: 0 | Y74: 0 | Z74: 0 | AA74: 0 | AB74: 0 | AC74: 0 | AD74: -8.95 | AE74: 0 | AF74: 0 | AG74: 0 | AH74: 0 | AI74: 0 | AJ74: 0 | AL74: 0 | AM74: 订单结算
A75: 46054.408 | B75: '2026020109465416653358274081 | C75: 入账 | D75: 170.05 | E75: 聚合账户 | F75: 货款结算入账 | G75: 小店自卖 | H75: '6923785656451890335 | I75: '6923785656451890335 | J75: 'SS76006138863969121700207 | K75: 46043.919 | L75: '3787311554958066065 | M75: 【小火山】雪中飞儿童羽绒服冬装外套保暖冬装X2501326322FXT | P75: 普通订单 | Q75: 139 | R75: =Q75+SUM(T75:AC75) -> 179 | S75: 0 | T75: 0 | U75: 20 | V75: 0 | W75: 0 | X75: 0 | Y75: 0 | Z75: 0 | AA75: 20 | AB75: 0 | AC75: 0 | AD75: -8.95 | AE75: 0 | AF75: 0 | AG75: 0 | AH75: 0 | AI75: 0 | AJ75: 0 | AL75: 0 | AM75: 订单结算
A76: 46054.442 | B76: '2026020110360214598149394081 | C76: 入账 | D76: 170.05 | E76: 聚合账户 | F76: 货款结算入账 | G76: 巨量千川 | H76: '6923795017319087857 | I76: '6923795017319022321 | J76: 'SS76006793364044395980124 | K76: 46044.555 | L76: '3787311554958066065 | M76: 【小火山】雪中飞儿童羽绒服冬装外套保暖冬装X2501326322FXT | P76: 普通订单 | Q76: 156.2 | R76: =Q76+SUM(T76:AC76) -> 179 | S76: 0 | T76: 0 | U76: 22.8 | V76: 0 | W76: 0 | X76: 0 | Y76: 0 | Z76: 0 | AA76: 0 | AB76: 0 | AC76: 0 | AD76: -8.95 | AE76: 0 | AF76: 0 | AG76: 0 | AH76: 0 | AI76: 0 | AJ76: 0 | AL76: 0 | AM76: 订单结算
A77: 46054.443 | B77: '2026020110380225166978754081 | C77: 出账 | D77: 11.43 | E77: 聚合账户 | F77: 权益保险 | P77: 普通订单 | Q77: 0 | R77: =Q77+SUM(T77:AC77) -> 0 | S77: 0 | T77: 0 | U77: 0 | V77: 0 | W77: 0 | X77: 0 | Y77: 0 | Z77: 0 | AA77: 0 | AB77: 0 | AC77: 0 | AD77: 0 | AE77: 0 | AF77: 0 | AG77: 0 | AH77: 0 | AI77: 0 | AJ77: 0 | AL77: 0 | AM77: 保费扣除（3笔保单扣费,明细详见保费扣除明细）
A78: 46054.445 | B78: '2026020110401936292572504081 | C78: 入账 | D78: 170.05 | E78: 聚合账户 | F78: 货款结算入账 | G78: 小店自卖 | H78: '6950151792355514067 | I78: '6950151792355514067 | J78: 'SS76006100742689098600244 | K78: 46043.978 | L78: '3787311554958066065 | M78: 【小火山】雪中飞儿童羽绒服冬装外套保暖冬装X2501326322FXT | P78: 普通订单 | Q78: 159 | R78: =Q78+SUM(T78:AC78) -> 179 | S78: 0 | T78: 0 | U78: 20 | V78: 0 | W78: 0 | X78: 0 | Y78: 0 | Z78: 0 | AA78: 0 | AB78: 0 | AC78: 0 | AD78: -8.95 | AE78: 0 | AF78: 0 | AG78: 0 | AH78: 0 | AI78: 0 | AJ78: 0 | AL78: 0 | AM78: 订单结算
A79: 46054.461 | B79: '2026020111030926139364254081 | C79: 出账 | D79: 3.81 | E79: 聚合账户 | F79: 权益保险 | P79: 普通订单 | Q79: 0 | R79: =Q79+SUM(T79:AC79) -> 0 | S79: 0 | T79: 0 | U79: 0 | V79: 0 | W79: 0 | X79: 0 | Y79: 0 | Z79: 0 | AA79: 0 | AB79: 0 | AC79: 0 | AD79: 0 | AE79: 0 | AF79: 0 | AG79: 0 | AH79: 0 | AI79: 0 | AJ79: 0 | AL79: 0 | AM79: 保费扣除（1笔保单扣费,明细详见保费扣除明细）
A80: 46054.477 | B80: '2026020111271431685064224081 | C80: 出账 | D80: 159 | E80: 聚合账户 | F80: 退款-结算后退款-退用户 | G80: 小店自卖 | H80: '6949983283308860679 | I80: '6949983283308860679 | J80: '147333449183426910 | K80: 46038.982 | L80: '3787311554958066065 | M80: 【小火山】雪中飞儿童羽绒服冬装外套保暖冬装X2501326322FXT | P80: 普通订单 | Q80: 0 | R80: =Q80+SUM(T80:AC80) -> -159 | S80: 0 | T80: 0 | U80: 0 | V80: 0 | W80: 0 | X80: 0 | Y80: 0 | Z80: 0 | AA80: 0 | AB80: 0 | AC80: -159 | AD80: 0 | AE80: 0 | AF80: 0 | AG80: 0 | AH80: 0 | AI80: 0 | AJ80: 0 | AL80: 0 | AM80: 已退款
A81: 46054.477 | B81: '2026020111271337301990594081 | C81: 入账 | D81: 8.95 | E81: 聚合账户 | F81: 退款-订单退款触发-退分账 | G81: 小店自卖 | H81: '6949983283308860679 | I81: '6949983283308860679 | J81: '147333449183426910 | K81: 46038.982 | L81: '3787311554958066065 | M81: 【小火山】雪中飞儿童羽绒服冬装外套保暖冬装X2501326322FXT | P81: 普通订单 | Q81: 0 | R81: =Q81+SUM(T81:AC81) -> 0 | S81: 0 | T81: 0 | U81: 0 | V81: 0 | W81: 0 | X81: 0 | Y81: 0 | Z81: 0 | AA81: 0 | AB81: 0 | AC81: 0 | AD81: 8.95 | AE81: 0 | AF81: 0 | AG81: 0 | AH81: 0 | AI81: 0 | AJ81: 0 | AL81: 0 | AM81: 服务费返还
A82: 46054.478 | B82: '2026020111273428208013074081 | C82: 出账 | D82: 20 | E82: 聚合账户 | F82: 退款-订单退款触发-退补贴 | G82: 小店自卖 | H82: '6949983283308860679 | I82: '6949983283308860679 | J82: '147333449183426910 | K82: 46038.982 | L82: '3787311554958066065 | M82: 【小火山】雪中飞儿童羽绒服冬装外套保暖冬装X2501326322FXT | P82: 普通订单 | Q82: 0 | R82: =Q82+SUM(T82:AC82) -> -20 | S82: 0 | T82: 0 | U82: -20 | V82: 0 | W82: 0 | X82: 0 | Y82: 0 | Z82: 0 | AA82: 0 | AB82: 0 | AC82: 0 | AD82: 0 | AE82: 0 | AF82: 0 | AG82: 0 | AH82: 0 | AI82: 0 | AJ82: 0 | AL82: 0 | AM82: 平台补贴扣回
A83: 46054.487 | B83: '2026020111415124583380984081 | C83: 出账 | D83: 22.9 | E83: 聚合账户 | F83: 权益保险 | P83: 普通订单 | Q83: 0 | R83: =Q83+SUM(T83:AC83) -> 0 | S83: 0 | T83: 0 | U83: 0 | V83: 0 | W83: 0 | X83: 0 | Y83: 0 | Z83: 0 | AA83: 0 | AB83: 0 | AC83: 0 | AD83: 0 | AE83: 0 | AF83: 0 | AG83: 0 | AH83: 0 | AI83: 0 | AJ83: 0 | AL83: 0 | AM83: 保费扣除（6笔保单扣费,明细详见保费扣除明细）
A84: 46054.495 | B84: '2026020111532716580119454081 | C84: 入账 | D84: 170.05 | E84: 聚合账户 | F84: 货款结算入账 | G84: 小店自卖 | H84: '6950238313315767937 | I84: '6950238313315767937 | J84: 'SS76006815706802631770222 | K84: 46046.776 | L84: '3787311554958066065 | M84: 【小火山】雪中飞儿童羽绒服冬装外套保暖冬装X2501326322FXT | P84: 普通订单 | Q84: 159 | R84: =Q84+SUM(T84:AC84) -> 179 | S84: 0 | T84: 0 | U84: 20 | V84: 0 | W84: 0 | X84: 0 | Y84: 0 | Z84: 0 | AA84: 0 | AB84: 0 | AC84: 0 | AD84: -8.95 | AE84: 0 | AF84: 0 | AG84: 0 | AH84: 0 | AI84: 0 | AJ84: 0 | AL84: 0 | AM84: 订单结算
A85: 46054.507 | B85: '2026020112095738390669074081 | C85: 入账 | D85: 66.4 | E85: 聚合账户 | F85: 货款结算入账 | G85: 巨量千川 | H85: '6923914119195884896 | I85: '6923914119195884896 | J85: 'SS76007802118906027860235 | K85: 46048.45 | L85: '3780871747608379667 | M85: 雪中飞运动冬季男女童松紧带休闲裤直筒运动裤X2509329934FXT | P85: 普通订单 | Q85: 69.9 | R85: =Q85+SUM(T85:AC85) -> 69.9 | S85: 0 | T85: 0 | U85: 0 | V85: 0 | W85: 0 | X85: 0 | Y85: 0 | Z85: 0 | AA85: 0 | AB85: 0 | AC85: 0 | AD85: -3.5 | AE85: 0 | AF85: 0 | AG85: 0 | AH85: 0 | AI85: 0 | AJ85: 0 | AL85: 0 | AM85: 订单结算
A86: 46054.507 | B86: '2026020112095704917660544081 | C86: 入账 | D86: 170.05 | E86: 聚合账户 | F86: 货款结算入账 | G86: 小店自卖 | H86: '6923902275911646596 | I86: '6923902275911646596 | J86: 'SS76006015292551173220220 | K86: 46047.744 | L86: '3787311554958066065 | M86: 【小火山】雪中飞儿童羽绒服冬装外套保暖冬装X2501326322FXT | P86: 普通订单 | Q86: 179 | R86: =Q86+SUM(T86:AC86) -> 179 | S86: 0 | T86: 0 | U86: 0 | V86: 0 | W86: 0 | X86: 0 | Y86: 0 | Z86: 0 | AA86: 0 | AB86: 0 | AC86: 0 | AD86: -8.95 | AE86: 0 | AF86: 0 | AG86: 0 | AH86: 0 | AI86: 0 | AJ86: 0 | AL86: 0 | AM86: 订单结算
A87: 46054.507 | B87: '2026020112095828636165524081 | C87: 入账 | D87: 170.05 | E87: 聚合账户 | F87: 货款结算入账 | G87: 小店自卖 | H87: '6950246602048804760 | I87: '6950246602048804760 | J87: 'SS76006947643712517640008 | K87: 46047.659 | L87: '3787311554958066065 | M87: 【小火山】雪中飞儿童羽绒服冬装外套保暖冬装X2501326322FXT | P87: 普通订单 | Q87: 179 | R87: =Q87+SUM(T87:AC87) -> 179 | S87: 0 | T87: 0 | U87: 0 | V87: 0 | W87: 0 | X87: 0 | Y87: 0 | Z87: 0 | AA87: 0 | AB87: 0 | AC87: 0 | AD87: -8.95 | AE87: 0 | AF87: 0 | AG87: 0 | AH87: 0 | AI87: 0 | AJ87: 0 | AL87: 0 | AM87: 订单结算
A88: 46054.507 | B88: '2026020112095824177259984081 | C88: 入账 | D88: 170.05 | E88: 聚合账户 | F88: 货款结算入账 | G88: 小店自卖 | H88: '6923940296877178729 | I88: '6923940296877178729 | J88: 'SS76007401528262538740034 | K88: 46049.482 | L88: '3758813381755273379 | M88: 雪中飞亲子儿童中长款加厚羽绒服连帽秋冬保暖-X250138648FXT | P88: 普通订单 | Q88: 179 | R88: =Q88+SUM(T88:AC88) -> 179 | S88: 0 | T88: 0 | U88: 0 | V88: 0 | W88: 0 | X88: 0 | Y88: 0 | Z88: 0 | AA88: 0 | AB88: 0 | AC88: 0 | AD88: -8.95 | AE88: 0 | AF88: 0 | AG88: 0 | AH88: 0 | AI88: 0 | AJ88: 0 | AL88: 0 | AM88: 订单结算
A89: 46054.511 | B89: '2026020112155020817515934081 | C89: 入账 | D89: 0.12 | E89: 聚合账户 | F89: 退款-订单退款触发-退分账 | G89: 小店自卖 | H89: '6923667343994027127 | I89: '6923667343994027127 | J89: '147337794834146153 | K89: 46039.854 | L89: '3787311554958066065 | M89: 【小火山】雪中飞儿童羽绒服冬装外套保暖冬装X2501326322FXT | P89: 普通订单 | Q89: 0 | R89: =Q89+SUM(T89:AC89) -> 0 | S89: 0 | T89: 0 | U89: 0 | V89: 0 | W89: 0 | X89: 0 | Y89: 0 | Z89: 0 | AA89: 0 | AB89: 0 | AC89: 0 | AD89: 0.12 | AE89: 0 | AF89: 0 | AG89: 0 | AH89: 0 | AI89: 0 | AJ89: 0 | AL89: 0 | AM89: 服务费返还
A90: 46054.511 | B90: '2026020112154819598259394081 | C90: 出账 | D90: 18 | E90: 聚合账户 | F90: 退款-结算后退款-退用户 | G90: 小店自卖 | H90: '6923667343994027127 | I90: '6923667343994027127 | J90: '147337794834146153 | K90: 46039.854 | L90: '3787311554958066065 | M90: 【小火山】雪中飞儿童羽绒服冬装外套保暖冬装X2501326322FXT | P90: 普通订单 | Q90: 0 | R90: =Q90+SUM(T90:AC90) -> -18 | S90: 0 | T90: 0 | U90: 0 | V90: 0 | W90: 0 | X90: 0 | Y90: 0 | Z90: 0 | AA90: 0 | AB90: 0 | AC90: -18 | AD90: 0 | AE90: 0 | AF90: 0 | AG90: 0 | AH90: 0 | AI90: 0 | AJ90: 0 | AL90: 0 | AM90: 已退款
A91: 46054.511 | B91: '2026020112155201059233784081 | C91: 出账 | D91: 2.27 | E91: 聚合账户 | F91: 退款-订单退款触发-退补贴 | G91: 小店自卖 | H91: '6923667343994027127 | I91: '6923667343994027127 | J91: '147337794834146153 | K91: 46039.854 | L91: '3787311554958066065 | M91: 【小火山】雪中飞儿童羽绒服冬装外套保暖冬装X2501326322FXT | P91: 普通订单 | Q91: 0 | R91: =Q91+SUM(T91:AC91) -> -2.27 | S91: 0 | T91: 0 | U91: -2.27 | V91: 0 | W91: 0 | X91: 0 | Y91: 0 | Z91: 0 | AA91: 0 | AB91: 0 | AC91: 0 | AD91: 0 | AE91: 0 | AF91: 0 | AG91: 0 | AH91: 0 | AI91: 0 | AJ91: 0 | AL91: 0 | AM91: 平台补贴扣回
A92: 46054.518 | B92: '2026020112262431259858444081 | C92: 入账 | D92: 170.05 | E92: 聚合账户 | F92: 货款结算入账 | G92: 小店自卖 | H92: '6923814459496300241 | I92: '6923814459496300241 | J92: 'SS76006943128975122440142 | K92: 46044.469 | L92: '3787311554958066065 | M92: 【小火山】雪中飞儿童羽绒服冬装外套保暖冬装X2501326322FXT | P92: 普通订单 | Q92: 155.74 | R92: =Q92+SUM(T92:AC92) -> 179 | S92: 0 | T92: 0 | U92: 23.26 | V92: 0 | W92: 0 | X92: 0 | Y92: 0 | Z92: 0 | AA92: 0 | AB92: 0 | AC92: 0 | AD92: -8.95 | AE92: 0 | AF92: 0 | AG92: 0 | AH92: 0 | AI92: 0 | AJ92: 0 | AL92: 0 | AM92: 订单结算
A93: 46054.518 | B93: '2026020112262321902833144081 | C93: 入账 | D93: 144.4 | E93: 聚合账户 | F93: 货款结算入账 | G93: 小店自卖 | H93: '6923795629490994689 | I93: '6923795629490994689 | J93: 'SS75996670904212403460210 | K93: 46043.846 | L93: '3787311554958066065 | M93: 【小火山】雪中飞儿童羽绒服冬装外套保暖冬装X2501326322FXT | P93: 普通订单 | Q93: 179 | R93: =Q93+SUM(T93:AC93) -> 152 | S93: 0 | T93: 0 | U93: 0 | V93: 0 | W93: 0 | X93: 0 | Y93: 0 | Z93: 0 | AA93: 0 | AB93: 0 | AC93: -27 | AD93: -7.6 | AE93: 0 | AF93: 0 | AG93: 0 | AH93: 0 | AI93: 0 | AJ93: 0 | AL93: 0 | AM93: 订单结算
A94: 46054.518 | B94: '2026020112262417078193154081 | C94: 入账 | D94: 170.05 | E94: 聚合账户 | F94: 货款结算入账 | G94: 小店自卖 | H94: '6923774060185943642 | I94: '6923774060185943642 | J94: 'SS76006147483053755380147 | K94: 46043.747 | L94: '3787311554958066065 | M94: 【小火山】雪中飞儿童羽绒服冬装外套保暖冬装X2501326322FXT | P94: 普通订单 | Q94: 159 | R94: =Q94+SUM(T94:AC94) -> 179 | S94: 0 | T94: 0 | U94: 20 | V94: 0 | W94: 0 | X94: 0 | Y94: 0 | Z94: 0 | AA94: 0 | AB94: 0 | AC94: 0 | AD94: -8.95 | AE94: 0 | AF94: 0 | AG94: 0 | AH94: 0 | AI94: 0 | AJ94: 0 | AL94: 0 | AM94: 订单结算
A95: 46054.518 | B95: '2026020112262424636296114081 | C95: 入账 | D95: 170.05 | E95: 聚合账户 | F95: 货款结算入账 | G95: 巨量千川 | H95: '6923780366895775107 | I95: '6923780366895775107 | J95: 'SS76006158057053721950125 | K95: 46043.756 | L95: '3787311554958066065 | M95: 【小火山】雪中飞儿童羽绒服冬装外套保暖冬装X2501326322FXT | P95: 普通订单 | Q95: 179 | R95: =Q95+SUM(T95:AC95) -> 179 | S95: 0 | T95: 0 | U95: 0 | V95: 0 | W95: 0 | X95: 0 | Y95: 0 | Z95: 0 | AA95: 0 | AB95: 0 | AC95: 0 | AD95: -8.95 | AE95: 0 | AF95: 0 | AG95: 0 | AH95: 0 | AI95: 0 | AJ95: 0 | AL95: 0 | AM95: 订单结算
... A112: 46054.554 | B112: '2026020113172704827550814081 | C112: 入账 | D112: 170.05 | E112: 聚合账户 | F112: 货款结算入账 | G112: 巨量千川 | H112: '6923787165141400674 | I112: '6923787165141400674 | J112: 'SS76006018389718310810221 | K112: 46043.815 | L112: '3787311554958066065 | M112: 【小火山】雪中飞儿童羽绒服冬装外套保暖冬装X2501326322FXT | P112: 普通订单 | Q112: 177 | R112: =Q112+SUM(T112:AC112) -> 179 | S112: 0 | T112: 0 | U112: 2 | V112: 0 | W112: 0 | X112: 0 | Y112: 0 | Z112: 0 | AA112: 0 | AB112: 0 | AC112: 0 | AD112: -8.95 | AE112: 0 | AF112: 0 | AG112: 0 | AH112: 0 | AI112: 0 | AJ112: 0 | AL112: 0 | AM112: 订单结算
A113: 46054.562 | B113: '2026020113290430032696734081 | C113: 出账 | D113: 57.55 | E113: 聚合账户 | F113: 权益保险 | P113: 普通订单 | Q113: 0 | R113: =Q113+SUM(T113:AC113) -> 0 | S113: 0 | T113: 0 | U113: 0 | V113: 0 | W113: 0 | X113: 0 | Y113: 0 | Z113: 0 | AA113: 0 | AB113: 0 | AC113: 0 | AD113: 0 | AE113: 0 | AF113: 0 | AG113: 0 | AH113: 0 | AI113: 0 | AJ113: 0 | AL113: 0 | AM113: 保费扣除（15笔保单扣费,明细详见保费扣除明细）
A114: 46054.562 | B114: '2026020113291108107461664081 | C114: 入账 | D114: 66.4 | E114: 聚合账户 | F114: 货款结算入账 | G114: 小店自卖 | H114: '6923793396860943741 | I114: '6923793396860943741 | J114: 'SS76005883592619791900219 | K114: 46043.878 | L114: '3780871747608379667 | M114: 雪中飞运动冬季男女童松紧带休闲裤直筒运动裤X2509329934FXT | P114: 普通订单 | Q114: 69.9 | R114: =Q114+SUM(T114:AC114) -> 69.9 | S114: 0 | T114: 0 | U114: 0 | V114: 0 | W114: 0 | X114: 0 | Y114: 0 | Z114: 0 | AA114: 0 | AB114: 0 | AC114: 0 | AD114: -3.5 | AE114: 0 | AF114: 0 | AG114: 0 | AH114: 0 | AI114: 0 | AJ114: 0 | AL114: 0 | AM114: 订单结算
A115: 46054.562 | B115: '2026020113290717044447134081 | C115: 入账 | D115: 170.05 | E115: 聚合账户 | F115: 货款结算入账 | G115: 小店自卖 | H115: '6950165991177393569 | I115: '6950165991177393569 | J115: 'SS76007070772033500660171 | K115: 46044.592 | L115: '3787311554958066065 | M115: 【小火山】雪中飞儿童羽绒服冬装外套保暖冬装X2501326322FXT | P115: 普通订单 | Q115: 179 | R115: =Q115+SUM(T115:AC115) -> 179 | S115: 0 | T115: 0 | U115: 0 | V115: 0 | W115: 0 | X115: 0 | Y115: 0 | Z115: 0 | AA115: 0 | AB115: 0 | AC115: 0 | AD115: -8.95 | AE115: 0 | AF115: 0 | AG115: 0 | AH115: 0 | AI115: 0 | AJ115: 0 | AK115: 否 | AL115: 0 | AM115: 订单结算
A116: 46054.562 | B116: '2026020113290941739886444081 | C116: 入账 | D116: 170.05 | E116: 聚合账户 | F116: 货款结算入账 | G116: 巨量千川 | H116: '6950174182196057416 | I116: '6950174182196057416 | J116: 'SS76006212390633518440218 | K116: 46045.432 | L116: '3787311554958066065 | M116: 【小火山】雪中飞儿童羽绒服冬装外套保暖冬装X2501326322FXT | P116: 普通订单 | Q116: 179 | R116: =Q116+SUM(T116:AC116) -> 179 | S116: 0 | T116: 0 | U116: 0 | V116: 0 | W116: 0 | X116: 0 | Y116: 0 | Z116: 0 | AA116: 0 | AB116: 0 | AC116: 0 | AD116: -8.95 | AE116: 0 | AF116: 0 | AG116: 0 | AH116: 0 | AI116: 0 | AJ116: 0 | AL116: 0 | AM116: 订单结算
A117: 46054.562 | B117: '2026020113291120819031454081 | C117: 入账 | D117: 170.05 | E117: 聚合账户 | F117: 货款结算入账 | G117: 巨量千川 | H117: '6950138658545341951 | I117: '6950138658545341951 | J117: 'SS76006594030958064740070 | K117: 46044.367 | L117: '3787311554958066065 | M117: 【小火山】雪中飞儿童羽绒服冬装外套保暖冬装X2501326322FXT | P117: 普通订单 | Q117: 179 | R117: =Q117+SUM(T117:AC117) -> 179 | S117: 0 | T117: 0 | U117: 0 | V117: 0 | W117: 0 | X117: 0 | Y117: 0 | Z117: 0 | AA117: 0 | AB117: 0 | AC117: 0 | AD117: -8.95 | AE117: 0 | AF117: 0 | AG117: 0 | AH117: 0 | AI117: 0 | AJ117: 0 | AL117: 0 | AM117: 订单结算
A118: 46054.562 | B118: '2026020113291035362739264081 | C118: 入账 | D118: 170.05 | E118: 聚合账户 | F118: 货款结算入账 | G118: 小店自卖 | H118: '6950156878352356395 | I118: '6950156878352356395 | J118: 'SS76006868706874821640234 | K118: 46044.627 | L118: '3787311554958066065 | M118: 【小火山】雪中飞儿童羽绒服冬装外套保暖冬装X2501326322FXT | P118: 普通订单 | Q118: 139 | R118: =Q118+SUM(T118:AC118) -> 179 | S118: 0 | T118: 0 | U118: 40 | V118: 0 | W118: 0 | X118: 0 | Y118: 0 | Z118: 0 | AA118: 0 | AB118: 0 | AC118: 0 | AD118: -8.95 | AE118: 0 | AF118: 0 | AG118: 0 | AH118: 0 | AI118: 0 | AJ118: 0 | AL118: 0 | AM118: 订单结算
A119: 46054.566 | B119: '2026020113342612793943234081 | C119: 出账 | D119: 7.62 | E119: 聚合账户 | F119: 权益保险 | P119: 普通订单 | Q119: 0 | R119: =Q119+SUM(T119:AC119) -> 0 | S119: 0 | T119: 0 | U119: 0 | V119: 0 | W119: 0 | X119: 0 | Y119: 0 | Z119: 0 | AA119: 0 | AB119: 0 | AC119: 0 | AD119: 0 | AE119: 0 | AF119: 0 | AG119: 0 | AH119: 0 | AI119: 0 | AJ119: 0 | AL119: 0 | AM119: 保费扣除（2笔保单扣费,明细详见保费扣除明细）
A120: 46054.566 | B120: '2026020113345906936171614081 | C120: 入账 | D120: 8.95 | E120: 聚合账户 | F120: 退款-订单退款触发-退分账 | G120: 小店自卖 | H120: '6923741802922998984 | I120: '6923741802922998984 | J120: '147336008046307129 | K120: 46042.013 | L120: '3787311554958066065 | M120: 【小火山】雪中飞儿童羽绒服冬装外套保暖冬装X2501326322FXT | P120: 普通订单 | Q120: 0 | R120: =Q120+SUM(T120:AC120) -> 0 | S120: 0 | T120: 0 | U120: 0 | V120: 0 | W120: 0 | X120: 0 | Y120: 0 | Z120: 0 | AA120: 0 | AB120: 0 | AC120: 0 | AD120: 8.95 | AE120: 0 | AF120: 0 | AG120: 0 | AH120: 0 | AI120: 0 | AJ120: 0 | AL120: 0 | AM120: 服务费返还
A121: 46054.566 | B121: '2026020113350103325463144081 | C121: 出账 | D121: 159 | E121: 聚合账户 | F121: 退款-极速退二阶段商家资金回补 | G121: 小店自卖 | H121: '6923741802922998984 | I121: '6923741802922998984 | J121: '147336008046307129 | K121: 46042.013 | L121: '3787311554958066065 | M121: 【小火山】雪中飞儿童羽绒服冬装外套保暖冬装X2501326322FXT | P121: 普通订单 | Q121: 0 | R121: =Q121+SUM(T121:AC121) -> -159 | S121: 0 | T121: 0 | U121: 0 | V121: 0 | W121: 0 | X121: 0 | Y121: 0 | Z121: 0 | AA121: 0 | AB121: 0 | AC121: -159 | AD121: 0 | AE121: 0 | AF121: 0 | AG121: 0 | AH121: 0 | AI121: 0 | AJ121: 0 | AL121: 0 | AM121: 订单号 6923741802922998984，退款金额 159.00 元
A122: 46054.566 | B122: '2026020113350116126446464081 | C122: 出账 | D122: 20 | E122: 聚合账户 | F122: 退款-订单退款触发-退补贴 | G122: 小店自卖 | H122: '6923741802922998984 | I122: '6923741802922998984 | J122: '147336008046307129 | K122: 46042.013 | L122: '3787311554958066065 | M122: 【小火山】雪中飞儿童羽绒服冬装外套保暖冬装X2501326322FXT | P122: 普通订单 | Q122: 0 | R122: =Q122+SUM(T122:AC122) -> -20 | S122: 0 | T122: 0 | U122: -20 | V122: 0 | W122: 0 | X122: 0 | Y122: 0 | Z122: 0 | AA122: 0 | AB122: 0 | AC122: 0 | AD122: 0 | AE122: 0 | AF122: 0 | AG122: 0 | AH122: 0 | AI122: 0 | AJ122: 0 | AL122: 0 | AM122: 平台补贴扣回
A123: 46054.567 | B123: '2026020113362111494732994081 | C123: 出账 | D123: 11.43 | E123: 聚合账户 | F123: 权益保险 | P123: 普通订单 | Q123: 0 | R123: =Q123+SUM(T123:AC123) -> 0 | S123: 0 | T123: 0 | U123: 0 | V123: 0 | W123: 0 | X123: 0 | Y123: 0 | Z123: 0 | AA123: 0 | AB123: 0 | AC123: 0 | AD123: 0 | AE123: 0 | AF123: 0 | AG123: 0 | AH123: 0 | AI123: 0 | AJ123: 0 | AL123: 0 | AM123: 保费扣除（3笔保单扣费,明细详见保费扣除明细）
A124: 46054.572 | B124: '2026020113433533022615584081 | C124: 入账 | D124: 170.05 | E124: 聚合账户 | F124: 货款结算入账 | G124: 小店自卖 | H124: '6923794763528633581 | I124: '6923794763528633581 | J124: 'SS76007075974442071560050 | K124: 46044.464 | L124: '3787311554958066065 | M124: 【小火山】雪中飞儿童羽绒服冬装外套保暖冬装X2501326322FXT | P124: 普通订单 | Q124: 159 | R124: =Q124+SUM(T124:AC124) -> 179 | S124: 0 | T124: 0 | U124: 20 | V124: 0 | W124: 0 | X124: 0 | Y124: 0 | Z124: 0 | AA124: 0 | AB124: 0 | AC124: 0 | AD124: -8.95 | AE124: 0 | AF124: 0 | AG124: 0 | AH124: 0 | AI124: 0 | AJ124: 0 | AL124: 0 | AM124: 订单结算
A125: 46054.572 | B125: '2026020113441826603525394081 | C125: 出账 | D125: 22.9 | E125: 聚合账户 | F125: 权益保险 | P125: 普通订单 | Q125: 0 | R125: =Q125+SUM(T125:AC125) -> 0 | S125: 0 | T125: 0 | U125: 0 | V125: 0 | W125: 0 | X125: 0 | Y125: 0 | Z125: 0 | AA125: 0 | AB125: 0 | AC125: 0 | AD125: 0 | AE125: 0 | AF125: 0 | AG125: 0 | AH125: 0 | AI125: 0 | AJ125: 0 | AL125: 0 | AM125: 保费扣除（6笔保单扣费,明细详见保费扣除明细）
A126: 46054.573 | B126: '2026020113442739933875394081 | C126: 入账 | D126: 170.05 | E126: 聚合账户 | F126: 货款结算入账 | G126: 小店自卖 | H126: '6923787697874238515 | I126: '6923787697874238515 | J126: 'SS76006012902558971070142 | K126: 46043.942 | L126: '3787311554958066065 | M126: 【小火山】雪中飞儿童羽绒服冬装外套保暖冬装X2501326322FXT | P126: 普通订单 | Q126: 159 | R126: =Q126+SUM(T126:AC126) -> 179 | S126: 0 | T126: 0 | U126: 20 | V126: 0 | W126: 0 | X126: 0 | Y126: 0 | Z126: 0 | AA126: 0 | AB126: 0 | AC126: 0 | AD126: -8.95 | AE126: 0 | AF126: 0 | AG126: 0 | AH126: 0 | AI126: 0 | AJ126: 0 | AL126: 0 | AM126: 订单结算
A127: 46054.575 | B127: '2026020113474501895183994081 | C127: 入账 | D127: 170.05 | E127: 聚合账户 | F127: 货款结算入账 | G127: 小店自卖 | H127: '6923796760034312097 | I127: '6923796760034312097 | J127: 'SS76006238294797688660233 | K127: 46044.395 | L127: '3787311554958066065 | M127: 【小火山】雪中飞儿童羽绒服冬装外套保暖冬装X2501326322FXT | P127: 普通订单 | Q127: 147 | R127: =Q127+SUM(T127:AC127) -> 179 | S127: 0 | T127: 0 | U127: 32 | V127: 0 | W127: 0 | X127: 0 | Y127: 0 | Z127: 0 | AA127: 0 | AB127: 0 | AC127: 0 | AD127: -8.95 | AE127: 0 | AF127: 0 | AG127: 0 | AH127: 0 | AI127: 0 | AJ127: 0 | AL127: 0 | AM127: 订单结算
A128: 46054.578 | B128: '2026020113520507610370824081 | C128: 入账 | D128: 170.05 | E128: 聚合账户 | F128: 货款结算入账 | G128: 小店自卖 | H128: '6923802418930810702 | I128: '6923802418930810702 | J128: 'SS76006148987749174020173 | K128: 46043.92 | L128: '3787311554958066065 | M128: 【小火山】雪中飞儿童羽绒服冬装外套保暖冬装X2501326322FXT | P128: 普通订单 | Q128: 159 | R128: =Q128+SUM(T128:AC128) -> 179 | S128: 0 | T128: 0 | U128: 20 | V128: 0 | W128: 0 | X128: 0 | Y128: 0 | Z128: 0 | AA128: 0 | AB128: 0 | AC128: 0 | AD128: -8.95 | AE128: 0 | AF128: 0 | AG128: 0 | AH128: 0 | AI128: 0 | AJ128: 0 | AL128: 0 | AM128: 订单结算
A129: 46054.58 | B129: '2026020113554408394552384081 | C129: 入账 | D129: 161.49 | E129: 聚合账户 | F129: 货款结算入账 | G129: 小店自卖 | H129: '6923876096675184542 | I129: '6923876096675184542 | J129: 'SS76007017602161915150125 | K129: 46046.917 | L129: '3787311554958066065 | M129: 【小火山】雪中飞儿童羽绒服冬装外套保暖冬装X2501326322FXT | P129: 普通订单 | Q129: 159 | R129: =Q129+SUM(T129:AC129) -> 169.99 | S129: 0 | T129: 0 | U129: 18.99 | V129: 0 | W129: 0 | X129: 0 | Y129: 0 | Z129: 0 | AA129: 0 | AB129: 0 | AC129: -8 | AD129: -8.5 | AE129: 0 | AF129: 0 | AG129: 0 | AH129: 0 | AI129: 0 | AJ129: 0 | AL129: 0 | AM129: 订单结算
A130: 46054.581 | B130: '2026020113564706211996664081 | C130: 出账 | D130: 22.86 | E130: 聚合账户 | F130: 权益保险 | P130: 普通订单 | Q130: 0 | R130: =Q130+SUM(T130:AC130) -> 0 | S130: 0 | T130: 0 | U130: 0 | V130: 0 | W130: 0 | X130: 0 | Y130: 0 | Z130: 0 | AA130: 0 | AB130: 0 | AC130: 0 | AD130: 0 | AE130: 0 | AF130: 0 | AG130: 0 | AH130: 0 | AI130: 0 | AJ130: 0 | AL130: 0 | AM130: 保费扣除（6笔保单扣费,明细详见保费扣除明细）
A131: 46054.582 | B131: '2026020113583610246108544081 | C131: 入账 | D131: 66.4 | E131: 聚合账户 | F131: 货款结算入账 | G131: 巨量千川 | H131: '6923814799489727923 | I131: '6923814799489727923 | J131: 'SS76006978129822354270142 | K131: 46044.515 | L131: '3780871747608379667 | M131: 雪中飞运动冬季男女童松紧带休闲裤直筒运动裤X2509329934FXT | P131: 普通订单 | Q131: 69.9 | R131: =Q131+SUM(T131:AC131) -> 69.9 | S131: 0 | T131: 0 | U131: 0 | V131: 0 | W131: 0 | X131: 0 | Y131: 0 | Z131: 0 | AA131: 0 | AB131: 0 | AC131: 0 | AD131: -3.5 | AE131: 0 | AF131: 0 | AG131: 0 | AH131: 0 | AI131: 0 | AJ131: 0 | AL131: 0 | AM131: 订单结算
A132: 46054.585 | B132: '2026020114015614358285064081 | C132: 出账 | D132: 11.43 | E132: 聚合账户 | F132: 权益保险 | P132: 普通订单 | Q132: 0 | R132: =Q132+SUM(T132:AC132) -> 0 | S132: 0 | T132: 0 | U132: 0 | V132: 0 | W132: 0 | X132: 0 | Y132: 0 | Z132: 0 | AA132: 0 | AB132: 0 | AC132: 0 | AD132: 0 | AE132: 0 | AF132: 0 | AG132: 0 | AH132: 0 | AI132: 0 | AJ132: 0 | AL132: 0 | AM132: 保费扣除（3笔保单扣费,明细详见保费扣除明细）
A133: 46054.585 | B133: '2026020114022615101670944081 | C133: 入账 | D133: 170.05 | E133: 聚合账户 | F133: 货款结算入账 | G133: 巨量千川 | H133: '6950156741106537642 | I133: '6950156741106537642 | J133: 'SS76006819093833326440189 | K133: 46044.561 | L133: '3787311554958066065 | M133: 【小火山】雪中飞儿童羽绒服冬装外套保暖冬装X2501326322FXT | P133: 普通订单 | Q133: 177 | R133: =Q133+SUM(T133:AC133) -> 179 | S133: 0 | T133: 0 | U133: 2 | V133: 0 | W133: 0 | X133: 0 | Y133: 0 | Z133: 0 | AA133: 0 | AB133: 0 | AC133: 0 | AD133: -8.95 | AE133: 0 | AF133: 0 | AG133: 0 | AH133: 0 | AI133: 0 | AJ133: 0 | AL133: 0 | AM133: 订单结算
A134: 46054.594 | B134: '2026020114152426427558824081 | C134: 入账 | D134: 170.05 | E134: 聚合账户 | F134: 货款结算入账 | G134: 小店自卖 | H134: '6923797942709484925 | I134: '6923797942709484925 | J134: 'SS76006697341113799680056 | K134: 46043.874 | L134: '3787311554958066065 | M134: 【小火山】雪中飞儿童羽绒服冬装外套保暖冬装X2501326322FXT | P134: 普通订单 | Q134: 159 | R134: =Q134+SUM(T134:AC134) -> 179 | S134: 0 | T134: 0 | U134: 20 | V134: 0 | W134: 0 | X134: 0 | Y134: 0 | Z134: 0 | AA134: 0 | AB134: 0 | AC134: 0 | AD134: -8.95 | AE134: 0 | AF134: 0 | AG134: 0 | AH134: 0 | AI134: 0 | AJ134: 0 | AL134: 0 | AM134: 订单结算
A135: 46054.595 | B135: '2026020114163712123671314081 | C135: 出账 | D135: 19.25 | E135: 聚合账户 | F135: 权益保险 | P135: 普通订单 | Q135: 0 | R135: =Q135+SUM(T135:AC135) -> 0 | S135: 0 | T135: 0 | U135: 0 | V135: 0 | W135: 0 | X135: 0 | Y135: 0 | Z135: 0 | AA135: 0 | AB135: 0 | AC135: 0 | AD135: 0 | AE135: 0 | AF135: 0 | AG135: 0 | AH135: 0 | AI135: 0 | AJ135: 0 | AL135: 0 | AM135: 保费扣除（5笔保单扣费,明细详见保费扣除明细）
A136: 46054.599 | B136: '2026020114215309237632424081 | C136: 出账 | D136: 34.33 | E136: 聚合账户 | F136: 权益保险 | P136: 普通订单 | Q136: 0 | R136: =Q136+SUM(T136:AC136) -> 0 | S136: 0 | T136: 0 | U136: 0 | V136: 0 | W136: 0 | X136: 0 | Y136: 0 | Z136: 0 | AA136: 0 | AB136: 0 | AC136: 0 | AD136: 0 | AE136: 0 | AF136: 0 | AG136: 0 | AH136: 0 | AI136: 0 | AJ136: 0 | AL136: 0 | AM136: 保费扣除（9笔保单扣费,明细详见保费扣除明细）
A137: 46054.602 | B137: '2026020114271830646973444081 | C137: 入账 | D137: 170.05 | E137: 聚合账户 | F137: 货款结算入账 | G137: 小店自卖 | H137: '6950126757341107474 | I137: '6950126757341107474 | J137: 'SS76006019444331482030156 | K137: 46043.726 | L137: '3787311554958066065 | M137: 【小火山】雪中飞儿童羽绒服冬装外套保暖冬装X2501326322FXT | P137: 普通订单 | Q137: 159 | R137: =Q137+SUM(T137:AC137) -> 179 | S137: 0 | T137: 0 | U137: 20 | V137: 0 | W137: 0 | X137: 0 | Y137: 0 | Z137: 0 | AA137: 0 | AB137: 0 | AC137: 0 | AD137: -8.95 | AE137: 0 | AF137: 0 | AG137: 0 | AH137: 0 | AI137: 0 | AJ137: 0 | AL137: 0 | AM137: 订单结算
A138: 46054.603 | B138: '2026020114280939415690704081 | C138: 出账 | D138: 38.5 | E138: 聚合账户 | F138: 权益保险 | P138: 普通订单 | Q138: 0 | R138: =Q138+SUM(T138:AC138) -> 0 | S138: 0 | T138: 0 | U138: 0 | V138: 0 | W138: 0 | X138: 0 | Y138: 0 | Z138: 0 | AA138: 0 | AB138: 0 | AC138: 0 | AD138: 0 | AE138: 0 | AF138: 0 | AG138: 0 | AH138: 0 | AI138: 0 | AJ138: 0 | AL138: 0 | AM138: 保费扣除（10笔保单扣费,明细详见保费扣除明细）
A139: 46054.607 | B139: '2026020114334800977679464081 | C139: 出账 | D139: 23.1 | E139: 聚合账户 | F139: 权益保险 | P139: 普通订单 | Q139: 0 | R139: =Q139+SUM(T139:AC139) -> 0 | S139: 0 | T139: 0 | U139: 0 | V139: 0 | W139: 0 | X139: 0 | Y139: 0 | Z139: 0 | AA139: 0 | AB139: 0 | AC139: 0 | AD139: 0 | AE139: 0 | AF139: 0 | AG139: 0 | AH139: 0 | AI139: 0 | AJ139: 0 | AL139: 0 | AM139: 保费扣除（6笔保单扣费,明细详见保费扣除明细）
A140: 46054.609 | B140: '2026020114373208600458504081 | C140: 出账 | D140: 23.1 | E140: 聚合账户 | F140: 权益保险 | P140: 普通订单 | Q140: 0 | R140: =Q140+SUM(T140:AC140) -> 0 | S140: 0 | T140: 0 | U140: 0 | V140: 0 | W140: 0 | X140: 0 | Y140: 0 | Z140: 0 | AA140: 0 | AB140: 0 | AC140: 0 | AD140: 0 | AE140: 0 | AF140: 0 | AG140: 0 | AH140: 0 | AI140: 0 | AJ140: 0 | AL140: 0 | AM140: 保费扣除（6笔保单扣费,明细详见保费扣除明细）
A141: 46054.625 | B141: '2026020114595108780684804081 | C141: 出账 | D141: 69.9 | E141: 聚合账户 | F141: 退款-结算后退款-退用户 | G141: 巨量千川 | H141: '6949744748009297684 | I141: '6949744748009297684 | J141: '147334010111580972 | K141: 46030.873 | L141: '3780871747608379667 | M141: 雪中飞运动冬季男女童松紧带休闲裤直筒运动裤X2509329934FXT | P141: 普通订单 | Q141: 0 | R141: =Q141+SUM(T141:AC141) -> -69.9 | S141: 0 | T141: 0 | U141: 0 | V141: 0 | W141: 0 | X141: 0 | Y141: 0 | Z141: 0 | AA141: 0 | AB141: 0 | AC141: -69.9 | AD141: 0 | AE141: 0 | AF141: 0 | AG141: 0 | AH141: 0 | AI141: 0 | AJ141: 0 | AL141: 0 | AM141: 已退款
A142: 46054.625 | B142: '2026020114595306470538594081 | C142: 入账 | D142: 3.5 | E142: 聚合账户 | F142: 退款-订单退款触发-退分账 | G142: 巨量千川 | H142: '6949744748009297684 | I142: '6949744748009297684 | J142: '147334010111580972 | K142: 46030.873 | L142: '3780871747608379667 | M142: 雪中飞运动冬季男女童松紧带休闲裤直筒运动裤X2509329934FXT | P142: 普通订单 | Q142: 0 | R142: =Q142+SUM(T142:AC142) -> 0 | S142: 0 | T142: 0 | U142: 0 | V142: 0 | W142: 0 | X142: 0 | Y142: 0 | Z142: 0 | AA142: 0 | AB142: 0 | AC142: 0 | AD142: 3.5 | AE142: 0 | AF142: 0 | AG142: 0 | AH142: 0 | AI142: 0 | AJ142: 0 | AL142: 0 | AM142: 服务费返还
A143: 46054.627 | B143: '2026020115025324678239224081 | C143: 出账 | D143: 3.85 | E143: 聚合账户 | F143: 权益保险 | P143: 普通订单 | Q143: 0 | R143: =Q143+SUM(T143:AC143) -> 0 | S143: 0 | T143: 0 | U143: 0 | V143: 0 | W143: 0 | X143: 0 | Y143: 0 | Z143: 0 | AA143: 0 | AB143: 0 | AC143: 0 | AD143: 0 | AE143: 0 | AF143: 0 | AG143: 0 | AH143: 0 | AI143: 0 | AJ143: 0 | AL143: 0 | AM143: 保费扣除（1笔保单扣费,明细详见保费扣除明细）
A144: 46054.63 | B144: '2026020115074136498480994081 | C144: 入账 | D144: 8.95 | E144: 聚合账户 | F144: 退款-订单退款触发-退分账 | G144: 巨量千川 | H144: '6950049542876436228 | I144: '6950049542876436228 | J144: '147333125199402515 | K144: 46041.417 | L144: '3787311554958066065 | M144: 【小火山】雪中飞儿童羽绒服冬装外套保暖冬装X2501326322FXT | P144: 普通订单 | Q144: 0 | R144: =Q144+SUM(T144:AC144) -> 0 | S144: 0 | T144: 0 | U144: 0 | V144: 0 | W144: 0 | X144: 0 | Y144: 0 | Z144: 0 | AA144: 0 | AB144: 0 | AC144: 0 | AD144: 8.95 | AE144: 0 | AF144: 0 | AG144: 0 | AH144: 0 | AI144: 0 | AJ144: 0 | AL144: 0 | AM144: 服务费返还
A145: 46054.63 | B145: '2026020115074211886600184081 | C145: 出账 | D145: 179 | E145: 聚合账户 | F145: 退款-极速退二阶段商家资金回补 | G145: 巨量千川 | H145: '6950049542876436228 | I145: '6950049542876436228 | J145: '147333125199402515 | K145: 46041.417 | L145: '3787311554958066065 | M145: 【小火山】雪中飞儿童羽绒服冬装外套保暖冬装X2501326322FXT | P145: 普通订单 | Q145: 0 | R145: =Q145+SUM(T145:AC145) -> -179 | S145: 0 | T145: 0 | U145: 0 | V145: 0 | W145: 0 | X145: 0 | Y145: 0 | Z145: 0 | AA145: 0 | AB145: 0 | AC145: -179 | AD145: 0 | AE145: 0 | AF145: 0 | AG145: 0 | AH145: 0 | AI145: 0 | AJ145: 0 | AL145: 0 | AM145: 订单号 6950049542876436228，退款金额 179.00 元
A146: 46054.637 | B146: '2026020115164500274271354081 | C146: 出账 | D146: 3.85 | E146: 聚合账户 | F146: 权益保险 | P146: 普通订单 | Q146: 0 | R146: =Q146+SUM(T146:AC146) -> 0 | S146: 0 | T146: 0 | U146: 0 | V146: 0 | W146: 0 | X146: 0 | Y146: 0 | Z146: 0 | AA146: 0 | AB146: 0 | AC146: 0 | AD146: 0 | AE146: 0 | AF146: 0 | AG146: 0 | AH146: 0 | AI146: 0 | AJ146: 0 | AL146: 0 | AM146: 保费扣除（1笔保单扣费,明细详见保费扣除明细）
A147: 46054.649 | B147: '2026020115342123245790984081 | C147: 入账 | D147: 66.4 | E147: 聚合账户 | F147: 货款结算入账 | G147: 小店自卖 | H147: '6950119849943832327 | I147: '6950119849943832327 | J147: 'SS76006997929733983230010 | K147: 46043.672 | L147: '3780871747608379667 | M147: 雪中飞运动冬季男女童松紧带休闲裤直筒运动裤X2509329934FXT | P147: 普通订单 | Q147: 69.9 | R147: =Q147+SUM(T147:AC147) -> 69.9 | S147: 0 | T147: 0 | U147: 0 | V147: 0 | W147: 0 | X147: 0 | Y147: 0 | Z147: 0 | AA147: 0 | AB147: 0 | AC147: 0 | AD147: -3.5 | AE147: 0 | AF147: 0 | AG147: 0 | AH147: 0 | AI147: 0 | AJ147: 0 | AK147: 否 | AL147: 0 | AM147: 订单结算
A148: 46054.653 | B148: '2026020115393236249275284081 | C148: 出账 | D148: 2.5 | E148: 聚合账户 | F148: 偏远地区物流服务 | I148: '6924075052164743066 | P148: 普通订单 | Q148: 0 | R148: =Q148+SUM(T148:AC148) -> 0 | S148: 0 | T148: 0 | U148: 0 | V148: 0 | W148: 0 | X148: 0 | Y148: 0 | Z148: 0 | AA148: 0 | AB148: 0 | AC148: 0 | AD148: 0 | AE148: 0 | AF148: 0 | AG148: 0 | AH148: 0 | AI148: 0 | AJ148: 0 | AL148: 0 | AM148: 偏远地区配送费_PK7601798238291788084_YT0011635213203
...

Sheet 已核对收入
A1: 原始线上订单号 | B1: 求和项:金额
A2: 6923416114502532384 | B2: -169
A3: 6923455763794263484 | B3: -179
A4: 6923636505633586984 | B4: 179
A5: 6923640314699284416 | B5: -179
A6: 6923643815047822963 | B6: 179
A7: 6923652229969313434 | B7: -179
A8: 6923661839766748780 | B8: -179
A9: 6923667343994027127 | B9: -20.27
A10: 6923676186043579878 | B10: 179
A11: 6923691053209255280 | B11: -179
A12: 6923706623434718909 | B12: 199
A13: 6923706884902846404 | B13: 179
... A2489: 总计 | B2489: 438770.18

Sheet 销售汇总
A3: 款式编码 | B3: 求和项:件数 | C3: 求和项:金额
A4: X2501319062FXT | B4: 1 | C4: 199
A5: X2501319626FXT | B5: 2 | C5: 358
A6: X2501324376FXT | B6: 1 | C6: 179
A7: X2501326322FXT | B7: 2280 | C7: 407489.64
A8: X250138238FXT | B8: 54 | C8: 10673.74
A9: X250138240FXT | B9: 32 | C9: 5088
A10: X250138648FXT | B10: 24 | C10: 4296
A11: X250138650FXT | B11: 1 | C11: 199
A12: X2501419056FT | B12: 2 | C12: 518
A13: X2501419060FXT | B13: 2 | C13: 558
A14: X2501419066FXT | B14: 3 | C14: 837
A15: X2501419131FT | B15: 1 | C15: 299
... A31: X40144476FXT | B31: 1 | C31: 259
A32: (空白)
A33: 总计 | B33: 2482 | C33: 438770.18

Sheet 聚水潭导出店铺数据
A1: 内部订单号 | B1: 标记多标签 | C1: 售后单号 | D1: 订单类型 | E1: 线上订单号 | F1: 平台外部订单号 | G1: 订单状态 | H1: 发货仓 | I1: 虚拟仓 | J1: 分销商 | K1: 店铺 | L1: 买家账号 | M1: 买家ID | N1: 买家留言 | O1: 卖家备注 | P1: 订单日期 | Q1: 发货日期 | R1: 付款日期 | S1: 确认收货日期 | T1: 供销支付时间 | U1: 省 | V1: 市 | W1: 区县 | X1: 订单快递公司 | Y1: 订单快递单号 | Z1: 售后快递公司 | AA1: 售后快递单号 | AB1: 收货人 | AC1: 售后登记日期 | AD1: 售后确认日期 | AE1: 售后进仓日期 | AF1: 售后进仓单号 | AG1: 收货仓 | AH1: 售后分类 | AI1: 问题类型 | AJ1: 商品编码 | AK1: 店铺款式编码 | AL1: 原始线上订单号 | AM1: 款式编码 | AN1: 产品分类 | AO1: 虚拟分类 | AP1: 商品简称 | AQ1: 颜色规格 | AR1: 线上颜色规格 | AS1: 品牌 | AT1: 供应商 | AU1: 供应商款号 | AV1: 供应商商品编码 | AW1: 商品标签 | AX1: 组合装实体编码 | AY1: 基本售价 | AZ1: 成本价 | BA1: 成本价来源 | BB1: 销售数量 | BC1: 赠品数量 | BD1: 实发数量 | BE1: 实发金额 | BF1: 销售金额 | BG1: 销售成本 | BH1: 实发成本 | BI1: 销售毛利 | BJ1: 销售毛利率 | BK1: 已付金额 | BL1: 应付金额 | BM1: 售价 | BN1: 基本金额 | BO1: 当期退货数量 | BP1: 当期实退数量 | BQ1: 当期退货金额 | BR1: 当期退货成本 | BS1: 当期实退成本 | BT1: 当期实退金额 | BU1: 运费收入 | BV1: 运费收入分摊 | BW1: 运费支出 | BX1: 运费支出分摊 | BY1: 优惠金额 | BZ1: 订单重量 | CA1: 订单商品重量 | CB1: 商店站点 | CC1: 订单来源 | CD1: 便签 | CE1: 其它价格1 | CF1: 件数 | CG1: 金额 | CH1: 抖音资金账单金额
A2: 19675024 | B2: 优先发货,发货后售后,小店,店铺新客,抖音,高频购买 | D2: 普通订单 | E2: 6923455763794263484 | G2: 已发货 | H2: 河北贝吉实业集团有限公司 | K2: 抖音-雪中飞德煌童装专卖店 | L2: 1@#GWBmmHWFl9twJLEV8t1WG+mzxE4ul4+7udBQ0AiGV/9GIpbUNQSA8y5iSDBr7Sqt99Ec | M2: 12867611 | O2: (收) 颜色分类:蝶恋紫;尺码大小:170cmI568114919700*1# | P2: 2026/1/6 16:23:14 | Q2: 2026/1/7 10:11:43 | R2: 2026/1/6 16:23:25 | S2: 2026/1/14 10:11:48 | T2: 2026/1/6 16:23:25 | U2: 湖北省 | V2: 荆州市 | W2: 监利市 | X2: 圆通速递 | Y2: YT0003734281957 | AB2: 147:颜* | AJ2: I568150074600 | AK2: 3787311554958066065 | AL2: 6923455763794263484 | AM2: X2501326322FXT | AP2: 儿童轻薄羽绒服 | AQ2: 绯红;160 | AR2: 颜色分类:绯红;尺码大小:160CM | AS2: 雪中飞 | AT2: 无唛尚品 | AY2: 179 | AZ2: 90 | BA2: 普通商品资料成本价 | BB2: 1 | BD2: 1 | BE2: 179 | BF2: 179 | BG2: 90 | BH2: 90 | BI2: 89 | BJ2: 49.721% | BM2: 179 | BN2: 179 | BX2: 2.8 | CB2: 头条放心购 | CC2: TOUTIAOFXG | CE2: 101.5 | CF2: 0 | CG2: 0 | CH2: =_xlfn.XLOOKUP(AL2,抖音账单汇总!$A:$A,抖音账单汇总!$B:$B) -> -179
A3: 21084099 | B3: 小店,平台补贴,店铺老客,服务优先,高频购买 | D3: 普通订单 | E3: 6950766742891665321 | G3: 已发货 | H3: 河北贝吉实业集团有限公司 | K3: 抖音-雪中飞德煌童装专卖店 | L3: 1@#z3Bl7h2mItj2my4HO6B1jh5TO7drsyUtmTMONWT40u5oP06Zq8MV7NT/mYrcwEfZ+wBk | M3: 13896512 | P3: 2026/2/18 14:18:05 | Q3: 2026/2/18 17:07:25 | R3: 2026/2/18 14:18:12 | S3: 2026/2/23 21:45:27 | T3: 2026/2/18 14:18:12 | U3: 河南省 | V3: 郑州市 | W3: 新郑市 | X3: 京东快递 | Y3: JDAZ23866283026 | AB3: 147:连* | AJ3: H626415547302 | AK3: 3787311554958066065 | AL3: 6950766742891665321 | AM3: X250138238FXT | AN3: 轻薄羽绒服 | AP3: 儿童轻薄羽绒服 | AQ3: 藏青色;130 | AR3: 颜色分类:藏青（8238款）;尺码大小:130CM | AS3: 雪中飞 | AT3: 茸淳羽绒 | AW3: 每日加权 | AY3: 199 | AZ3: 105.3 | BA3: 普通商品资料成本价 | BB3: 1 | BD3: 1 | BE3: 199 | BF3: 199 | BG3: 105.3 | BH3: 105.3 | BI3: 93.7 | BJ3: 47.085% | BK3: 199 | BL3: 199 | BM3: 199 | BN3: 199 | BU3: 0 | BW3: 15 | BX3: 15 | BZ3: 0.512 | CA3: 0.512 | CB3: 头条放心购 | CC3: TOUTIAOFXG | CE3: 116.8 | CF3: =BD3-BP3 -> 1 | CG3: 199 | CH3: =_xlfn.XLOOKUP(AL3,抖音账单汇总!$A:$A,抖音账单汇总!$B:$B) -> 199
A4: 21081483 | B4: 发货后售后,小店,店铺新客,抖音,高频购买 | D4: 普通订单 | E4: 6924387514871283172 | G4: 已发货 | H4: 河北贝吉实业集团有限公司 | K4: 抖音-雪中飞德煌童装专卖店 | L4: 1@#kJAIYJrStILJaLum1t2WfTmTWnqv0C3MlW+8EQK5t+71DkI9RoUSEjMVw/j4EXcvnkBc | M4: 13894338 | O4: hp返8【雪風 02-26 15:27】 | P4: 2026/2/16 17:49:57 | Q4: 2026/2/18 13:52:41 | R4: 2026/2/16 17:50:03 | S4: 2026/2/25 13:52:43 | T4: 2026/2/16 17:50:03 | U4: 湖南省 | V4: 长沙市 | W4: 浏阳市 | X4: 京东快递 | Y4: JDAZ23864881536 | AB4: 147:张* | AJ4: I568150018600 | AK4: 3787311554958066065 | AL4: 6924387514871283172 | AM4: X2501326322FXT | AP4: 儿童轻薄羽绒服 | AQ4: 橄榄绿;160 | AR4: 颜色分类:橄榄绿;尺码大小:160CM | AS4: 雪中飞 | AT4: 涛源 | AY4: 179 | AZ4: 86.7 | BA4: 普通商品资料成本价 | BB4: 1 | BD4: 1 | BE4: 179 | BF4: 179 | BG4: 86.7 | BH4: 86.7 | BI4: 92.3 | BJ4: 51.564% | BK4: 179 | BL4: 179 | BM4: 179 | BN4: 179 | BU4: 0 | BW4: 15 | BX4: 15 | BZ4: 0.506 | CA4: 0.506 | CB4: 头条放心购 | CC4: TOUTIAOFXG | CE4: 98.2 | CF4: =BD4-BP4 -> 1 | CG4: 171 | CH4: =_xlfn.XLOOKUP(AL4,抖音账单汇总!$A:$A,抖音账单汇总!$B:$B) -> 171
A5: 19675024 | B5: 优先发货,发货后售后,小店,店铺新客,抖音,高频购买 | C5: 1226353186 | D5: 普通订单 | E5: 6923455763794263484 | G5: 已发货 | H5: 河北贝吉实业集团有限公司 | K5: 抖音-雪中飞德煌童装专卖店 | L5: 1@#GWBmmHWFl9twJLEV8t1WG+mzxE4ul4+7udBQ0AiGV/9GIpbUNQSA8y5iSDBr7Sqt99Ec | M5: 12867611 | O5: (收) 颜色分类:蝶恋紫;尺码大小:170cmI568114919700*1# | P5: 2026/1/6 16:23:14 | Q5: 2026/1/7 10:11:43 | R5: 2026/1/6 16:23:25 | S5: 2026/1/14 10:11:48 | T5: 2026/1/6 16:23:25 | U5: 湖北省 | V5: 荆州市 | W5: 监利市 | X5: 圆通速递 | Y5: YT0003734281957 | Z5: 韵达快递 | AA5: 312955322570264 | AB5: 147:颜* | AC5: 2026/2/4 19:18:58 | AD5: 2026/2/7 14:28:20 | AE5: 2026-02-07 14:28:13 | AF5: 20171187 | AG5: 河北贝吉实业集团有限公司 | AH5: 普通退货 | AI5: 与商家协商一致退款 | AJ5: I568114919700 | AK5: 3787311554958066065 | AL5: 6923455763794263484 | AM5: X2501326322FXT | AN5: 轻薄羽绒服 | AP5: 儿童轻薄羽绒服 | AQ5: 香芋紫;170 | AR5: 颜色分类:蝶恋紫;尺码大小:170CM | AS5: 雪中飞 | AT5: 涛源 | AY5: 179 | AZ5: 86.7 | BA5: 普通商品资料成本价 | BB5: 1 | BD5: 1 | BE5: 179 | BF5: 179 | BG5: 86.7 | BH5: 86.7 | BI5: 92.3 | BJ5: 51.564% | BK5: 358 | BL5: 358 | BM5: 179 | BN5: 179 | BO5: 1 | BP5: 1 | BQ5: 179 | BR5: 86.7 | BS5: 86.7 | BT5: 179 | BU5: 0 | BW5: 5.6 | BX5: 2.8 | BZ5: 1.043 | CA5: 1.043 | CB5: 头条放心购 | CC5: TOUTIAOFXG | CE5: 98.2 | CF5: -1 | CG5: -179 | CH5: =_xlfn.XLOOKUP(AL5,抖音账单汇总!$A:$A,抖音账单汇总!$B:$B) -> -179
A6: 21078885 | B6: 小店,店铺老客,抖音,高频购买 | D6: 普通订单 | E6: 6950767968497244059 | G6: 已发货 | H6: 河北贝吉实业集团有限公司 | K6: 抖音-雪中飞德煌童装专卖店 | L6: 1@#vNwC0k86jojzwXHn09Ly/x6b1HWAlSLA+r1tbkmXTUvHLbGyDWXC22M0+5lu6bd5kUJ16iUCnA== | M6: 13883831 | P6: 2026/2/15 9:43:34 | Q6: 2026/2/15 13:15:18 | R6: 2026/2/15 9:43:35 | S6: 2026/2/22 13:15:20 | T6: 2026/2/15 9:43:35 | U6: 上海 | V6: 上海市 | W6: 浦东新区 | X6: 京东快递 | Y6: JDAZ23847075801 | AB6: 147:叶* | AJ6: H493814417140 | AK6: 3787311554958066065 | AL6: 6950767968497244059 | AM6: X250138240FXT | AN6: 羽绒服 | AP6: 儿童轻薄羽绒服 | AQ6: 黑色;150 | AR6: 颜色分类:黑色（8240款）;尺码大小:150CM | AS6: 雪中飞 | AT6: 茸淳羽绒 | AW6: 每日加权 | AY6: 179 | AZ6: 87 | BA6: 普通商品资料成本价 | BB6: 1 | BD6: 1 | BE6: 159 | BF6: 159 | BG6: 87 | BH6: 87 | BI6: 72 | BJ6: 45.283% | BK6: 159 | BL6: 159 | BM6: 159 | BN6: 159 | BU6: 0 | BW6: 15 | BX6: 15 | BZ6: 0.493 | CA6: 0.493 | CB6: 头条放心购 | CC6: TOUTIAOFXG | CE6: 98.5 | CF6: =BD6-BP6 -> 1 | CG6: 159 | CH6: =_xlfn.XLOOKUP(AL6,抖音账单汇总!$A:$A,抖音账单汇总!$B:$B) -> 159
A7: 20037758 | B7: 发货后售后,小店,平台补贴,店铺新客,抖音,极速发货,直播间 | C7: 1226246815 | D7: 普通订单 | E7: 6923640314699284416 | G7: 已发货 | H7: 河北贝吉实业集团有限公司 | K7: 抖音-雪中飞德煌童装专卖店 | L7: 1@#PrdAaJ/c19AB08ja780iU+2EKC4MlXBj6RwsFAEr5mTfsiLF9a0L8/Z6wV/i7YQwMlBANg== | M7: 13125723 | O7: cp8 ，14点红云,(收) 新雾蓝;170I568114898700*1# | P7: 2026/1/16 11:46:42 | Q7: 2026/1/16 14:07:46 | R7: 2026/1/16 11:46:55 | S7: 2026/1/23 14:07:48 | T7: 2026/1/16 11:46:55 | U7: 安徽省 | V7: 合肥市 | W7: 肥东县 | X7: 圆通速递 | Y7: YT0006530080771 | Z7: 中通快递 | AA7: 73594118093819 | AB7: 147:王* | AC7: 2026/1/30 16:29:14 | AD7: 2026/2/2 13:41:17 | AE7: 2026-02-02 13:41:06 | AF7: 20009694 | AG7: 河北贝吉实业集团有限公司 | AH7: 普通退货 | AI7: 多拍/错拍/不想要 | AJ7: I568114898140 | AK7: 3787311554958066065 | AL7: 6923640314699284416 | AM7: X2501326322FXT | AP7: 儿童轻薄羽绒服 | AQ7: 新雾蓝;150 | AR7: 颜色分类:新雾蓝;尺码大小:150CM | AS7: 雪中飞 | AT7: 涛源 | AY7: 179 | AZ7: 86.7 | BA7: 普通商品资料成本价 | BB7: 1 | BD7: 1 | BE7: 179 | BF7: 179 | BG7: 86.7 | BH7: 86.7 | BI7: 92.3 | BJ7: 51.564% | BK7: 179 | BL7: 179 | BM7: 179 | BN7: 179 | BO7: 1 | BQ7: 179 | BR7: 86.7 | BU7: 0 | BW7: 3.6 | BX7: 3.6 | BZ7: 0.481 | CA7: 0.481 | CB7: 头条放心购 | CC7: TOUTIAOFXG | CE7: 98.2 | CF7: -1 | CG7: -179 | CH7: =_xlfn.XLOOKUP(AL7,抖音账单汇总!$A:$A,抖音账单汇总!$B:$B) -> -179
A8: 21076980 | B8: 小店,平台补贴,店铺老客,抖音极速版,直播间,高频购买 | D8: 普通订单 | E8: 6950742490609031071 | G8: 已发货 | H8: 河北贝吉实业集团有限公司 | K8: 抖音-雪中飞德煌童装专卖店 | L8: 1@#usS1WUSpN8Gr+E3nz4vYl/ls6EyPfg5JGJdJ29emjx9c7t8LmLuzMSszNjg+9i2lOGrG | M8: 13866300 | P8: 2026/2/14 12:37:53 | Q8: 2026/2/14 15:59:08 | R8: 2026/2/14 12:38:02 | S8: 2026/2/21 15:59:10 | T8: 2026/2/14 12:38:02 | U8: 安徽省 | V8: 芜湖市 | W8: 弋江区 | X8: 京东快递 | Y8: JDAZ23838272891 | AB8: 147:鲍* | AJ8: I568150018700 | AK8: 3787311554958066065 | AL8: 6950742490609031071 | AM8: X2501326322FXT | AP8: 儿童轻薄羽绒服 | AQ8: 橄榄绿;170 | AR8: 颜色分类:橄榄绿;尺码大小:170CM | AS8: 雪中飞 | AT8: 涛源 | AY8: 179 | AZ8: 86.7 | BA8: 普通商品资料成本价 | BB8: 1 | BD8: 1 | BE8: 179 | BF8: 179 | BG8: 86.7 | BH8: 86.7 | BI8: 92.3 | BJ8: 51.564% | BK8: 179 | BL8: 179 | BM8: 179 | BN8: 179 | BU8: 0 | BW8: 15 | BX8: 15 | BZ8: 0.537 | CA8: 0.537 | CB8: 头条放心购 | CC8: TOUTIAOFXG | CE8: 98.2 | CF8: =BD8-BP8 -> 1 | CG8: 179 | CH8: =_xlfn.XLOOKUP(AL8,抖音账单汇总!$A:$A,抖音账单汇总!$B:$B) -> 179
A9: 20037758 | B9: 发货后售后,小店,平台补贴,店铺新客,抖音,极速发货,直播间 | C9: 1226246815 | D9: 普通订单 | E9: 6923640314699284416 | G9: 已发货 | H9: 河北贝吉实业集团有限公司 | K9: 抖音-雪中飞德煌童装专卖店 | L9: 1@#PrdAaJ/c19AB08ja780iU+2EKC4MlXBj6RwsFAEr5mTfsiLF9a0L8/Z6wV/i7YQwMlBANg== | O9: cp8 ，14点红云,(收) 新雾蓝;170I568114898700*1# | P9: 2026/1/16 11:46:42 | Q9: 2026/1/16 14:07:46 | R9: 2026/1/16 11:46:55 | U9: 安徽省 | V9: 合肥市 | W9: 肥东县 | X9: 圆通速递 | Y9: YT0006530080771 | Z9: 中通快递 | AA9: 73594118093819 | AB9: 147:王* | AC9: 2026/1/30 16:29:14 | AD9: 2026/2/2 13:41:17 | AE9: 2026-02-02 13:41:06 | AF9: 20009694 | AG9: 河北贝吉实业集团有限公司 | AH9: 普通退货 | AI9: 多拍/错拍/不想要 | AJ9: I568114898700 | AL9: 6923640314699284416 | AM9: X2501326322FXT | AP9: 儿童轻薄羽绒服 | AQ9: 新雾蓝;170 | AR9: 新雾蓝;170 | AS9: 雪中飞 | AT9: 涛源 | AY9: 179 | AZ9: 86.7 | BF9: 0 | BJ9: 0.000% | BP9: 1 | BS9: 86.7 | CB9: 头条放心购 | CE9: 98.2 | CF9: 0 | CG9: 0 | CH9: =_xlfn.XLOOKUP(AL9,抖音账单汇总!$A:$A,抖音账单汇总!$B:$B) -> -179
A10: 21070645 | B10: 小店,店铺新客,抖音,服务优先,高频购买 | D10: 普通订单 | E10: 6950728574875866280 | G10: 已发货 | H10: 河北贝吉实业集团有限公司 | K10: 抖音-雪中飞德煌童装专卖店 | L10: 1@#xprY5As0/CxBKVAfxt5eb4lnRFJ0GpmwEg6p3VoKFyRZ4XhZh2JxQClUz7LXq5qalHJox0WFldo= | M10: 13885768 | P10: 2026/2/13 3:57:17 | Q10: 2026/2/13 10:29:28 | R10: 2026/2/13 3:57:19 | S10: 2026/2/20 10:29:29 | T10: 2026/2/13 3:57:19 | U10: 重庆 | V10: 重庆市 | W10: 沙坪坝区 | X10: 京东快递 | Y10: JDAZ23813768295 | AB10: 147:唐* | AJ10: I568150018700 | AK10: 3779048132244013371 | AL10: 6950728574875866280 | AM10: X2501326322FXT | AP10: 儿童轻薄羽绒服 | AQ10: 橄榄绿;170 | AR10: 颜色分类:橄榄绿;尺码大小:170CM | AS10: 雪中飞 | AT10: 涛源 | AY10: 179 | AZ10: 86.7 | BA10: 普通商品资料成本价 | BB10: 1 | BD10: 1 | BE10: 179 | BF10: 179 | BG10: 86.7 | BH10: 86.7 | BI10: 92.3 | BJ10: 51.564% | BK10: 179 | BL10: 179 | BM10: 179 | BN10: 179 | BU10: 0 | BW10: 15 | BX10: 15 | BZ10: 0.537 | CA10: 0.537 | CB10: 头条放心购 | CC10: TOUTIAOFXG | CE10: 98.2 | CF10: =BD10-BP10 -> 1 | CG10: 179 | CH10: =_xlfn.XLOOKUP(AL10,抖音账单汇总!$A:$A,抖音账单汇总!$B:$B) -> 179
A11: 21070327 | B11: 小店,平台补贴,店铺新客,抖音,高频购买 | D11: 普通订单 | E11: 6924337955066903674 | G11: 已发货 | H11: 河北贝吉实业集团有限公司 | K11: 抖音-雪中飞德煌童装专卖店 | L11: 1@#2eYD5mOtYnQnwRgpwcEto09eBSrU/62fitXuSHze5rnewguX2BACXZ2+p/oqXHduA3YW | M11: 13850164 | P11: 2026/2/13 0:30:15 | Q11: 2026/2/13 10:11:06 | R11: 2026/2/13 0:30:30 | S11: 2026/2/20 10:11:11 | T11: 2026/2/13 0:30:30 | U11: 湖南省 | V11: 常德市 | W11: 鼎城区 | X11: 京东快递 | Y11: JDAZ23813829585 | AB11: 147:许* | AJ11: I568150018252 | AK11: 3779048132244013371 | AL11: 6924337955066903674 | AM11: X2501326322FXT | AP11: 儿童轻薄羽绒服 | AQ11: 橄榄绿;110 | AR11: 颜色分类:橄榄绿;尺码大小:110CM | AS11: 雪中飞 | AT11: 涛源 | AY11: 179 | AZ11: 86.7 | BA11: 普通商品资料成本价 | BB11: 1 | BD11: 1 | BE11: 179 | BF11: 179 | BG11: 86.7 | BH11: 86.7 | BI11: 92.3 | BJ11: 51.564% | BK11: 179 | BL11: 179 | BM11: 179 | BN11: 179 | BU11: 0 | BW11: 15 | BX11: 15 | BZ11: 0.36 | CA11: 0.36 | CB11: 头条放心购 | CC11: TOUTIAOFXG | CE11: 98.2 | CF11: =BD11-BP11 -> 1 | CG11: 179 | CH11: =_xlfn.XLOOKUP(AL11,抖音账单汇总!$A:$A,抖音账单汇总!$B:$B) -> 179
A12: 21069880 | B12: 小店,店铺新客,抖音,高频购买 | D12: 普通订单 | E12: 6950735723996321284 | G12: 已发货 | H12: 河北贝吉实业集团有限公司 | K12: 抖音-雪中飞德煌童装专卖店 | L12: 1@#g5MLuOx4qSHSIr71V4yoBqFTjGEPD1qVTEZb63/8yZOTRYKTJ4zQh2XkoS0l9isHERwCqn9ytP4= | M12: 13885096 | P12: 2026/2/12 23:20:20 | Q12: 2026/2/13 10:29:26 | R12: 2026/2/12 23:20:28 | S12: 2026/2/20 10:29:29 | T12: 2026/2/12 23:20:28 | U12: 河南省 | V12: 周口市 | W12: 商水县 | X12: 京东快递 | Y12: JDAZ23813815879 | AB12: 147:武* | AJ12: I568150018700 | AK12: 3787311554958066065 | AL12: 6950735723996321284 | AM12: X2501326322FXT | AP12: 儿童轻薄羽绒服 | AQ12: 橄榄绿;170 | AR12: 颜色分类:橄榄绿;尺码大小:170CM | AS12: 雪中飞 | AT12: 涛源 | AY12: 179 | AZ12: 86.7 | BA12: 普通商品资料成本价 | BB12: 1 | BD12: 1 | BE12: 179 | BF12: 179 | BG12: 86.7 | BH12: 86.7 | BI12: 92.3 | BJ12: 51.564% | BK12: 179 | BL12: 179 | BM12: 179 | BN12: 179 | BU12: 0 | BW12: 15 | BX12: 15 | BZ12: 0.537 | CA12: 0.537 | CB12: 头条放心购 | CC12: TOUTIAOFXG | CE12: 98.2 | CF12: =BD12-BP12 -> 1 | CG12: 179 | CH12: =_xlfn.XLOOKUP(AL12,抖音账单汇总!$A:$A,抖音账单汇总!$B:$B) -> 179
A13: 21068764 | B13: 小店,店铺新客,抖音,高频购买 | D13: 普通订单 | E13: 6950719343804749677 | G13: 已发货 | H13: 河北贝吉实业集团有限公司 | K13: 抖音-雪中飞德煌童装专卖店 | L13: 1@#+j8NsD5qsCReOUshndIinM9Opo2LWXKOJ/H10yf5nTXTQoYqizxKSBQqIwfe+6/RKIZ2NA== | M13: 13884280 | P13: 2026/2/12 20:48:46 | Q13: 2026/2/13 11:01:50 | R13: 2026/2/12 20:49:09 | S13: 2026/2/20 11:01:52 | T13: 2026/2/12 20:49:09 | U13: 湖南省 | V13: 衡阳市 | W13: 衡东县 | X13: 京东快递 | Y13: JDAZ23813829576 | AB13: 147:龙* | AJ13: I568150018600 | AK13: 3779048132244013371 | AL13: 6950719343804749677 | AM13: X2501326322FXT | AP13: 儿童轻薄羽绒服 | AQ13: 橄榄绿;160 | AR13: 颜色分类:橄榄绿;尺码大小:160CM | AS13: 雪中飞 | AT13: 涛源 | AY13: 179 | AZ13: 86.7 | BA13: 普通商品资料成本价 | BB13: 1 | BD13: 1 | BE13: 179 | BF13: 179 | BG13: 86.7 | BH13: 86.7 | BI13: 92.3 | BJ13: 51.564% | BK13: 179 | BL13: 179 | BM13: 179 | BN13: 179 | BU13: 0 | BW13: 15 | BX13: 15 | BZ13: 0.506 | CA13: 0.506 | CB13: 头条放心购 | CC13: TOUTIAOFXG | CE13: 98.2 | CF13: =BD13-BP13 -> 1 | CG13: 179 | CH13: =_xlfn.XLOOKUP(AL13,抖音账单汇总!$A:$A,抖音账单汇总!$B:$B) -> 179
A14: 21068046 | B14: 小店,店铺新客,抖音,服务优先,直播间 | D14: 普通订单 | E14: 6950739525784048859 | G14: 已发货 | H14: 河北贝吉实业集团有限公司 | K14: 抖音-雪中飞德煌童装专卖店 | L14: 1@#KBXQLJN7CoL9lgCw5yOGnqe/CgB1tjAxi2+vFLAJNqmkOq04csDO49Bhjwp37mo2dffqF07ZHw== | M14: 13883713 | P14: 2026/2/12 18:32:55 | Q14: 2026/2/13 11:10:56 | R14: 2026/2/12 18:33:03 | S14: 2026/2/20 11:10:59 | T14: 2026/2/12 18:33:03 | U14: 湖北省 | V14: 黄冈市 | W14: 英山县 | X14: 京东快递 | Y14: JDAZ23813790499 | AB14: 147:伍* | AJ14: H493814417402 | AK14: 3787311554958066065 | AL14: 6950739525784048859 | AM14: X250138240FXT | AN14: 羽绒服 | AP14: 儿童轻薄羽绒服 | AQ14: 黑色;140 | AR14: 颜色分类:黑色（8240款）;尺码大小:140CM | AS14: 雪中飞 | AT14: 茸淳羽绒 | AW14: 每日加权 | AY14: 179 | AZ14: 87 | BA14: 普通商品资料成本价 | BB14: 1 | BD14: 1 | BE14: 159 | BF14: 159 | BG14: 87 | BH14: 87 | BI14: 72 | BJ14: 45.283% | BK14: 159 | BL14: 159 | BM14: 159 | BN14: 159 | BU14: 0 | BW14: 15 | BX14: 15 | BZ14: 0.4655 | CA14: 0.4655 | CB14: 头条放心购 | CC14: TOUTIAOFXG | CE14: 98.5 | CF14: =BD14-BP14 -> 1 | CG14: 159 | CH14: =_xlfn.XLOOKUP(AL14,抖音账单汇总!$A:$A,抖音账单汇总!$B:$B) -> 159
A15: 21067952 | B15: 小店,店铺新客,抖音,直播间,高频购买 | D15: 普通订单 | E15: 6950725986157138995 | G15: 已发货 | H15: 河北贝吉实业集团有限公司 | K15: 抖音-雪中飞德煌童装专卖店 | L15: 1@#P1I6Sq+B3fkweBiXZ2UZc3ZRaXi1D71WLGlf9neQPJU2/4ynlZCk+0jSI+Z4F1UUeS/H | M15: 13883640 | P15: 2026/2/12 18:12:20 | Q15: 2026/2/13 10:29:34 | R15: 2026/2/12 18:12:21 | S15: 2026/2/20 10:29:35 | T15: 2026/2/12 18:12:21 | U15: 甘肃省 | V15: 庆阳市 | W15: 西峰区 | X15: 京东快递 | Y15: JDAZ23813790462 | AB15: 147:杨* | AJ15: I568150018700 | AK15: 3787311554958066065 | AL15: 6950725986157138995 | AM15: X2501326322FXT | AP15: 儿童轻薄羽绒服 | AQ15: 橄榄绿;170 | AR15: 颜色分类:橄榄绿;尺码大小:170CM | AS15: 雪中飞 | AT15: 涛源 | AY15: 179 | AZ15: 86.7 | BA15: 普通商品资料成本价 | BB15: 1 | BD15: 1 | BE15: 179 | BF15: 179 | BG15: 86.7 | BH15: 86.7 | BI15: 92.3 | BJ15: 51.564% | BK15: 179 | BL15: 179 | BM15: 179 | BN15: 179 | BU15: 0 | BW15: 15 | BX15: 15 | BZ15: 0.537 | CA15: 0.537 | CB15: 头条放心购 | CC15: TOUTIAOFXG | CE15: 98.2 | CF15: =BD15-BP15 -> 1 | CG15: 179 | CH15: =_xlfn.XLOOKUP(AL15,抖音账单汇总!$A:$A,抖音账单汇总!$B:$B) -> 179
A16: 20053626 | B16: 优先发货,发货后售后,小店,平台补贴,店铺新客,抖音,直播间,高频购买 | C16: 1226358737 | D16: 普通订单 | E16: 6923661839766748780 | G16: 已发货 | H16: 河北贝吉实业集团有限公司 | K16: 抖音-雪中飞德煌童装专卖店 | L16: 1@#QqH0gZYSdwx+A/cCDRAmn0118Gv7ryEGvA/bSREMrUboeTvhz4tjgOwv2CQsXOKnfGFD | M16: 13136948 | O16: cp8不评 ，15点红云,(收) 橄榄绿;160I568150018600*1# | P16: 2026/1/16 20:12:32 | Q16: 2026/1/17 8:48:46 | R16: 2026/1/16 20:12:33 | S16: 2026/1/24 8:48:47 | T16: 2026/1/16 20:12:33 | U16: 河北省 | V16: 邢台市 | W16: 宁晋县 | X16: 圆通速递 | Y16: YT0006642273225 | Z16: 中通快递 | AA16: 73595104410153 | AB16: 147:铱* | AC16: 2026/2/5 1:02:08 | AD16: 2026/2/10 13:44:47 | AE16: 2026-02-10 13:44:41 | AF16: 20243528 | AG16: 河北贝吉实业集团有限公司 | AH16: 普通退货 | AI16: 多拍/错拍/不想要 | AJ16: I568150018140 | AK16: 3787311554958066065 | AL16: 6923661839766748780 | AM16: X2501326322FXT | AP16: 儿童轻薄羽绒服 | AQ16: 橄榄绿;150 | AR16: 颜色分类:橄榄绿;尺码大小:150CM | AS16: 雪中飞 | AT16: 涛源 | AY16: 179 | AZ16: 86.7 | BA16: 普通商品资料成本价 | BB16: 1 | BD16: 1 | BE16: 179 | BF16: 179 | BG16: 86.7 | BH16: 86.7 | BI16: 92.3 | BJ16: 51.564% | BK16: 179 | BL16: 179 | BM16: 179 | BN16: 179 | BO16: 1 | BQ16: 179 | BR16: 86.7 | BU16: 0 | BW16: 3.6 | BX16: 3.6 | BZ16: 0.481 | CA16: 0.481 | CB16: 头条放心购 | CC16: TOUTIAOFXG | CE16: 98.2 | CF16: -1 | CG16: -179 | CH16: =_xlfn.XLOOKUP(AL16,抖音账单汇总!$A:$A,抖音账单汇总!$B:$B) -> -179
A17: 21067210 | B17: 小店,平台补贴,店铺新客,抖音,极速发货,直播间,高频购买 | D17: 普通订单 | E17: 6950735340405658797 | G17: 已发货 | H17: 河北贝吉实业集团有限公司 | K17: 抖音-雪中飞德煌童装专卖店 | L17: 1@#4Z+yBV4Qyscp/oBBgBga25Vc598Uxt9s2OLax8K+drEsD+TXHQqXD3vTsMfxGDlzOX6baVSKP9Q= | M17: 13883118 | P17: 2026/2/12 16:13:12 | Q17: 2026/2/12 17:20:05 | R17: 2026/2/12 16:13:13 | S17: 2026/2/19 17:20:06 | T17: 2026/2/12 16:13:13 | U17: 河南省 | V17: 安阳市 | W17: 文峰区 | X17: 京东快递 | Y17: JDAZ23804663869 | AB17: 147:王* | AJ17: H493814417140 | AK17: 3787311554958066065 | AL17: 6950735340405658797 | AM17: X250138240FXT | AN17: 羽绒服 | AP17: 儿童轻薄羽绒服 | AQ17: 黑色;150 | AR17: 颜色分类:黑色（8240款）;尺码大小:150CM | AS17: 雪中飞 | AT17: 茸淳羽绒 | AW17: 每日加权 | AY17: 179 | AZ17: 87 | BA17: 普通商品资料成本价 | BB17: 1 | BD17: 1 | BE17: 159 | BF17: 159 | BG17: 87 | BH17: 87 | BI17: 72 | BJ17: 45.283% | BK17: 159 | BL17: 159 | BM17: 159 | BN17: 159 | BU17: 0 | BW17: 15 | BX17: 15 | BZ17: 0.493 | CA17: 0.493 | CB17: 头条放心购 | CC17: TOUTIAOFXG | CE17: 98.5 | CF17: =BD17-BP17 -> 1 | CG17: 159 | CH17: =_xlfn.XLOOKUP(AL17,抖音账单汇总!$A:$A,抖音账单汇总!$B:$B) -> 159
A18: 21067198 | B18: 发货后售后,小店,店铺新客,抖音,服务优先,极速发货,直播间,高频购买 | D18: 普通订单 | E18: 6924354549235416269 | G18: 已发货 | H18: 河北贝吉实业集团有限公司 | K18: 抖音-雪中飞德煌童装专卖店 | L18: 1@#0TRxVML4T67csFMl47CIoVSgSohi0ou6gPxwZdnX+ihZvhhZuEQEWM+z1wwAUdiLqMDB | M18: 13883107 | O18: (收) 颜色分类:橄榄绿;尺码大小:140cmI568150018402*1# | P18: 2026/2/12 16:11:02 | Q18: 2026/2/12 17:17:33 | R18: 2026/2/12 16:11:03 | S18: 2026/2/15 13:17:08 | T18: 2026/2/12 16:11:03 | U18: 四川省 | V18: 成都市 | W18: 新都区 | X18: 京东快递 | Y18: JDAZ23804750656 | AB18: 147:汪* | AJ18: I568150018402 | AK18: 3787311554958066065 | AL18: 6924354549235416269 | AM18: X2501326322FXT | AP18: 儿童轻薄羽绒服 | AQ18: 橄榄绿;140 | AR18: 颜色分类:橄榄绿;尺码大小:140CM | AS18: 雪中飞 | AT18: 涛源 | AY18: 179 | AZ18: 86.7 | BA18: 普通商品资料成本价 | BB18: 1 | BD18: 1 | BE18: 179 | BF18: 179 | BG18: 86.7 | BH18: 86.7 | BI18: 92.3 | BJ18: 51.564% | BK18: 179 | BL18: 179 | BM18: 179 | BN18: 179 | BU18: 0 | BW18: 15 | BX18: 15 | BZ18: 0.456 | CA18: 0.456 | CB18: 头条放心购 | CC18: TOUTIAOFXG | CE18: 98.2 | CF18: =BD18-BP18 -> 1 | CG18: 179 | CH18: =_xlfn.XLOOKUP(AL18,抖音账单汇总!$A:$A,抖音账单汇总!$B:$B) -> 179
A19: 21067069 | B19: 小店,店铺新客,服务优先,极速发货,直播间,线上修改地址,高频购买 | D19: 普通订单 | E19: 6950733011866097255 | G19: 已发货 | H19: 河北贝吉实业集团有限公司 | K19: 抖音-雪中飞德煌童装专卖店 | L19: 1@#UdW2AvezOzHdIFPFBp0ZkxEZLuR2FPLB3A/wowgisAKw0Hva6YHsnv2Az+r/4YCWl1yxUuE+rNM= | M19: 13883005 | P19: 2026/2/12 15:54:03 | Q19: 2026/2/12 17:20:16 | R19: 2026/2/12 15:54:20 | S19: 2026/2/19 17:20:18 | T19: 2026/2/12 15:54:20 | U19: 河北省 | V19: 衡水市 | W19: 景县 | X19: 京东快递 | Y19: JDAZ23804698760 | AB19: 147:李* | AJ19: I568150018600 | AK19: 3787311554958066065 | AL19: 6950733011866097255 | AM19: X2501326322FXT | AP19: 儿童轻薄羽绒服 | AQ19: 橄榄绿;160 | AR19: 颜色分类:橄榄绿;尺码大小:160CM | AS19: 雪中飞 | AT19: 涛源 | AY19: 179 | AZ19: 86.7 | BA19: 普通商品资料成本价 | BB19: 1 | BD19: 1 | BE19: 179 | BF19: 179 | BG19: 86.7 | BH19: 86.7 | BI19: 92.3 | BJ19: 51.564% | BK19: 179 | BL19: 179 | BM19: 179 | BN19: 179 | BU19: 0 | BW19: 15 | BX19: 15 | BZ19: 0.506 | CA19: 0.506 | CB19: 头条放心购 | CC19: TOUTIAOFXG | CE19: 98.2 | CF19: =BD19-BP19 -> 1 | CG19: 179 | CH19: =_xlfn.XLOOKUP(AL19,抖音账单汇总!$A:$A,抖音账单汇总!$B:$B) -> 179
A20: 21066954 | B20: 小店,店铺新客,抖音极速版,直播间,线上修改地址,高频购买 | D20: 普通订单 | E20: 6924339630726282713 | G20: 已发货 | H20: 河北贝吉实业集团有限公司 | K20: 抖音-雪中飞德煌童装专卖店 | L20: 1@#PB5AZcZ/2+wXuvNVPLAT8CVsDq4oLjD5phzstM8VE/lN2WY3VwjbfFb3yw13D7UyJgyIVNu8yUo= | M20: 13882937 | P20: 2026/2/12 15:40:16 | Q20: 2026/2/12 16:24:42 | R20: 2026/2/12 15:40:30 | S20: 2026/2/19 16:24:44 | T20: 2026/2/12 15:40:30 | U20: 河南省 | V20: 商丘市 | W20: 柘城县 | X20: 京东快递 | Y20: JDAZ23803065479 | AB20: 147:吴* | AJ20: H598714417164 | AK20: 3787311554958066065 | AL20: 6924339630726282713 | AM20: X250138648FXT | AN20: 轻薄羽绒服 | AP20: 儿童轻薄羽绒服 | AQ20: 黑色;120 | AR20: 颜色分类:黑色（8648款）;尺码大小:120CM | AS20: 雪中飞 | AT20: 贝优 | AW20: 每日加权 | AY20: 179 | AZ20: 85.5 | BA20: 普通商品资料成本价 | BB20: 1 | BD20: 1 | BE20: 179 | BF20: 179 | BG20: 85.5 | BH20: 85.5 | BI20: 93.5 | BJ20: 52.235% | BK20: 179 | BL20: 179 | BM20: 179 | BN20: 179 | BU20: 0 | BW20: 15 | BX20: 15 | BZ20: 0.385 | CA20: 0.385 | CB20: 头条放心购 | CC20: TOUTIAOFXG | CE20: 97 | CF20: =BD20-BP20 -> 1 | CG20: 179 | CH20: =_xlfn.XLOOKUP(AL20,抖音账单汇总!$A:$A,抖音账单汇总!$B:$B) -> 179
A21: 21064680 | B21: 小店,店铺新客,抖音,服务优先,极速发货,直播间 | D21: 普通订单 | E21: 6950714426810242370 | G21: 已发货 | H21: 河北贝吉实业集团有限公司 | K21: 抖音-雪中飞德煌童装专卖店 | L21: 1@#/Txi9Y5TDAHjqnfA/bWCpWQWmOWXk1bxRjwEt3juduhij5HbLuyIUWM5kLB4HUBTd+Wh | M21: 13881244 | P21: 2026/2/12 10:53:49 | Q21: 2026/2/12 14:25:36 | R21: 2026/2/12 10:53:58 | S21: 2026/2/19 14:25:38 | T21: 2026/2/12 10:53:58 | U21: 四川省 | V21: 眉山市 | W21: 青神县 | X21: 京东快递 | Y21: JDAZ23799744126 | AB21: 147:文* | AJ21: I568150018140 | AK21: 3787311554958066065 | AL21: 6950714426810242370 | AM21: X2501326322FXT | AP21: 儿童轻薄羽绒服 | AQ21: 橄榄绿;150 | AR21: 颜色分类:橄榄绿;尺码大小:150CM | AS21: 雪中飞 | AT21: 涛源 | AY21: 179 | AZ21: 86.7 | BA21: 普通商品资料成本价 | BB21: 1 | BD21: 1 | BE21: 179 | BF21: 179 | BG21: 86.7 | BH21: 86.7 | BI21: 92.3 | BJ21: 51.564% | BK21: 179 | BL21: 179 | BM21: 179 | BN21: 179 | BU21: 0 | BW21: 15 | BX21: 15 | BZ21: 0.481 | CA21: 0.481 | CB21: 头条放心购 | CC21: TOUTIAOFXG | CE21: 98.2 | CF21: =BD21-BP21 -> 1 | CG21: 179 | CH21: =_xlfn.XLOOKUP(AL21,抖音账单汇总!$A:$A,抖音账单汇总!$B:$B) -> 179
A22: 21064565 | B22: 小店,店铺新客,抖音,服务优先,直播间 | D22: 普通订单 | E22: 6924333026177875241 | G22: 已发货 | H22: 河北贝吉实业集团有限公司 | K22: 抖音-雪中飞德煌童装专卖店 | L22: 1@#7bfqJnxLKOn+Z4I09thb22fDHiGhKbG9NqmwHpwGMDRXdwg2I3dcFYx/GA5zqgnE5GtRLQ== | M22: 13881174 | P22: 2026/2/12 10:41:55 | Q22: 2026/2/12 14:54:01 | R22: 2026/2/12 10:42:26 | S22: 2026/2/19 14:54:03 | T22: 2026/2/12 10:42:26 | U22: 江苏省 | V22: 常州市 | W22: 武进区 | X22: 京东快递 | Y22: JDAZ23799637052 | AB22: 147:许* | AJ22: I568150018700 | AK22: 3787311554958066065 | AL22: 6924333026177875241 | AM22: X2501326322FXT | AP22: 儿童轻薄羽绒服 | AQ22: 橄榄绿;170 | AR22: 颜色分类:橄榄绿;尺码大小:170CM | AS22: 雪中飞 | AT22: 涛源 | AY22: 179 | AZ22: 86.7 | BA22: 普通商品资料成本价 | BB22: 1 | BD22: 1 | BE22: 179 | BF22: 179 | BG22: 86.7 | BH22: 86.7 | BI22: 92.3 | BJ22: 51.564% | BK22: 179 | BL22: 179 | BM22: 179 | BN22: 179 | BU22: 0 | BW22: 15 | BX22: 15 | BZ22: 0.537 | CA22: 0.537 | CB22: 头条放心购 | CC22: TOUTIAOFXG | CE22: 98.2 | CF22: =BD22-BP22 -> 1 | CG22: 179 | CH22: =_xlfn.XLOOKUP(AL22,抖音账单汇总!$A:$A,抖音账单汇总!$B:$B) -> 179
A23: 21064561 | B23: 小店,店铺新客,抖音,极速发货,直播间 | D23: 普通订单 | E23: 6950743455072589518 | G23: 已发货 | H23: 河北贝吉实业集团有限公司 | K23: 抖音-雪中飞德煌童装专卖店 | L23: 1@#8MUr8M7J8XHPq9jZUKPQ/Sb7NYZyJgYM67FoRBC6UntKA4IqdPFdnz6xVh/1KP7U9VlroL758y8= | M23: 13881176 | P23: 2026/2/12 10:42:11 | Q23: 2026/2/12 14:24:05 | R23: 2026/2/12 10:42:15 | S23: 2026/2/19 14:24:06 | T23: 2026/2/12 10:42:15 | U23: 四川省 | V23: 达州市 | W23: 宣汉县 | X23: 京东快递 | Y23: JDAZ23799744071 | AB23: 147:爸* | AJ23: I568150018402 | AK23: 3787311554958066065 | AL23: 6950743455072589518 | AM23: X2501326322FXT | AP23: 儿童轻薄羽绒服 | AQ23: 橄榄绿;140 | AR23: 颜色分类:橄榄绿;尺码大小:140CM | AS23: 雪中飞 | AT23: 涛源 | AY23: 179 | AZ23: 86.7 | BA23: 普通商品资料成本价 | BB23: 1 | BD23: 1 | BE23: 179 | BF23: 179 | BG23: 86.7 | BH23: 86.7 | BI23: 92.3 | BJ23: 51.564% | BK23: 179 | BL23: 179 | BM23: 179 | BN23: 179 | BU23: 0 | BW23: 15 | BX23: 15 | BZ23: 0.456 | CA23: 0.456 | CB23: 头条放心购 | CC23: TOUTIAOFXG | CE23: 98.2 | CF23: =BD23-BP23 -> 1 | CG23: 179 | CH23: =_xlfn.XLOOKUP(AL23,抖音账单汇总!$A:$A,抖音账单汇总!$B:$B) -> 179
A24: 21064523 | B24: 小店,店铺新客,抖音,极速发货,直播间,高频购买 | D24: 普通订单 | E24: 6924341239823301947 | G24: 已发货 | H24: 河北贝吉实业集团有限公司 | K24: 抖音-雪中飞德煌童装专卖店 | L24: 1@#aWC+XDVok/b91foqffC2nz8CXpR3S0AZROSLrVSmxH0wYl9ZUPVPFxqTPVFz7P2H/+Tq | M24: 13881145 | P24: 2026/2/12 10:39:11 | Q24: 2026/2/12 14:24:27 | R24: 2026/2/12 10:39:13 | S24: 2026/2/19 14:24:30 | T24: 2026/2/12 10:39:13 | U24: 甘肃省 | V24: 平凉市 | W24: 静宁县 | X24: 京东快递 | Y24: JDAZ23799647150 | AB24: 147:唐* | AJ24: H493814417140 | AK24: 3787311554958066065 | AL24: 6924341239823301947 | AM24: X250138240FXT | AN24: 羽绒服 | AP24: 儿童轻薄羽绒服 | AQ24: 黑色;150 | AR24: 颜色分类:黑色（8240款）;尺码大小:150CM | AS24: 雪中飞 | AT24: 茸淳羽绒 | AW24: 每日加权 | AY24: 179 | AZ24: 87 | BA24: 普通商品资料成本价 | BB24: 1 | BD24: 1 | BE24: 159 | BF24: 159 | BG24: 87 | BH24: 87 | BI24: 72 | BJ24: 45.283% | BK24: 159 | BL24: 159 | BM24: 159 | BN24: 159 | BU24: 0 | BW24: 15 | BX24: 15 | BZ24: 0.493 | CA24: 0.493 | CB24: 头条放心购 | CC24: TOUTIAOFXG | CE24: 98.5 | CF24: =BD24-BP24 -> 1 | CG24: 159 | CH24: =_xlfn.XLOOKUP(AL24,抖音账单汇总!$A:$A,抖音账单汇总!$B:$B) -> 159
A25: 21064413 | B25: 小店,店铺新客,抖音,极速发货,直播间 | D25: 普通订单 | E25: 6924343450946141328 | G25: 已发货 | H25: 河北贝吉实业集团有限公司 | K25: 抖音-雪中飞德煌童装专卖店 | L25: 1@#tylngmqou5oBjV0Bs+W9m4PktvK6uNN2dCGfpaqv/ieWqaUufFuoWk57KbT8yzsklUiQ | M25: 13881065 | O25: hp反8【栀 03-02 10:56】 | P25: 2026/2/12 10:27:41 | Q25: 2026/2/12 14:25:24 | R25: 2026/2/12 10:27:45 | S25: 2026/2/19 14:25:25 | T25: 2026/2/12 10:27:45 | U25: 山东省 | V25: 济南市 | W25: 章丘区 | X25: 京东快递 | Y25: JDAZ23799629205 | AB25: 147:杨* | AJ25: I568150018140 | AK25: 3787311554958066065 | AL25: 6924343450946141328 | AM25: X2501326322FXT | AP25: 儿童轻薄羽绒服 | AQ25: 橄榄绿;150 | AR25: 颜色分类:橄榄绿;尺码大小:150CM | AS25: 雪中飞 | AT25: 涛源 | AY25: 179 | AZ25: 86.7 | BA25: 普通商品资料成本价 | BB25: 1 | BD25: 1 | BE25: 179 | BF25: 179 | BG25: 86.7 | BH25: 86.7 | BI25: 92.3 | BJ25: 51.564% | BK25: 179 | BL25: 179 | BM25: 179 | BN25: 179 | BU25: 0 | BW25: 15 | BX25: 15 | BZ25: 0.481 | CA25: 0.481 | CB25: 头条放心购 | CC25: TOUTIAOFXG | CE25: 98.2 | CF25: =BD25-BP25 -> 1 | CG25: 179 | CH25: =_xlfn.XLOOKUP(AL25,抖音账单汇总!$A:$A,抖音账单汇总!$B:$B) -> 179
A26: 21064094 | B26: 小店,店铺新客,抖音,服务优先,直播间,高频购买 | D26: 普通订单 | E26: 6924341217322696219 | G26: 已发货 | H26: 河北贝吉实业集团有限公司 | K26: 抖音-雪中飞德煌童装专卖店 | L26: 1@#9SkKjUZXzAg8RE5igbXGu+1tbG5EH7A65JQbTpqMF5fscDBP5Kx1ikCa04fJHqfLNmU9 | M26: 13880822 | P26: 2026/2/12 9:55:05 | Q26: 2026/2/12 14:25:17 | R26: 2026/2/12 9:55:07 | S26: 2026/2/19 14:25:21 | T26: 2026/2/12 9:55:07 | U26: 北京 | V26: 北京市 | W26: 海淀区 | X26: 京东快递 | Y26: JDAZ23799672260 | AB26: 147:月* | AJ26: I568150018140 | AK26: 3787311554958066065 | AL26: 6924341217322696219 | AM26: X2501326322FXT | AP26: 儿童轻薄羽绒服 | AQ26: 橄榄绿;150 | AR26: 颜色分类:橄榄绿;尺码大小:150CM | AS26: 雪中飞 | AT26: 涛源 | AY26: 179 | AZ26: 86.7 | BA26: 普通商品资料成本价 | BB26: 1 | BD26: 1 | BE26: 179 | BF26: 179 | BG26: 86.7 | BH26: 86.7 | BI26: 92.3 | BJ26: 51.564% | BK26: 179 | BL26: 179 | BM26: 179 | BN26: 179 | BU26: 0 | BW26: 15 | BX26: 15 | BZ26: 0.481 | CA26: 0.481 | CB26: 头条放心购 | CC26: TOUTIAOFXG | CE26: 98.2 | CF26: =BD26-BP26 -> 1 | CG26: 179 | CH26: =_xlfn.XLOOKUP(AL26,抖音账单汇总!$A:$A,抖音账单汇总!$B:$B) -> 179
A27: 21063992 | B27: 小店,店铺新客,抖音极速版,服务优先,极速发货,直播间,高频购买 | D27: 普通订单 | E27: 6924347572239629550 | G27: 已发货 | H27: 河北贝吉实业集团有限公司 | K27: 抖音-雪中飞德煌童装专卖店 | L27: 1@#jq0Ay/w86ur/DRaGwETF5W3fY1gtfn/CrYGkBS0ttDpkTBup/e6MJdUULrogUGyQpFfgEQ== | M27: 13880755 | P27: 2026/2/12 9:45:12 | Q27: 2026/2/12 15:18:21 | R27: 2026/2/12 9:45:16 | S27: 2026/2/19 15:18:23 | T27: 2026/2/12 9:45:16 | U27: 广西壮族自治区 | V27: 南宁市 | W27: 西乡塘区 | X27: 京东快递 | Y27: JDAZ23799703913 | AB27: 147:顺* | AJ27: I568150018600 | AK27: 3787311554958066065 | AL27: 6924347572239629550 | AM27: X2501326322FXT | AP27: 儿童轻薄羽绒服 | AQ27: 橄榄绿;160 | AR27: 颜色分类:橄榄绿;尺码大小:160CM | AS27: 雪中飞 | AT27: 涛源 | AY27: 179 | AZ27: 86.7 | BA27: 普通商品资料成本价 | BB27: 1 | BD27: 1 | BE27: 179 | BF27: 179 | BG27: 86.7 | BH27: 86.7 | BI27: 92.3 | BJ27: 51.564% | BK27: 179 | BL27: 179 | BM27: 179 | BN27: 179 | BU27: 0 | BW27: 15 | BX27: 15 | BZ27: 0.506 | CA27: 0.506 | CB27: 头条放心购 | CC27: TOUTIAOFXG | CE27: 98.2 | CF27: =BD27-BP27 -> 1 | CG27: 179 | CH27: =_xlfn.XLOOKUP(AL27,抖音账单汇总!$A:$A,抖音账单汇总!$B:$B) -> 179
A28: 21063883 | B28: 小店,平台补贴,店铺新客,抖音,极速发货,直播间,高频购买 | D28: 普通订单 | E28: 6950723299436991679 | G28: 已发货 | H28: 河北贝吉实业集团有限公司 | K28: 抖音-雪中飞德煌童装专卖店 | L28: 1@#5H5o07ydxX0gIH/xiDHrSxM7+JOX6vPsUH2hH07bjdeGDYFnmkYtOVRNWbJhNmR79uAI | M28: 13880679 | P28: 2026/2/12 9:36:22 | Q28: 2026/2/12 15:07:31 | R28: 2026/2/12 9:36:26 | S28: 2026/2/19 15:07:34 | T28: 2026/2/12 9:36:26 | U28: 湖北省 | V28: 黄冈市 | W28: 麻城市 | X28: 京东快递 | Y28: JDAZ23799647186 | AB28: 147:何* | AJ28: I568150018302 | AK28: 3787311554958066065 | AL28: 6950723299436991679 | AM28: X2501326322FXT | AP28: 儿童轻薄羽绒服 | AQ28: 橄榄绿;130 | AR28: 颜色分类:橄榄绿;尺码大小:130CM | AS28: 雪中飞 | AT28: 涛源 | AY28: 179 | AZ28: 86.7 | BA28: 普通商品资料成本价 | BB28: 1 | BD28: 1 | BE28: 179 | BF28: 179 | BG28: 86.7 | BH28: 86.7 | BI28: 92.3 | BJ28: 51.564% | BK28: 179 | BL28: 179 | BM28: 179 | BN28: 179 | BU28: 0 | BW28: 15 | BX28: 15 | BZ28: 0.419 | CA28: 0.419 | CB28: 头条放心购 | CC28: TOUTIAOFXG | CE28: 98.2 | CF28: =BD28-BP28 -> 1 | CG28: 179 | CH28: =_xlfn.XLOOKUP(AL28,抖音账单汇总!$A:$A,抖音账单汇总!$B:$B) -> 179
A29: 21063874 | B29: 小店,店铺老客,抖音极速版,消费者催发货,高频购买 | D29: 普通订单 | E29: 6924339142331891449 | G29: 已发货 | H29: 河北贝吉实业集团有限公司 | K29: 抖音-雪中飞德煌童装专卖店 | L29: 1@#HKjtaKoQ4doLbMWHOExpSRFJ4WropYDd1kThpAIQkRjiMXia2qTftab9H/Js6z7dYJdc | M29: 13880457 | P29: 2026/2/12 9:35:36 | Q29: 2026/2/12 15:17:53 | R29: 2026/2/12 9:35:50 | S29: 2026/2/16 20:55:11 | T29: 2026/2/12 9:35:50 | U29: 贵州省 | V29: 遵义市 | W29: 汇川区 | X29: 京东快递 | Y29: JDAZ23799637009 | AB29: 147:艳* | AJ29: I568150018600 | AK29: 3787311554958066065 | AL29: 6924339142331891449 | AM29: X2501326322FXT | AP29: 儿童轻薄羽绒服 | AQ29: 橄榄绿;160 | AR29: 颜色分类:橄榄绿;尺码大小:160CM | AS29: 雪中飞 | AT29: 涛源 | AY29: 179 | AZ29: 86.7 | BA29: 普通商品资料成本价 | BB29: 1 | BD29: 1 | BE29: 179 | BF29: 179 | BG29: 86.7 | BH29: 86.7 | BI29: 92.3 | BJ29: 51.564% | BK29: 179 | BL29: 179 | BM29: 179 | BN29: 179 | BU29: 0 | BW29: 15 | BX29: 15 | BZ29: 0.506 | CA29: 0.506 | CB29: 头条放心购 | CC29: TOUTIAOFXG | CE29: 98.2 | CF29: =BD29-BP29 -> 1 | CG29: 179 | CH29: =_xlfn.XLOOKUP(AL29,抖音账单汇总!$A:$A,抖音账单汇总!$B:$B) -> 179
A30: 21063775 | B30: 小店,平台补贴,店铺新客,服务优先,极速发货,直播间,高频购买 | D30: 普通订单 | E30: 6924347607424138364 | G30: 已发货 | H30: 河北贝吉实业集团有限公司 | K30: 抖音-雪中飞德煌童装专卖店 | L30: 1@#NuGvpqkvbQVwoh5Gk5E+nfMuWuL1s+s8rbO0mFH/QwhJaXVbNoD8vaawo2+Smad25bDURg== | M30: 13880545 | O30: hp8 【叙源 02-26 10:48】 | P30: 2026/2/12 9:15:18 | Q30: 2026/2/12 14:28:45 | R30: 2026/2/12 9:23:49 | S30: 2026/2/19 14:28:49 | T30: 2026/2/12 9:23:49 | U30: 河南省 | V30: 漯河市 | W30: 召陵区 | X30: 京东快递 | Y30: JDAZ23799671900 | AB30: 147:姚* | AJ30: I180852187700 | AK30: 3779552986313916499 | AL30: 6924347607424138364 | AM30: X2501324376FXT | AN30: 羽绒服 | AP30: 儿童轻薄羽绒服 | AQ30: 新嫩黄;170 | AR30: 颜色分类:新嫩黄;尺码大小:170 | AS30: 雪中飞 | AT30: 华衫 | AY30: 179 | AZ30: 76 | BA30: 普通商品资料成本价 | BB30: 1 | BD30: 1 | BE30: 179 | BF30: 179 | BG30: 76 | BH30: 76 | BI30: 103 | BJ30: 57.542% | BK30: 179 | BL30: 179 | BM30: 179 | BN30: 179 | BU30: 0 | BW30: 15 | BX30: 15 | BZ30: 0.488 | CA30: 0.488 | CB30: 头条放心购 | CC30: TOUTIAOFXG | CE30: 87.5 | CF30: =BD30-BP30 -> 1 | CG30: 179 | CH30: =_xlfn.XLOOKUP(AL30,抖音账单汇总!$A:$A,抖音账单汇总!$B:$B) -> 179
A31: 21063714 | B31: 小店,店铺新客,抖音,服务优先,极速发货,直播间,高频购买 | D31: 普通订单 | E31: 6924343325591305750 | G31: 已发货 | H31: 河北贝吉实业集团有限公司 | K31: 抖音-雪中飞德煌童装专卖店 | L31: 1@#ANen5HipxsFlcq8n3PGxMepIoMvXzgo/2geyi5k4zOfH5fDwhEIYHwfnMN8mjOo9ZnkFonu0f68= | M31: 13880547 | P31: 2026/2/12 9:15:44 | Q31: 2026/2/12 14:23:42 | R31: 2026/2/12 9:15:51 | S31: 2026/2/19 14:23:45 | T31: 2026/2/12 9:15:51 | U31: 湖北省 | V31: 宜昌市 | W31: 枝江市 | X31: 京东快递 | Y31: JDAZ23799671927 | AB31: 147:陈* | AJ31: I568150018402 | AK31: 3787311554958066065 | AL31: 6924343325591305750 | AM31: X2501326322FXT | AP31: 儿童轻薄羽绒服 | AQ31: 橄榄绿;140 | AR31: 颜色分类:橄榄绿;尺码大小:140CM | AS31: 雪中飞 | AT31: 涛源 | AY31: 179 | AZ31: 86.7 | BA31: 普通商品资料成本价 | BB31: 1 | BD31: 1 | BE31: 179 | BF31: 179 | BG31: 86.7 | BH31: 86.7 | BI31: 92.3 | BJ31: 51.564% | BK31: 179 | BL31: 179 | BM31: 179 | BN31: 179 | BU31: 0 | BW31: 15 | BX31: 15 | BZ31: 0.456 | CA31: 0.456 | CB31: 头条放心购 | CC31: TOUTIAOFXG | CE31: 98.2 | CF31: =BD31-BP31 -> 1 | CG31: 179 | CH31: =_xlfn.XLOOKUP(AL31,抖音账单汇总!$A:$A,抖音账单汇总!$B:$B) -> 179
A32: 21063712 | B32: 小店,平台补贴,店铺新客,抖音,极速发货,消费者催发货,直播间,线上修改地址,高频购买 | D32: 普通订单 | E32: 6950734975035840390 | G32: 已发货 | H32: 河北贝吉实业集团有限公司 | K32: 抖音-雪中飞德煌童装专卖店 | L32: 1@#O6poNV3ToZZoEKz9h5C5J3Qd7/C+OQjtp+IEDInx6SGdAp/dmTvVjRfExh/+JJ4r4aqs | M32: 13880540 | P32: 2026/2/12 9:15:08 | Q32: 2026/2/12 15:06:25 | R32: 2026/2/12 9:15:21 | S32: 2026/2/19 15:06:28 | T32: 2026/2/12 9:15:21 | U32: 安徽省 | V32: 亳州市 | W32: 蒙城县 | X32: 京东快递 | Y32: JDAZ23799629123 | AB32: 147:冯* | AJ32: I568150018302 | AK32: 3787311554958066065 | AL32: 6950734975035840390 | AM32: X2501326322FXT | AP32: 儿童轻薄羽绒服 | AQ32: 橄榄绿;130 | AR32: 颜色分类:橄榄绿;尺码大小:130CM | AS32: 雪中飞 | AT32: 涛源 | AY32: 179 | AZ32: 86.7 | BA32: 普通商品资料成本价 | BB32: 1 | BD32: 1 | BE32: 179 | BF32: 179 | BG32: 86.7 | BH32: 86.7 | BI32: 92.3 | BJ32: 51.564% | BK32: 179 | BL32: 179 | BM32: 179 | BN32: 179 | BU32: 0 | BW32: 15 | BX32: 15 | BZ32: 0.419 | CA32: 0.419 | CB32: 头条放心购 | CC32: TOUTIAOFXG | CE32: 98.2 | CF32: =BD32-BP32 -> 1 | CG32: 179 | CH32: =_xlfn.XLOOKUP(AL32,抖音账单汇总!$A:$A,抖音账单汇总!$B:$B) -> 179
A33: 21063600 | B33: 小店,店铺新客,极速发货,直播间,高频购买 | D33: 普通订单 | E33: 6924343311481535605 | G33: 已发货 | H33: 河北贝吉实业集团有限公司 | K33: 抖音-雪中飞德煌童装专卖店 | L33: 1@#s6MpDoOUAhLz4P9ynbsHB3yEOcAS7wI2ipo6s5PcjNTnMNiKTJKZfct7nK5/Ii3NvpaO | M33: 13877487 | P33: 2026/2/12 9:04:02 | Q33: 2026/2/12 14:24:43 | R33: 2026/2/12 9:04:23 | S33: 2026/2/19 14:24:44 | T33: 2026/2/12 9:04:23 | U33: 浙江省 | V33: 温州市 | W33: 瑞安市 | X33: 京东快递 | Y33: JDAZ23799704337 | AB33: 147:郭* | AJ33: I568150018140 | AK33: 3787311554958066065 | AL33: 6924343311481535605 | AM33: X2501326322FXT | AP33: 儿童轻薄羽绒服 | AQ33: 橄榄绿;150 | AR33: 颜色分类:橄榄绿;尺码大小:150CM | AS33: 雪中飞 | AT33: 涛源 | AY33: 179 | AZ33: 86.7 | BA33: 普通商品资料成本价 | BB33: 1 | BD33: 1 | BE33: 179 | BF33: 179 | BG33: 86.7 | BH33: 86.7 | BI33: 92.3 | BJ33: 51.564% | BK33: 179 | BL33: 179 | BM33: 179 | BN33: 179 | BU33: 0 | BW33: 15 | BX33: 15 | BZ33: 0.481 | CA33: 0.481 | CB33: 头条放心购 | CC33: TOUTIAOFXG | CE33: 98.2 | CF33: =BD33-BP33 -> 1 | CG33: 179 | CH33: =_xlfn.XLOOKUP(AL33,抖音账单汇总!$A:$A,抖音账单汇总!$B:$B) -> 179
A34: 21063599 | B34: 小店,已推送至供应商,店铺老客,抖音,直播间,高频购买 | D34: 普通订单,分销Plus | E34: 6924339128078401289 | G34: 已发货 | H34: ---- 未设定 ---- | K34: 抖音-雪中飞德煌童装专卖店 | L34: 1@#+OQ3mCftYUZ5vAw1VW6poGDpfFSHim0hdpuD1g84E9VhrlxrXUQ03kHjW8asHdCH8wrA | M34: 13821258 | P34: 2026/2/12 9:03:48 | Q34: 2026/2/12 17:14:14 | R34: 2026/2/12 9:04:04 | S34: 2026/2/19 17:14:17 | T34: 2026/2/12 9:04:04 | U34: 安徽省 | V34: 宣城市 | W34: 宣州区 | X34: 无极圆通速递公司 | Y34: YT0014766044546 | AB34: 147:王* | AJ34: I687051663823 | AK34: 3802578368348685236 | AL34: 6924339128078401289 | AM34: X2509329934FXT | AP34: 儿童裤子 | AQ34: 浅花灰;130 | AR34: 颜色分类:浅花灰;尺码大小:130 | AS34: 雪中飞 | AT34: 咔咔商贸 | AY34: 109 | AZ34: 40 | BA34: 分销单成本价 | BB34: 1 | BD34: 0 | BF34: 69.9 | BG34: 40 | BI34: 29.9 | BJ34: 42.775% | BK34: 69.9 | BL34: 69.9 | BM34: 69.9 | BN34: 69.9 | BU34: 0 | BZ34: 0 | CA34: 0 | CB34: 头条放心购 | CC34: TOUTIAOFXG | CF34: 1 | CG34: 69.9 | CH34: =_xlfn.XLOOKUP(AL34,抖音账单汇总!$A:$A,抖音账单汇总!$B:$B) -> 69.9
A35: 21063319 | B35: 发货后售后,小店,店铺新客,抖音极速版,直播间,高频购买 | D35: 普通订单 | E35: 6924347547891629873 | G35: 已发货 | H35: 河北贝吉实业集团有限公司 | K35: 抖音-雪中飞德煌童装专卖店 | L35: 1@#/hzCOxARPyqF6J75lPj9gVitCPQj5BzjmvQm2uaS4UrvtzznnTx78bP16wVLHdFEnSCl | M35: 13880285 | O35: (收) 颜色分类:橄榄绿;尺码大小:160cmI568150018600*1# | P35: 2026/2/12 8:42:13 | Q35: 2026/2/12 9:42:34 | R35: 2026/2/12 8:42:28 | S35: 2026/2/19 9:42:36 | T35: 2026/2/12 8:42:28 | U35: 江西省 | V35: 上饶市 | W35: 广丰区 | X35: 京东快递 | Y35: JDAZ23788744101 | AB35: 147:夏* | AJ35: I568150018600 | AK35: 3787311554958066065 | AL35: 6924347547891629873 | AM35: X2501326322FXT | AP35: 儿童轻薄羽绒服 | AQ35: 橄榄绿;160 | AR35: 颜色分类:橄榄绿;尺码大小:160CM | AS35: 雪中飞 | AT35: 涛源 | AY35: 179 | AZ35: 86.7 | BA35: 普通商品资料成本价 | BB35: 1 | BD35: 1 | BE35: 179 | BF35: 179 | BG35: 86.7 | BH35: 86.7 | BI35: 92.3 | BJ35: 51.564% | BK35: 179 | BL35: 179 | BM35: 179 | BN35: 179 | BU35: 0 | BW35: 15 | BX35: 15 | BZ35: 0.506 | CA35: 0.506 | CB35: 头条放心购 | CC35: TOUTIAOFXG | CE35: 98.2 | CF35: =BD35-BP35 -> 1 | CG35: 179 | CH35: =_xlfn.XLOOKUP(AL35,抖音账单汇总!$A:$A,抖音账单汇总!$B:$B) -> 179
A36: 21063153 | B36: 小店,平台补贴,店铺新客,抖音,服务优先,直播间 | D36: 普通订单 | E36: 6924332881092050522 | G36: 已发货 | H36: 河北贝吉实业集团有限公司 | K36: 抖音-雪中飞德煌童装专卖店 | L36: 1@#/nyQO3TpZ4bVtvFrFqqcaVOC7VftH7K7QBLPmR4g6BbwgGBDVh7BDuL/o2ErS2Lz0un2 | M36: 13880163 | P36: 2026/2/12 8:24:59 | Q36: 2026/2/12 9:39:40 | R36: 2026/2/12 8:25:00 | S36: 2026/2/17 2:39:00 | T36: 2026/2/12 8:25:00 | U36: 浙江省 | V36: 宁波市 | W36: 慈溪市 | X36: 京东快递 | Y36: JDAZ23788771317 | AB36: 147:高* | AJ36: I568150018140 | AK36: 3787311554958066065 | AL36: 6924332881092050522 | AM36: X2501326322FXT | AP36: 儿童轻薄羽绒服 | AQ36: 橄榄绿;150 | AR36: 颜色分类:橄榄绿;尺码大小:150CM | AS36: 雪中飞 | AT36: 涛源 | AY36: 179 | AZ36: 86.7 | BA36: 普通商品资料成本价 | BB36: 1 | BD36: 1 | BE36: 179 | BF36: 179 | BG36: 86.7 | BH36: 86.7 | BI36: 92.3 | BJ36: 51.564% | BK36: 179 | BL36: 179 | BM36: 179 | BN36: 179 | BU36: 0 | BW36: 15 | BX36: 15 | BZ36: 0.481 | CA36: 0.481 | CB36: 头条放心购 | CC36: TOUTIAOFXG | CE36: 98.2 | CF36: =BD36-BP36 -> 1 | CG36: 179 | CH36: =_xlfn.XLOOKUP(AL36,抖音账单汇总!$A:$A,抖音账单汇总!$B:$B) -> 179
A37: 21063118 | B37: 小店,店铺新客,服务优先,直播间,高频购买 | D37: 普通订单 | E37: 6924341080710676024 | G37: 已发货 | H37: 河北贝吉实业集团有限公司 | K37: 抖音-雪中飞德煌童装专卖店 | L37: 1@#GBCw9afG+9k3s+BMlhO9hCUbrown/ImoCDWzEyoJGv/dkA2EKArDZPBBEnPZ/kbPR9s/ | M37: 13880134 | P37: 2026/2/12 8:21:15 | Q37: 2026/2/12 9:41:49 | R37: 2026/2/12 8:21:18 | S37: 2026/2/19 9:41:52 | T37: 2026/2/12 8:21:18 | U37: 安徽省 | V37: 合肥市 | W37: 庐阳区 | X37: 京东快递 | Y37: JDAZ23788906766 | AB37: 147:潘* | AJ37: I568150018600 | AK37: 3787311554958066065 | AL37: 6924341080710676024 | AM37: X2501326322FXT | AP37: 儿童轻薄羽绒服 | AQ37: 橄榄绿;160 | AR37: 颜色分类:橄榄绿;尺码大小:160CM | AS37: 雪中飞 | AT37: 涛源 | AY37: 179 | AZ37: 86.7 | BA37: 普通商品资料成本价 | BB37: 1 | BD37: 1 | BE37: 179 | BF37: 179 | BG37: 86.7 | BH37: 86.7 | BI37: 92.3 | BJ37: 51.564% | BK37: 179 | BL37: 179 | BM37: 179 | BN37: 179 | BU37: 0 | BW37: 15 | BX37: 15 | BZ37: 0.506 | CA37: 0.506 | CB37: 头条放心购 | CC37: TOUTIAOFXG | CE37: 98.2 | CF37: =BD37-BP37 -> 1 | CG37: 179 | CH37: =_xlfn.XLOOKUP(AL37,抖音账单汇总!$A:$A,抖音账单汇总!$B:$B) -> 179
A38: 21063053 | B38: 小店,平台补贴,店铺新客,抖音,直播间 | D38: 普通订单 | E38: 6950716683855336632 | G38: 已发货 | H38: 河北贝吉实业集团有限公司 | K38: 抖音-雪中飞德煌童装专卖店 | L38: 1@#kTFpqAXjBPv2RMUFBNkUWfnBibatO4X/ib8sFNhlvuQ/jpXYfHcigCweBUQG+SfvsZJZ7VTcDxI= | M38: 13847098 | P38: 2026/2/12 8:13:33 | Q38: 2026/2/12 11:14:55 | R38: 2026/2/12 8:13:40 | S38: 2026/2/19 11:14:58 | T38: 2026/2/12 8:13:40 | U38: 陕西省 | V38: 榆林市 | W38: 横山区 | X38: 京东快递 | Y38: JDAZ23788835648 | AB38: 147:尉* | AJ38: I568150018302 | AK38: 3787311554958066065 | AL38: 6950716683855336632 | AM38: X2501326322FXT | AP38: 儿童轻薄羽绒服 | AQ38: 橄榄绿;130 | AR38: 颜色分类:橄榄绿;尺码大小:130CM | AS38: 雪中飞 | AT38: 涛源 | AY38: 179 | AZ38: 86.7 | BA38: 普通商品资料成本价 | BB38: 1 | BD38: 1 | BE38: 179 | BF38: 179 | BG38: 86.7 | BH38: 86.7 | BI38: 92.3 | BJ38: 51.564% | BK38: 179 | BL38: 179 | BM38: 179 | BN38: 179 | BU38: 0 | BW38: 15 | BX38: 15 | BZ38: 0.419 | CA38: 0.419 | CB38: 头条放心购 | CC38: TOUTIAOFXG | CE38: 98.2 | CF38: =BD38-BP38 -> 1 | CG38: 179 | CH38: =_xlfn.XLOOKUP(AL38,抖音账单汇总!$A:$A,抖音账单汇总!$B:$B) -> 179
A39: 20053626 | B39: 优先发货,发货后售后,小店,平台补贴,店铺新客,抖音,直播间,高频购买 | C39: 1226358737 | D39: 普通订单 | E39: 6923661839766748780 | G39: 已发货 | H39: 河北贝吉实业集团有限公司 | K39: 抖音-雪中飞德煌童装专卖店 | L39: 1@#QqH0gZYSdwx+A/cCDRAmn0118Gv7ryEGvA/bSREMrUboeTvhz4tjgOwv2CQsXOKnfGFD | O39: cp8不评 ，15点红云,(收) 橄榄绿;160I568150018600*1# | P39: 2026/1/16 20:12:32 | Q39: 2026/1/17 8:48:46 | R39: 2026/1/16 20:12:33 | U39: 河北省 | V39: 邢台市 | W39: 宁晋县 | X39: 圆通速递 | Y39: YT0006642273225 | Z39: 中通快递 | AA39: 73595104410153 | AB39: 147:铱* | AC39: 2026/2/5 1:02:08 | AD39: 2026/2/10 13:44:47 | AE39: 2026-02-10 13:44:41 | AF39: 20243528 | AG39: 河北贝吉实业集团有限公司 | AH39: 普通退货 | AI39: 多拍/错拍/不想要 | AJ39: I568150018600 | AL39: 6923661839766748780 | AM39: X2501326322FXT | AP39: 儿童轻薄羽绒服 | AQ39: 橄榄绿;160 | AR39: 橄榄绿;160 | AS39: 雪中飞 | AT39: 涛源 | AY39: 179 | AZ39: 86.7 | BF39: 0 | BJ39: 0.000% | BP39: 1 | BS39: 86.7 | CB39: 头条放心购 | CE39: 98.2 | CF39: 0 | CG39: 0 | CH39: =_xlfn.XLOOKUP(AL39,抖音账单汇总!$A:$A,抖音账单汇总!$B:$B) -> -179
A40: 20514151 | D40: 换货订单 | E40: 6923676186043579878 | G40: 已发货 | H40: 河北贝吉实业集团有限公司 | K40: 抖音-雪中飞德煌童装专卖店 | L40: 1@#md0n7unxb20X4hneVQR7WwZLLM8Rs7s/bXYVk2QfjbdzN6Io64D7/2Y8edC/ZpzkAj1R | M40: 13169701 | N40: 原始线上单号:6923676186043579878 | P40: 2026/1/25 18:29:31 | Q40: 2026/1/26 10:31:04 | R40: 2026/1/25 18:29:31 | S40: 2026/1/26 10:31:04 | T40: 2026/1/25 18:29:31 | U40: 广西壮族自治区 | V40: 桂林市 | W40: 平乐县 | X40: 圆通速递 | Y40: YT0009484096388 | AB40: 147:617D4BD1781D5D5BE30FD2D23717760C | AJ40: I568114898700 | AK40: 3787311554958066065 | AL40: 6923676186043579878 | AM40: X2501326322FXT | AP40: 儿童轻薄羽绒服 | AQ40: 新雾蓝;170 | AR40: 新雾蓝;170 | AS40: 雪中飞 | AT40: 涛源 | AY40: 179 | AZ40: 86.7 | BA40: 普通商品资料成本价 | BB40: 1 | BD40: 1 | BF40: 0 | BG40: 86.7 | BH40: 86.7 | BI40: -86.7 | BJ40: 0.000% | BK40: 0 | BL40: 0 | BW40: 3.6 | BX40: 3.6 | BZ40: 0.537 | CA40: 0.537 | CB40: 头条放心购 | CC40: AS,online | CE40: 98.2 | CF40: 0 | CG40: 0 | CH40: =_xlfn.XLOOKUP(AL40,抖音账单汇总!$A:$A,抖音账单汇总!$B:$B) -> 179
A41: 20097916 | B41: 发货后售后,小店,平台补贴,店铺新客,抖音极速版,直播间,线上修改地址,高频购买 | C41: 1226012268 | D41: 普通订单 | E41: 6923676186043579878 | G41: 已发货 | H41: 河北贝吉实业集团有限公司 | K41: 抖音-雪中飞德煌童装专卖店 | L41: 1@#md0n7unxb20X4hneVQR7WwZLLM8Rs7s/bXYVk2QfjbdzN6Io64D7/2Y8edC/ZpzkAj1R | M41: 13169701 | O41: (收) 颜色分类:新雾蓝;尺码大小:160cmI568114898600*1#,换货(20514151)# | P41: 2026/1/17 19:52:04 | Q41: 2026/1/18 8:31:28 | R41: 2026/1/17 19:52:44 | S41: 2026/2/2 10:31:08 | T41: 2026/1/17 19:52:44 | U41: 广西壮族自治区 | V41: 桂林市 | W41: 平乐县 | X41: 圆通速递 | Y41: YT0006934239304 | Z41: 极兔快递 | AA41: JT0021523775467 | AB41: 147:曾* | AC41: 2026/1/21 13:03:37 | AD41: 2026/1/25 18:29:31 | AE41: 2026-01-25 18:29:24 | AF41: 19686934 | AG41: 河北贝吉实业集团有限公司 | AH41: 换货 | AI41: 尺码不合适 | AJ41: I568114898600 | AK41: 3787311554958066065 | AL41: 6923676186043579878 | AM41: X2501326322FXT | AP41: 儿童轻薄羽绒服 | AQ41: 新雾蓝;160 | AR41: 颜色分类:新雾蓝;尺码大小:160CM | AS41: 雪中飞 | AT41: 涛源 | AY41: 179 | AZ41: 86.7 | BA41: 普通商品资料成本价 | BB41: 1 | BD41: 1 | BE41: 179 | BF41: 179 | BG41: 86.7 | BH41: 86.7 | BI41: 92.3 | BJ41: 51.564% | BK41: 179 | BL41: 179 | BM41: 179 | BN41: 179 | BO41: 1 | BP41: 1 | BR41: 86.7 | BS41: 86.7 | BU41: 0 | BW41: 3.6 | BX41: 3.6 | BZ41: 0.506 | CA41: 0.506 | CB41: 头条放心购 | CC41: TOUTIAOFXG | CE41: 98.2 | CF41: 1 | CG41: 179 | CH41: =_xlfn.XLOOKUP(AL41,抖音账单汇总!$A:$A,抖音账单汇总!$B:$B) -> 179
A42: 21062988 | B42: 发货后售后,小店,平台补贴,店铺新客,抖音,直播间,高频购买 | D42: 普通订单 | E42: 6924339032964300029 | G42: 已发货 | H42: 河北贝吉实业集团有限公司 | K42: 抖音-雪中飞德煌童装专卖店 | L42: 1@#Sxjf0Cd9Lm5WGcGjZpg40h/gL51xfTnSsIJnJDk+Hcrw+CG4Xbp3mkXaYghAJh4pn7FN | M42: 13880029 | O42: 侧身缝隙线头 补20【玉灿 02-22 14:27】;2.22 侧身缝线处有线头 绮 | P42: 2026/2/12 8:05:50 | Q42: 2026/2/12 10:30:46 | R42: 2026/2/12 8:05:55 | S42: 2026/2/19 10:30:48 | T42: 2026/2/12 8:05:55 | U42: 安徽省 | V42: 合肥市 | W42: 长丰县 | X42: 京东快递 | Y42: JDAZ23788725713 | AB42: 147:木* | AJ42: I568150018402 | AK42: 3787311554958066065 | AL42: 6924339032964300029 | AM42: X2501326322FXT | AP42: 儿童轻薄羽绒服 | AQ42: 橄榄绿;140 | AR42: 颜色分类:橄榄绿;尺码大小:140CM | AS42: 雪中飞 | AT42: 涛源 | AY42: 179 | AZ42: 86.7 | BA42: 普通商品资料成本价 | BB42: 1 | BD42: 1 | BE42: 179 | BF42: 179 | BG42: 86.7 | BH42: 86.7 | BI42: 92.3 | BJ42: 51.564% | BK42: 179 | BL42: 179 | BM42: 179 | BN42: 179 | BU42: 0 | BW42: 15 | BX42: 15 | BZ42: 0.456 | CA42: 0.456 | CB42: 头条放心购 | CC42: TOUTIAOFXG | CE42: 98.2 | CF42: =BD42-BP42 -> 1 | CG42: 158.77 | CH42: =_xlfn.XLOOKUP(AL42,抖音账单汇总!$A:$A,抖音账单汇总!$B:$B) -> 158.77
A43: 21060991 | B43: 发货后售后,小店,店铺新客,抖音,直播间,高频购买 | D43: 普通订单 | E43: 6950727649303074587 | G43: 已发货 | H43: 河北贝吉实业集团有限公司 | K43: 抖音-雪中飞德煌童装专卖店 | L43: 1@#K81vALHI+e3oh7xF1jlLV1zAm2sVIMCZa4/BqS8oJ91N+nbiBL4yo3cMXBm5yk4cPstE | M43: 13878430 | O43: 2.17侧身缝隙有针眼 兰 侧身缝隙有针眼 灿【玉灿 02-17 19:44】 | P43: 2026/2/11 23:53:19 | Q43: 2026/2/12 9:39:36 | R43: 2026/2/11 23:53:25 | S43: 2026/2/17 19:42:44 | T43: 2026/2/11 23:53:25 | U43: 安徽省 | V43: 六安市 | W43: 舒城县 | X43: 京东快递 | Y43: JDAZ23788906478 | AB43: 147:罗* | AJ43: I568150018140 | AK43: 3787311554958066065 | AL43: 6950727649303074587 | AM43: X2501326322FXT | AP43: 儿童轻薄羽绒服 | AQ43: 橄榄绿;150 | AR43: 颜色分类:橄榄绿;尺码大小:150CM | AS43: 雪中飞 | AT43: 涛源 | AY43: 179 | AZ43: 86.7 | BA43: 普通商品资料成本价 | BB43: 1 | BD43: 1 | BE43: 179 | BF43: 179 | BG43: 86.7 | BH43: 86.7 | BI43: 92.3 | BJ43: 51.564% | BK43: 179 | BL43: 179 | BM43: 179 | BN43: 179 | BU43: 0 | BW43: 15 | BX43: 15 | BZ43: 0.481 | CA43: 0.481 | CB43: 头条放心购 | CC43: TOUTIAOFXG | CE43: 98.2 | CF43: =BD43-BP43 -> 1 | CG43: 169 | CH43: =_xlfn.XLOOKUP(AL43,抖音账单汇总!$A:$A,抖音账单汇总!$B:$B) -> 169
A44: 21060978 | B44: 小店,店铺新客,抖音,服务优先,直播间,高频购买 | D44: 普通订单 | E44: 6950705402567333081 | G44: 已发货 | H44: 河北贝吉实业集团有限公司 | K44: 抖音-雪中飞德煌童装专卖店 | L44: 1@#qhRJPb8uHFhiDs34LssVEwRADIEYDDD1g5Fi+lcsJgBD+A0ZzmaL7YvC46d+LDWcQnxnuA== | M44: 13878419 | P44: 2026/2/11 23:51:38 | Q44: 2026/2/12 10:00:05 | R44: 2026/2/11 23:51:39 | S44: 2026/2/19 10:00:07 | T44: 2026/2/11 23:51:39 | U44: 陕西省 | V44: 西安市 | W44: 长安区 | X44: 京东快递 | Y44: JDAZ23788835657 | AB44: 147:李* | AJ44: H493851022140 | AK44: 3787311554958066065 | AL44: 6950705402567333081 | AM44: X250138240FXT | AN44: 轻薄羽绒服 | AP44: 儿童轻薄羽绒服 | AQ44: 咖啡棕;150 | AR44: 颜色分类:咖啡棕（8240款）;尺码大小:150CM | AS44: 雪中飞 | AT44: 茸淳羽绒 | AY44: 179 | AZ44: 87 | BA44: 普通商品资料成本价 | BB44: 1 | BD44: 1 | BE44: 159 | BF44: 159 | BG44: 87 | BH44: 87 | BI44: 72 | BJ44: 45.283% | BK44: 159 | BL44: 159 | BM44: 159 | BN44: 159 | BU44: 0 | BW44: 15 | BX44: 15 | BZ44: 0.493 | CA44: 0.493 | CB44: 头条放心购 | CC44: TOUTIAOFXG | CE44: 98.5 | CF44: =BD44-BP44 -> 1 | CG44: 159 | CH44: =_xlfn.XLOOKUP(AL44,抖音账单汇总!$A:$A,抖音账单汇总!$B:$B) -> 159
A45: 21060967 | B45: 小店,平台补贴,店铺老客,抖音,直播间,高频购买 | D45: 普通订单 | E45: 6950732444965934802 | G45: 已发货 | H45: 河北贝吉实业集团有限公司 | K45: 抖音-雪中飞德煌童装专卖店 | L45: 1@#9XtOaeS3oqliOgOV93J7AUc6TC5vmJJcW/UNo+9QE5V/+/1xkcv5Sjte2T2Woij5C9N+ | M45: 13878189 | P45: 2026/2/11 23:51:04 | Q45: 2026/2/12 9:39:33 | R45: 2026/2/11 23:51:05 | S45: 2026/2/14 1:31:31 | T45: 2026/2/11 23:51:05 | U45: 陕西省 | V45: 西安市 | W45: 未央区 | X45: 京东快递 | Y45: JDAZ23788744163 | AB45: 147:石* | AJ45: I568150018140 | AK45: 3787311554958066065 | AL45: 6950732444965934802 | AM45: X2501326322FXT | AP45: 儿童轻薄羽绒服 | AQ45: 橄榄绿;150 | AR45: 颜色分类:橄榄绿;尺码大小:150CM | AS45: 雪中飞 | AT45: 涛源 | AY45: 179 | AZ45: 86.7 | BA45: 普通商品资料成本价 | BB45: 1 | BD45: 1 | BE45: 179 | BF45: 179 | BG45: 86.7 | BH45: 86.7 | BI45: 92.3 | BJ45: 51.564% | BK45: 179 | BL45: 179 | BM45: 179 | BN45: 179 | BU45: 0 | BW45: 15 | BX45: 15 | BZ45: 0.481 | CA45: 0.481 | CB45: 头条放心购 | CC45: TOUTIAOFXG | CE45: 98.2 | CF45: =BD45-BP45 -> 1 | CG45: 179 | CH45: =_xlfn.XLOOKUP(AL45,抖音账单汇总!$A:$A,抖音账单汇总!$B:$B) -> 179
A46: 21060877 | B46: 小店,店铺新客,抖音,直播间,高频购买 | D46: 普通订单 | E46: 6924334834536119338 | G46: 已发货 | H46: 河北贝吉实业集团有限公司 | K46: 抖音-雪中飞德煌童装专卖店 | L46: 1@#mMhRIJ59KNIubUa7qCZ1ma5qlk66DwxeQ2UU8cxvHIjFRaP454RC03mnDAQ7zHkB3uQF | M46: 13878348 | P46: 2026/2/11 23:41:50 | Q46: 2026/2/12 9:39:27 | R46: 2026/2/11 23:41:59 | S46: 2026/2/19 9:39:29 | T46: 2026/2/11 23:41:59 | U46: 湖北省 | V46: 武汉市 | W46: 东西湖区 | X46: 京东快递 | Y46: JDAZ23788879208 | AB46: 147:李* | AJ46: I568150018140 | AK46: 3787311554958066065 | AL46: 6924334834536119338 | AM46: X2501326322FXT | AP46: 儿童轻薄羽绒服 | AQ46: 橄榄绿;150 | AR46: 颜色分类:橄榄绿;尺码大小:150CM | AS46: 雪中飞 | AT46: 涛源 | AY46: 179 | AZ46: 86.7 | BA46: 普通商品资料成本价 | BB46: 1 | BD46: 1 | BE46: 179 | BF46: 179 | BG46: 86.7 | BH46: 86.7 | BI46: 92.3 | BJ46: 51.564% | BK46: 179 | BL46: 179 | BM46: 179 | BN46: 179 | BU46: 0 | BW46: 15 | BX46: 15 | BZ46: 0.481 | CA46: 0.481 | CB46: 头条放心购 | CC46: TOUTIAOFXG | CE46: 98.2 | CF46: =BD46-BP46 -> 1 | CG46: 179 | CH46: =_xlfn.XLOOKUP(AL46,抖音账单汇总!$A:$A,抖音账单汇总!$B:$B) -> 179
A47: 21060542 | B47: 小店,平台补贴,店铺新客,服务优先,直播间,高频购买 | D47: 普通订单 | E47: 6950709747118839504 | G47: 已发货 | H47: 河北贝吉实业集团有限公司 | K47: 抖音-雪中飞德煌童装专卖店 | L47: 1@#vFKUCJa2xrYCePW5w0FPqHZX3KO5vl5+wJe7UPIFul0b1kEyGugYW4kpOCTpa+dSa5gnIw== | M47: 13878088 | P47: 2026/2/11 23:14:27 | Q47: 2026/2/12 9:39:23 | R47: 2026/2/11 23:14:43 | S47: 2026/2/19 9:39:25 | T47: 2026/2/11 23:14:43 | U47: 重庆 | V47: 重庆市 | W47: 南岸区 | X47: 京东快递 | Y47: JDAZ23788771370 | AB47: 147:黄* | AJ47: I568150018140 | AK47: 3787311554958066065 | AL47: 6950709747118839504 | AM47: X2501326322FXT | AP47: 儿童轻薄羽绒服 | AQ47: 橄榄绿;150 | AR47: 颜色分类:橄榄绿;尺码大小:150CM | AS47: 雪中飞 | AT47: 涛源 | AY47: 179 | AZ47: 86.7 | BA47: 普通商品资料成本价 | BB47: 1 | BD47: 1 | BE47: 179 | BF47: 179 | BG47: 86.7 | BH47: 86.7 | BI47: 92.3 | BJ47: 51.564% | BK47: 179 | BL47: 179 | BM47: 179 | BN47: 179 | BU47: 0 | BW47: 15 | BX47: 15 | BZ47: 0.481 | CA47: 0.481 | CB47: 头条放心购 | CC47: TOUTIAOFXG | CE47: 98.2 | CF47: =BD47-BP47 -> 1 | CG47: 179 | CH47: =_xlfn.XLOOKUP(AL47,抖音账单汇总!$A:$A,抖音账单汇总!$B:$B) -> 179
A48: 21060516 | B48: 小店,店铺新客,抖音,直播间,高频购买 | D48: 普通订单 | E48: 6950727662896944204 | G48: 已发货 | H48: 河北贝吉实业集团有限公司 | K48: 抖音-雪中飞德煌童装专卖店 | L48: 1@#2pGErcrHJtj/VgzNmP0KZr6wC5bfcVGtvGDNuGmTkv3HavKQAjjGudvqgrTGtKkPvbFfRPgCxlQ= | M48: 13878067 | P48: 2026/2/11 23:12:03 | Q48: 2026/2/12 10:23:24 | R48: 2026/2/11 23:12:20 | S48: 2026/2/19 10:23:26 | T48: 2026/2/11 23:12:20 | U48: 河南省 | V48: 郑州市 | W48: 金水区 | X48: 京东快递 | Y48: JDAZ23788901314 | AB48: 147:丁* | AJ48: I568150018402 | AK48: 3787311554958066065 | AL48: 6950727662896944204 | AM48: X2501326322FXT | AP48: 儿童轻薄羽绒服 | AQ48: 橄榄绿;140 | AR48: 颜色分类:橄榄绿;尺码大小:140CM | AS48: 雪中飞 | AT48: 涛源 | AY48: 179 | AZ48: 86.7 | BA48: 普通商品资料成本价 | BB48: 1 | BD48: 1 | BE48: 179 | BF48: 179 | BG48: 86.7 | BH48: 86.7 | BI48: 92.3 | BJ48: 51.564% | BK48: 179 | BL48: 179 | BM48: 179 | BN48: 179 | BU48: 0 | BW48: 15 | BX48: 15 | BZ48: 0.456 | CA48: 0.456 | CB48: 头条放心购 | CC48: TOUTIAOFXG | CE48: 98.2 | CF48: =BD48-BP48 -> 1 | CG48: 179 | CH48: =_xlfn.XLOOKUP(AL48,抖音账单汇总!$A:$A,抖音账单汇总!$B:$B) -> 179
A49: 21060413 | B49: 小店,店铺新客,抖音,服务优先,直播间,高频购买 | D49: 普通订单 | E49: 6924342980388552201 | G49: 已发货 | H49: 河北贝吉实业集团有限公司 | K49: 抖音-雪中飞德煌童装专卖店 | L49: 1@#FuKMUuMUA4otqRsKev7vMaRDyeSW4RIeRcXr8hYclRun3zIzQrdvK/KrxXvpCDugsUuTPO9M5w== | M49: 13877996 | P49: 2026/2/11 23:04:29 | Q49: 2026/2/12 11:50:28 | R49: 2026/2/11 23:04:31 | S49: 2026/2/19 11:50:31 | T49: 2026/2/11 23:04:31 | U49: 江苏省 | V49: 徐州市 | W49: 邳州市 | X49: 京东快递 | Y49: JDAZ23788876031 | AB49: 147:张* | AJ49: H626415547302 | AK49: 3787311554958066065 | AL49: 6924342980388552201 | AM49: X250138238FXT | AN49: 轻薄羽绒服 | AP49: 儿童轻薄羽绒服 | AQ49: 藏青色;130 | AR49: 颜色分类:藏青（8238款）;尺码大小:130CM | AS49: 雪中飞 | AT49: 茸淳羽绒 | AW49: 每日加权 | AY49: 199 | AZ49: 105.3 | BA49: 普通商品资料成本价 | BB49: 2 | BD49: 2 | BE49: 398 | BF49: 398 | BG49: 210.6 | BH49: 210.6 | BI49: 187.4 | BJ49: 47.085% | BK49: 398 | BL49: 398 | BM49: 199 | BN49: 398 | BU49: 0 | BW49: 15 | BX49: 15 | BZ49: 1.024 | CA49: 1.024 | CB49: 头条放心购 | CC49: TOUTIAOFXG | CE49: 116.8 | CF49: =BD49-BP49 -> 2 | CG49: 398 | CH49: =_xlfn.XLOOKUP(AL49,抖音账单汇总!$A:$A,抖音账单汇总!$B:$B) -> 398
A50: 21060392 | B50: 小店,平台补贴,店铺新客,高频购买 | D50: 普通订单 | E50: 6924334792578924105 | G50: 已发货 | H50: 河北贝吉实业集团有限公司 | K50: 抖音-雪中飞德煌童装专卖店 | L50: 1@#yhmCfCYTuwfecBvUwBHv90+Pvbv/7x4iolwlXAtXzKHd4tyljiiyqOFgON2W3cksbnSN | M50: 13877979 | P50: 2026/2/11 23:02:54 | Q50: 2026/2/12 10:57:53 | R50: 2026/2/11 23:03:13 | S50: 2026/2/17 13:06:36 | T50: 2026/2/11 23:03:13 | U50: 广东省 | V50: 韶关市 | W50: 仁化县 | X50: 京东快递 | Y50: JDAZ23788906757 | AB50: 147:领* | AJ50: I568150018700 | AK50: 3787311554958066065 | AL50: 6924334792578924105 | AM50: X2501326322FXT | AP50: 儿童轻薄羽绒服 | AQ50: 橄榄绿;170 | AR50: 颜色分类:橄榄绿;尺码大小:170CM | AS50: 雪中飞 | AT50: 涛源 | AY50: 179 | AZ50: 86.7 | BA50: 普通商品资料成本价 | BB50: 1 | BD50: 1 | BE50: 179 | BF50: 179 | BG50: 86.7 | BH50: 86.7 | BI50: 92.3 | BJ50: 51.564% | BK50: 179 | BL50: 179 | BM50: 179 | BN50: 179 | BU50: 0 | BW50: 15 | BX50: 15 | BZ50: 0.537 | CA50: 0.537 | CB50: 头条放心购 | CC50: TOUTIAOFXG | CE50: 98.2 | CF50: =BD50-BP50 -> 1 | CG50: 179 | CH50: =_xlfn.XLOOKUP(AL50,抖音账单汇总!$A:$A,抖音账单汇总!$B:$B) -> 179
A51: 21060385 | B51: 小店,店铺新客,服务优先,直播间 | D51: 普通订单 | E51: 6924340747038391648 | G51: 已发货 | H51: 河北贝吉实业集团有限公司 | K51: 抖音-雪中飞德煌童装专卖店 | L51: 1@#7l8TJ9riIbsv8ednOePx/Mh1sSRpkDR8I/dRkBWwHJiAsJMnQFC38wDnL1fPb/TPe7jODiM2EeU= | M51: 13877975 | P51: 2026/2/11 23:02:40 | Q51: 2026/2/12 11:10:40 | R51: 2026/2/11 23:02:41 | S51: 2026/2/19 11:10:45 | T51: 2026/2/11 23:02:41 | U51: 江苏省 | V51: 淮安市 | W51: 淮安区 | X51: 京东快递 | Y51: JDAZ23788879162 | AB51: 147:李* | AJ51: I568150074700 | AK51: 3787311554958066065 | AL51: 6924340747038391648 | AM51: X2501326322FXT | AP51: 儿童轻薄羽绒服 | AQ51: 绯红;170 | AR51: 颜色分类:绯红;尺码大小:170CM | AS51: 雪中飞 | AT51: 无唛尚品 | AY51: 179 | AZ51: 90 | BA51: 普通商品资料成本价 | BB51: 1 | BD51: 1 | BE51: 179 | BF51: 179 | BG51: 90 | BH51: 90 | BI51: 89 | BJ51: 49.721% | BK51: 179 | BL51: 179 | BM51: 179 | BN51: 179 | BU51: 0 | BW51: 15 | BX51: 15 | BZ51: 0.537 | CA51: 0.537 | CB51: 头条放心购 | CC51: TOUTIAOFXG | CE51: 101.5 | CF51: =BD51-BP51 -> 1 | CG51: 179 | CH51: =_xlfn.XLOOKUP(AL51,抖音账单汇总!$A:$A,抖音账单汇总!$B:$B) -> 179
A52: 21060275 | B52: 小店,店铺新客,服务优先,直播间 | D52: 普通订单 | E52: 6924336506549403478 | G52: 已发货 | H52: 河北贝吉实业集团有限公司 | K52: 抖音-雪中飞德煌童装专卖店 | L52: 1@#T8Y/6Ohl8eoG1KjU2G+m+Ug6fVOWox0Gs9k0swCUDbdkjnslAr5mlODHBcoGClVwE9GkgV5XeWs= | M52: 13877871 | P52: 2026/2/11 22:53:08 | Q52: 2026/2/12 10:57:38 | R52: 2026/2/11 22:54:47 | S52: 2026/2/19 10:57:41 | T52: 2026/2/11 22:54:47 | U52: 江苏省 | V52: 连云港市 | W52: 连云区 | X52: 京东快递 | Y52: JDAZ23788901331 | AB52: 147:洪* | AJ52: I568150018700 | AK52: 3787311554958066065 | AL52: 6924336506549403478 | AM52: X2501326322FXT | AP52: 儿童轻薄羽绒服 | AQ52: 橄榄绿;170 | AR52: 颜色分类:橄榄绿;尺码大小:170CM | AS52: 雪中飞 | AT52: 涛源 | AY52: 179 | AZ52: 86.7 | BA52: 普通商品资料成本价 | BB52: 1 | BD52: 1 | BE52: 179 | BF52: 179 | BG52: 86.7 | BH52: 86.7 | BI52: 92.3 | BJ52: 51.564% | BK52: 179 | BL52: 179 | BM52: 179 | BN52: 179 | BU52: 0 | BW52: 15 | BX52: 15 | BZ52: 0.537 | CA52: 0.537 | CB52: 头条放心购 | CC52: TOUTIAOFXG | CE52: 98.2 | CF52: =BD52-BP52 -> 1 | CG52: 179 | CH52: =_xlfn.XLOOKUP(AL52,抖音账单汇总!$A:$A,抖音账单汇总!$B:$B) -> 179
A53: 20634124 | B53: 极速发货 | D53: 换货订单 | E53: 6923706623434718909 | G53: 已发货 | H53: 河北贝吉实业集团有限公司 | K53: 抖音-雪中飞德煌童装专卖店 | L53: 1@#myO5PCCM7KtWPra5AEvzT5JNyBXy3vgIhPOah3zFh7pPysy5qdaKxwGYNQfb0nnOolhhrCBvgiM= | M53: 13207929 | N53: 原始线上单号:6923706623434718909 | P53: 2026/1/28 15:44:01 | Q53: 2026/1/28 18:14:59 | R53: 2026/1/28 15:44:01 | S53: 2026/1/28 18:14:59 | T53: 2026/1/28 15:44:01 | U53: 湖北省 | V53: 襄阳市 | W53: 樊城区 | X53: 圆通速递 | Y53: YT0010383190880 | AB53: 147:8039AE1299DFBF3B72EEE490B6D17570 | AJ53: H626415547600 | AK53: 3776786849159315776 | AL53: 6923706623434718909 | AM53: X250138238FXT | AN53: 轻薄羽绒服 | AP53: 儿童轻薄羽绒服 | AQ53: 藏青色;160 | AR53: 藏青色;160 | AS53: 雪中飞 | AT53: 茸淳羽绒 | AW53: 每日加权 | AY53: 199 | AZ53: 105.3 | BA53: 普通商品资料成本价 | BB53: 1 | BD53: 1 | BF53: 0 | BG53: 105.3 | BH53: 105.3 | BI53: -105.3 | BJ53: 0.000% | BK53: 0 | BL53: 0 | BW53: 3.6 | BX53: 3.6 | BZ53: 0.617 | CA53: 0.617 | CB53: 头条放心购 | CC53: AS,online | CE53: 116.8 | CF53: 0 | CG53: 0 | CH53: =_xlfn.XLOOKUP(AL53,抖音账单汇总!$A:$A,抖音账单汇总!$B:$B) -> 199
A54: 20147863 | B54: 优先发货,发货后售后,小店,店铺新客,抖音,服务优先,直播间 | C54: 1226130340 | D54: 普通订单 | E54: 6923706623434718909 | G54: 已发货 | H54: 河北贝吉实业集团有限公司 | K54: 抖音-雪中飞德煌童装专卖店 | L54: 1@#myO5PCCM7KtWPra5AEvzT5JNyBXy3vgIhPOah3zFh7pPysy5qdaKxwGYNQfb0nnOolhhrCBvgiM= | M54: 13207929 | O54: cp8无人接听，16点梦函,(收) 颜色分类:蝶恋紫;尺码大小:160cmI568114919600*1#,(收) 颜色分类:藏青色;尺码大小:150cmH626415547140*1#,换货(20634124)# | P54: 2026/1/18 16:08:29 | Q54: 2026/1/19 9:34:36 | R54: 2026/1/18 16:08:36 | S54: 2026/1/25 17:18:02 | T54: 2026/1/18 16:08:36 | U54: 湖北省 | V54: 襄阳市 | W54: 樊城区 | X54: 圆通速递 | Y54: YT0007237198710 | Z54: 圆通快递 | AA54: YT2536848282137 | AB54: 147:马* | AC54: 2026/1/25 18:50:31 | AD54: 2026/1/28 15:44:01 | AE54: 2026-01-28 15:43:54 | AF54: 19813448 | AG54: 河北贝吉实业集团有限公司 | AH54: 换货 | AI54: 尺码不合适 | AJ54: H626415547140 | AK54: 3776786849159315776 | AL54: 6923706623434718909 | AM54: X250138238FXT | AN54: 轻薄羽绒服 | AP54: 儿童轻薄羽绒服 | AQ54: 藏青色;150 | AR54: 颜色分类:藏青色;尺码大小:150CM | AS54: 雪中飞 | AT54: 茸淳羽绒 | AW54: 每日加权 | AY54: 199 | AZ54: 105.3 | BA54: 普通商品资料成本价 | BB54: 1 | BD54: 1 | BE54: 199 | BF54: 199 | BG54: 105.3 | BH54: 105.3 | BI54: 93.7 | BJ54: 47.085% | BM54: 199 | BN54: 199 | BO54: 1 | BP54: 1 | BR54: 105.3 | BS54: 105.3 | BX54: 2.95 | CB54: 头条放心购 | CC54: TOUTIAOFXG | CE54: 116.8 | CF54: 1 | CG54: 199 | CH54: =_xlfn.XLOOKUP(AL54,抖音账单汇总!$A:$A,抖音账单汇总!$B:$B) -> 199
A55: 21060112 | B55: 小店,店铺新客,抖音,服务优先,直播间 | D55: 普通订单 | E55: 6924340740669603642 | G55: 已发货 | H55: 河北贝吉实业集团有限公司 | K55: 抖音-雪中飞德煌童装专卖店 | L55: 1@#AckTi+Uh69WG3FjD2v81pdxDbVcVku7ahXF12DlaNvB6fUq6qtznY0GHBfHOKfh1tJZBOYq4Quk= | M55: 13877763 | P55: 2026/2/11 22:43:48 | Q55: 2026/2/12 10:22:33 | R55: 2026/2/11 22:43:49 | S55: 2026/2/19 10:22:34 | T55: 2026/2/11 22:43:49 | U55: 江苏省 | V55: 泰州市 | W55: 兴化市 | X55: 京东快递 | Y55: JDAZ23788771227 | AB55: 147:许* | AJ55: I568150018402 | AK55: 3787311554958066065 | AL55: 6924340740669603642 | AM55: X2501326322FXT | AP55: 儿童轻薄羽绒服 | AQ55: 橄榄绿;140 | AR55: 颜色分类:橄榄绿;尺码大小:140CM | AS55: 雪中飞 | AT55: 涛源 | AY55: 179 | AZ55: 86.7 | BA55: 普通商品资料成本价 | BB55: 1 | BD55: 1 | BE55: 179 | BF55: 179 | BG55: 86.7 | BH55: 86.7 | BI55: 92.3 | BJ55: 51.564% | BK55: 179 | BL55: 179 | BM55: 179 | BN55: 179 | BU55: 0 | BW55: 15 | BX55: 15 | BZ55: 0.456 | CA55: 0.456 | CB55: 头条放心购 | CC55: TOUTIAOFXG | CE55: 98.2 | CF55: =BD55-BP55 -> 1 | CG55: 179 | CH55: =_xlfn.XLOOKUP(AL55,抖音账单汇总!$A:$A,抖音账单汇总!$B:$B) -> 179
A56: 21059774 | B56: 小店,店铺新客,抖音,消费者催发货,直播间,高频购买 | D56: 普通订单 | E56: 6924321233695178382 | G56: 已发货 | H56: 河北贝吉实业集团有限公司 | K56: 抖音-雪中飞德煌童装专卖店 | L56: 1@#+aGOsICmtHy9XcpfxBQtbXczQqTiwAo9pd/I1QnZHf1YmYl6mU3tqsJrTsCu983ecQUYfXy98NA= | M56: 13877488 | P56: 2026/2/11 22:18:14 | Q56: 2026/2/12 10:22:13 | R56: 2026/2/11 22:18:16 | S56: 2026/2/19 10:22:15 | T56: 2026/2/11 22:18:16 | U56: 重庆 | V56: 重庆市 | W56: 开州区 | X56: 京东快递 | Y56: JDAZ23788744110 | AB56: 147:小* | AJ56: I568150018402 | AK56: 3787311554958066065 | AL56: 6924321233695178382 | AM56: X2501326322FXT | AP56: 儿童轻薄羽绒服 | AQ56: 橄榄绿;140 | AR56: 颜色分类:橄榄绿;尺码大小:140CM | AS56: 雪中飞 | AT56: 涛源 | AY56: 179 | AZ56: 86.7 | BA56: 普通商品资料成本价 | BB56: 1 | BD56: 1 | BE56: 179 | BF56: 179 | BG56: 86.7 | BH56: 86.7 | BI56: 92.3 | BJ56: 51.564% | BK56: 179 | BL56: 179 | BM56: 179 | BN56: 179 | BU56: 0 | BW56: 15 | BX56: 15 | BZ56: 0.456 | CA56: 0.456 | CB56: 头条放心购 | CC56: TOUTIAOFXG | CE56: 98.2 | CF56: =BD56-BP56 -> 1 | CG56: 179 | CH56: =_xlfn.XLOOKUP(AL56,抖音账单汇总!$A:$A,抖音账单汇总!$B:$B) -> 179
A57: 21059736 | B57: 小店,店铺新客,抖音,直播间 | D57: 普通订单 | E57: 6924328223509413085 | G57: 已发货 | H57: 河北贝吉实业集团有限公司 | K57: 抖音-雪中飞德煌童装专卖店 | L57: 1@#yFUYo2pR4MeI2lN1pxgE/NofQ43ti/FtpY95Djc3Uv8qzHuoMO9QIRiAtFtZ0Wk9J0Kt | M57: 13877449 | P57: 2026/2/11 22:14:53 | Q57: 2026/2/12 10:21:56 | R57: 2026/2/11 22:15:58 | S57: 2026/2/19 10:21:59 | T57: 2026/2/11 22:15:58 | U57: 江西省 | V57: 赣州市 | W57: 瑞金市 | X57: 京东快递 | Y57: JDAZ23788771506 | AB57: 147:土* | AJ57: I568150018402 | AK57: 3787311554958066065 | AL57: 6924328223509413085 | AM57: X2501326322FXT | AP57: 儿童轻薄羽绒服 | AQ57: 橄榄绿;140 | AR57: 颜色分类:橄榄绿;尺码大小:140CM | AS57: 雪中飞 | AT57: 涛源 | AY57: 179 | AZ57: 86.7 | BA57: 普通商品资料成本价 | BB57: 1 | BD57: 1 | BE57: 179 | BF57: 179 | BG57: 86.7 | BH57: 86.7 | BI57: 92.3 | BJ57: 51.564% | BK57: 179 | BL57: 179 | BM57: 179 | BN57: 179 | BU57: 0 | BW57: 15 | BX57: 15 | BZ57: 0.456 | CA57: 0.456 | CB57: 头条放心购 | CC57: TOUTIAOFXG | CE57: 98.2 | CF57: =BD57-BP57 -> 1 | CG57: 179 | CH57: =_xlfn.XLOOKUP(AL57,抖音账单汇总!$A:$A,抖音账单汇总!$B:$B) -> 179
A58: 21059490 | B58: 发货后售后,小店,平台补贴,店铺新客,抖音,直播间,高频购买 | D58: 普通订单 | E58: 6924334667434655285 | G58: 已发货 | H58: 河北贝吉实业集团有限公司 | K58: 抖音-雪中飞德煌童装专卖店 | L58: 1@#MJPXpPLjFwH3H7f0slmx8A/650tXFrzN9z+wXa+x06RUuFkEibsKLpvSQq70BKbmOmOuQ3uPeLk= | M58: 13877277 | O58: 穿着内衬缝隙出绒 补15【玉灿 03-05 13:23】;3.5 穿着 后身缝线处 下摆内里缝线处钻绒 绮 | P58: 2026/2/11 21:56:21 | Q58: 2026/2/12 10:55:47 | R58: 2026/2/11 21:56:27 | S58: 2026/2/19 10:55:48 | T58: 2026/2/11 21:56:27 | U58: 湖北省 | V58: 孝感市 | W58: 孝南区 | X58: 京东快递 | Y58: JDAZ23788909393 | AB58: 147:俆* | AJ58: H493814417402 | AK58: 3787311554958066065 | AL58: 6924334667434655285 | AM58: X250138240FXT | AN58: 羽绒服 | AP58: 儿童轻薄羽绒服 | AQ58: 黑色;140 | AR58: 颜色分类:黑色（8240款）;尺码大小:140CM | AS58: 雪中飞 | AT58: 茸淳羽绒 | AW58: 每日加权 | AY58: 179 | AZ58: 87 | BA58: 普通商品资料成本价 | BB58: 1 | BD58: 1 | BE58: 159 | BF58: 159 | BG58: 87 | BH58: 87 | BI58: 72 | BJ58: 45.283% | BK58: 159 | BL58: 159 | BM58: 159 | BN58: 159 | BU58: 0 | BW58: 15 | BX58: 15 | BZ58: 0.4655 | CA58: 0.4655 | CB58: 头条放心购 | CC58: TOUTIAOFXG | CE58: 98.5 | CF58: =BD58-BP58 -> 1 | CG58: 159 | CH58: =_xlfn.XLOOKUP(AL58,抖音账单汇总!$A:$A,抖音账单汇总!$B:$B) -> 159
A59: 21059367 | B59: 小店,平台补贴,店铺新客,服务优先,直播间,高频购买 | D59: 普通订单 | E59: 6950734536108807462 | G59: 已发货 | H59: 河北贝吉实业集团有限公司 | K59: 抖音-雪中飞德煌童装专卖店 | L59: 1@#OQjMVvvWg8cNknfEmjDgNID8lWVE53Q55Ayvw0GrsHMPFXMca1Hd0XS/KNIUkqR1P3sw | M59: 13877195 | P59: 2026/2/11 21:47:13 | Q59: 2026/2/12 10:36:43 | R59: 2026/2/11 21:47:21 | S59: 2026/2/19 10:36:45 | T59: 2026/2/11 21:47:21 | U59: 安徽省 | V59: 阜阳市 | W59: 颍上县 | X59: 京东快递 | Y59: JDAZ23788917098 | AB59: 147:小* | AJ59: I568150018402 | AK59: 3787311554958066065 | AL59: 6950734536108807462 | AM59: X2501326322FXT | AP59: 儿童轻薄羽绒服 | AQ59: 橄榄绿;140 | AR59: 颜色分类:橄榄绿;尺码大小:140CM | AS59: 雪中飞 | AT59: 涛源 | AY59: 179 | AZ59: 86.7 | BA59: 普通商品资料成本价 | BB59: 1 | BD59: 1 | BE59: 179 | BF59: 179 | BG59: 86.7 | BH59: 86.7 | BI59: 92.3 | BJ59: 51.564% | BK59: 179 | BL59: 179 | BM59: 179 | BN59: 179 | BU59: 0 | BW59: 15 | BX59: 15 | BZ59: 0.456 | CA59: 0.456 | CB59: 头条放心购 | CC59: TOUTIAOFXG | CE59: 98.2 | CF59: =BD59-BP59 -> 1 | CG59: 179 | CH59: =_xlfn.XLOOKUP(AL59,抖音账单汇总!$A:$A,抖音账单汇总!$B:$B) -> 179
A60: 21059291 | B60: 小店,平台补贴,店铺新客,抖音,直播间,高频购买 | D60: 普通订单 | E60: 6950736244491884459 | G60: 已发货 | H60: 河北贝吉实业集团有限公司 | K60: 抖音-雪中飞德煌童装专卖店 | L60: 1@#tZ81ivh+MEgojLOmPQ9zCMhW2sY2CA+Y/sdb/YltfDviWsjAhRN4B3h4CfuQ1emQrBLf | M60: 13877136 | P60: 2026/2/11 21:42:55 | Q60: 2026/2/12 11:30:12 | R60: 2026/2/11 21:42:56 | S60: 2026/2/19 16:47:34 | T60: 2026/2/11 21:42:56 | U60: 广东省 | V60: 潮州市 | W60: 饶平县 | X60: 京东快递 | Y60: JDAZ23788917071 | AB60: 147:刘* | AJ60: H493814417302 | AK60: 3787311554958066065 | AL60: 6950736244491884459 | AM60: X250138240FXT | AN60: 羽绒服 | AP60: 儿童轻薄羽绒服 | AQ60: 黑色;130 | AR60: 颜色分类:黑色（8240款）;尺码大小:130CM | AS60: 雪中飞 | AT60: 茸淳羽绒 | AW60: 每日加权 | AY60: 179 | AZ60: 87 | BA60: 普通商品资料成本价 | BB60: 1 | BD60: 1 | BE60: 159 | BF60: 159 | BG60: 87 | BH60: 87 | BI60: 72 | BJ60: 45.283% | BK60: 159 | BL60: 159 | BM60: 159 | BN60: 159 | BU60: 0 | BW60: 15 | BX60: 15 | BZ60: 0.4185 | CA60: 0.4185 | CB60: 头条放心购 | CC60: TOUTIAOFXG | CE60: 98.5 | CF60: =BD60-BP60 -> 1 | CG60: 159 | CH60: =_xlfn.XLOOKUP(AL60,抖音账单汇总!$A:$A,抖音账单汇总!$B:$B) -> 159
A61: 21059281 | B61: 小店,平台补贴,店铺新客,抖音,直播间,高频购买 | D61: 普通订单 | E61: 6924334664030649869 | G61: 已发货 | H61: 河北贝吉实业集团有限公司 | K61: 抖音-雪中飞德煌童装专卖店 | L61: 1@#wWULmI+S96RnIu8urNBl+CYod9XI1aPuvqx9ncH3MQluFlKFeoWXtop9DU6QCRp4hXHI | M61: 13877128 | P61: 2026/2/11 21:42:03 | Q61: 2026/2/12 10:35:06 | R61: 2026/2/11 21:42:07 | S61: 2026/2/19 10:35:08 | T61: 2026/2/11 21:42:07 | U61: 湖北省 | V61: 襄阳市 | W61: 南漳县 | X61: 京东快递 | Y61: JDAZ23788909268 | AB61: 147:雷* | AJ61: I568150018402 | AK61: 3787311554958066065 | AL61: 6924334664030649869 | AM61: X2501326322FXT | AP61: 儿童轻薄羽绒服 | AQ61: 橄榄绿;140 | AR61: 颜色分类:橄榄绿;尺码大小:140CM | AS61: 雪中飞 | AT61: 涛源 | AY61: 179 | AZ61: 86.7 | BA61: 普通商品资料成本价 | BB61: 1 | BD61: 1 | BE61: 179 | BF61: 179 | BG61: 86.7 | BH61: 86.7 | BI61: 92.3 | BJ61: 51.564% | BK61: 179 | BL61: 179 | BM61: 179 | BN61: 179 | BU61: 0 | BW61: 15 | BX61: 15 | BZ61: 0.456 | CA61: 0.456 | CB61: 头条放心购 | CC61: TOUTIAOFXG | CE61: 98.2 | CF61: =BD61-BP61 -> 1 | CG61: 179 | CH61: =_xlfn.XLOOKUP(AL61,抖音账单汇总!$A:$A,抖音账单汇总!$B:$B) -> 179
A62: 21059265 | B62: 小店,店铺新客,抖音,直播间,高频购买 | D62: 普通订单 | E62: 6950734561550145375 | G62: 已发货 | H62: 河北贝吉实业集团有限公司 | K62: 抖音-雪中飞德煌童装专卖店 | L62: 1@#6UDBNADwFN6+ivyl5xJ2+QMWSb2tin4pVuJHPd5vIFoAuGec45Ijx06THSYfA2ofXqdr | M62: 13877116 | P62: 2026/2/11 21:41:07 | Q62: 2026/2/12 9:40:58 | R62: 2026/2/11 21:41:09 | S62: 2026/2/19 9:40:59 | T62: 2026/2/11 21:41:09 | U62: 河南省 | V62: 濮阳市 | W62: 华龙区 | X62: 京东快递 | Y62: JDAZ23788909241 | AB62: 147:秦* | AJ62: I568150018140 | AK62: 3787311554958066065 | AL62: 6950734561550145375 | AM62: X2501326322FXT | AP62: 儿童轻薄羽绒服 | AQ62: 橄榄绿;150 | AR62: 颜色分类:橄榄绿;尺码大小:150CM | AS62: 雪中飞 | AT62: 涛源 | AY62: 179 | AZ62: 86.7 | BA62: 普通商品资料成本价 | BB62: 1 | BD62: 1 | BE62: 179 | BF62: 179 | BG62: 86.7 | BH62: 86.7 | BI62: 92.3 | BJ62: 51.564% | BK62: 179 | BL62: 179 | BM62: 179 | BN62: 179 | BU62: 0 | BW62: 15 | BX62: 15 | BZ62: 0.481 | CA62: 0.481 | CB62: 头条放心购 | CC62: TOUTIAOFXG | CE62: 98.2 | CF62: =BD62-BP62 -> 1 | CG62: 179 | CH62: =_xlfn.XLOOKUP(AL62,抖音账单汇总!$A:$A,抖音账单汇总!$B:$B) -> 179
A63: 21059082 | B63: 小店,店铺新客,抖音极速版,直播间,高频购买 | D63: 普通订单 | E63: 6924330726998768674 | G63: 已发货 | H63: 河北贝吉实业集团有限公司 | K63: 抖音-雪中飞德煌童装专卖店 | L63: 1@#HwnBqwf+A3X2HIC1ADlc1PsMmOPAEMbzp1XN1FTrdTIC2sMkxy5jdf1rM0Bt66tL4QvXhoLxaOg= | M63: 13876972 | P63: 2026/2/11 21:26:42 | Q63: 2026/2/12 9:40:49 | R63: 2026/2/11 21:26:52 | S63: 2026/2/19 9:40:50 | T63: 2026/2/11 21:26:52 | U63: 山东省 | V63: 青岛市 | W63: 平度市 | X63: 京东快递 | Y63: JDAZ23788943307 | AB63: 147:宿* | AJ63: I568150018140 | AK63: 3787311554958066065 | AL63: 6924330726998768674 | AM63: X2501326322FXT | AP63: 儿童轻薄羽绒服 | AQ63: 橄榄绿;150 | AR63: 颜色分类:橄榄绿;尺码大小:150CM | AS63: 雪中飞 | AT63: 涛源 | AY63: 179 | AZ63: 86.7 | BA63: 普通商品资料成本价 | BB63: 1 | BD63: 1 | BE63: 179 | BF63: 179 | BG63: 86.7 | BH63: 86.7 | BI63: 92.3 | BJ63: 51.564% | BK63: 179 | BL63: 179 | BM63: 179 | BN63: 179 | BU63: 0 | BW63: 15 | BX63: 15 | BZ63: 0.481 | CA63: 0.481 | CB63: 头条放心购 | CC63: TOUTIAOFXG | CE63: 98.2 | CF63: =BD63-BP63 -> 1 | CG63: 179 | CH63: =_xlfn.XLOOKUP(AL63,抖音账单汇总!$A:$A,抖音账单汇总!$B:$B) -> 179
A64: 21059024 | B64: 小店,店铺新客,直播间 | D64: 普通订单 | E64: 6950721130633827732 | G64: 已发货 | H64: 河北贝吉实业集团有限公司 | K64: 抖音-雪中飞德煌童装专卖店 | L64: 1@#zYFkfmLSaUSKQUp7evrK/6d9bsJOU7Kwu1VGld2D0wKqvRPC7TXMRrQyksTmeVlSbJ4JAg== | M64: 13876926 | P64: 2026/2/11 21:21:44 | Q64: 2026/2/12 11:30:11 | R64: 2026/2/11 21:21:45 | S64: 2026/2/19 11:30:14 | T64: 2026/2/11 21:21:45 | U64: 山东省 | V64: 青岛市 | W64: 黄岛区 | X64: 京东快递 | Y64: JDAZ23788810324 | AB64: 147:张* | AJ64: H493814417302 | AK64: 3787311554958066065 | AL64: 6950721130633827732 | AM64: X250138240FXT | AN64: 羽绒服 | AP64: 儿童轻薄羽绒服 | AQ64: 黑色;130 | AR64: 颜色分类:黑色（8240款）;尺码大小:130CM | AS64: 雪中飞 | AT64: 茸淳羽绒 | AW64: 每日加权 | AY64: 179 | AZ64: 87 | BA64: 普通商品资料成本价 | BB64: 1 | BD64: 1 | BE64: 159 | BF64: 159 | BG64: 87 | BH64: 87 | BI64: 72 | BJ64: 45.283% | BK64: 159 | BL64: 159 | BM64: 159 | BN64: 159 | BU64: 0 | BW64: 15 | BX64: 15 | BZ64: 0.4185 | CA64: 0.4185 | CB64: 头条放心购 | CC64: TOUTIAOFXG | CE64: 98.5 | CF64: =BD64-BP64 -> 1 | CG64: 159 | CH64: =_xlfn.XLOOKUP(AL64,抖音账单汇总!$A:$A,抖音账单汇总!$B:$B) -> 159
A65: 21058574 | B65: 小店,平台补贴,店铺老客,抖音,服务优先,直播间,高频购买 | D65: 普通订单 | E65: 6950736229082993785 | G65: 已发货 | H65: 河北贝吉实业集团有限公司 | K65: 抖音-雪中飞德煌童装专卖店 | L65: 1@#9RPSfuAg8yclS7pm0YRcaA+DM9olA/BFQCaCGYC8MBlhMWvKZnd91bF/bpmAdNMt7//viYAJDSs= | M65: 13876422 | P65: 2026/2/11 20:46:31 | Q65: 2026/2/12 9:42:57 | R65: 2026/2/11 20:46:57 | S65: 2026/2/19 9:43:00 | T65: 2026/2/11 20:46:57 | U65: 广东省 | V65: 揭阳市 | W65: 榕城区 | X65: 京东快递 | Y65: JDAZ23788917053 | AB65: 147:陈* | AJ65: I568150018600 | AK65: 3787311554958066065 | AL65: 6950736229082993785 | AM65: X2501326322FXT | AP65: 儿童轻薄羽绒服 | AQ65: 橄榄绿;160 | AR65: 颜色分类:橄榄绿;尺码大小:160CM | AS65: 雪中飞 | AT65: 涛源 | AY65: 179 | AZ65: 86.7 | BA65: 普通商品资料成本价 | BB65: 1 | BD65: 1 | BE65: 179 | BF65: 179 | BG65: 86.7 | BH65: 86.7 | BI65: 92.3 | BJ65: 51.564% | BK65: 179 | BL65: 179 | BM65: 179 | BN65: 179 | BU65: 0 | BW65: 15 | BX65: 15 | BZ65: 0.506 | CA65: 0.506 | CB65: 头条放心购 | CC65: TOUTIAOFXG | CE65: 98.2 | CF65: =BD65-BP65 -> 1 | CG65: 179 | CH65: =_xlfn.XLOOKUP(AL65,抖音账单汇总!$A:$A,抖音账单汇总!$B:$B) -> 179
A66: 21058494 | B66: 小店,平台补贴,店铺新客,服务优先,直播间,高频购买 | D66: 普通订单 | E66: 6924334489643875411 | G66: 已发货 | H66: 河北贝吉实业集团有限公司 | K66: 抖音-雪中飞德煌童装专卖店 | L66: 1@#034bkgyQPzWTThZiBzN6yBd1SH3RudDIxVRo2DJ+fs4zS4Uo04yK73yOB5AqRukgHYjsHw== | M66: 13876384 | P66: 2026/2/11 20:27:38 | Q66: 2026/2/12 10:03:01 | R66: 2026/2/11 20:42:36 | S66: 2026/2/19 10:03:03 | T66: 2026/2/11 20:42:36 | U66: 山东省 | V66: 济南市 | W66: 历城区 | X66: 京东快递 | Y66: JDAZ23788961307 | AB66: 147:王* | AJ66: H701651416302 | AK66: 3790120658906775806 | AL66: 6924334489643875411 | AM66: X2501419066FXT | AN66: 羽绒服 | AP66: 儿童羽绒服 | AQ66: 藕粉;130 | AR66: 颜色分类:藕粉;尺码大小:130 | AS66: 雪中飞 | AT66: 茸淳羽绒 | AW66: 每日加权 | AY66: 279 | AZ66: 128.5 | BA66: 普通商品资料成本价 | BB66: 1 | BD66: 1 | BE66: 279 | BF66: 279 | BG66: 128.5 | BH66: 128.5 | BI66: 150.5 | BJ66: 53.943% | BK66: 279 | BL66: 279 | BM66: 279 | BN66: 279 | BU66: 0 | BW66: 15 | BX66: 15 | BZ66: 0.763 | CA66: 0.763 | CB66: 头条放心购 | CC66: TOUTIAOFXG | CE66: 145 | CF66: =BD66-BP66 -> 1 | CG66: 279 | CH66: =_xlfn.XLOOKUP(AL66,抖音账单汇总!$A:$A,抖音账单汇总!$B:$B) -> 279
A67: 21058380 | B67: 小店,店铺新客,抖音,直播间,高频购买 | D67: 普通订单 | E67: 6950712194261915467 | G67: 已发货 | H67: 河北贝吉实业集团有限公司 | K67: 抖音-雪中飞德煌童装专卖店 | L67: 1@#Up/9MvW4fi0JRN71aJMEy/2lDBwId2lEgIhoQi3AUXkUIyt7b8+Km3BygRfqI5abfiQsO1Patgc= | M67: 13876436 | P67: 2026/2/11 20:31:52 | Q67: 2026/2/12 10:36:56 | R67: 2026/2/11 20:31:57 | S67: 2026/2/19 10:36:59 | T67: 2026/2/11 20:31:57 | U67: 山东省 | V67: 临沂市 | W67: 兰山区 | X67: 京东快递 | Y67: JDAZ23788827251 | AB67: 147:朱* | AJ67: H493814417140 | AK67: 3787311554958066065 | AL67: 6950712194261915467 | AM67: X250138240FXT | AN67: 羽绒服 | AP67: 儿童轻薄羽绒服 | AQ67: 黑色;150 | AR67: 颜色分类:黑色（8240款）;尺码大小:150CM | AS67: 雪中飞 | AT67: 茸淳羽绒 | AW67: 每日加权 | AY67: 179 | AZ67: 87 | BA67: 普通商品资料成本价 | BB67: 1 | BD67: 1 | BE67: 159 | BF67: 159 | BG67: 87 | BH67: 87 | BI67: 72 | BJ67: 45.283% | BK67: 159 | BL67: 159 | BM67: 159 | BN67: 159 | BU67: 0 | BW67: 15 | BX67: 15 | BZ67: 0.493 | CA67: 0.493 | CB67: 头条放心购 | CC67: TOUTIAOFXG | CE67: 98.5 | CF67: =BD67-BP67 -> 1 | CG67: 159 | CH67: =_xlfn.XLOOKUP(AL67,抖音账单汇总!$A:$A,抖音账单汇总!$B:$B) -> 159
A68: 21058061 | B68: 小店,店铺新客,直播间,高频购买 | D68: 普通订单 | E68: 6924336297861152476 | G68: 已发货 | H68: 河北贝吉实业集团有限公司 | K68: 抖音-雪中飞德煌童装专卖店 | L68: 1@#IrZtgzxnKROEugx9nFYU9XpfbuTUxvj5uj+LJoadB6DpkoKpl91XiHKbPZR2w40w2pd2kw== | M68: 13876188 | P68: 2026/2/11 20:05:48 | Q68: 2026/2/12 9:42:52 | R68: 2026/2/11 20:05:58 | S68: 2026/2/15 15:46:55 | T68: 2026/2/11 20:05:58 | U68: 山东省 | V68: 济南市 | W68: 历下区 | X68: 京东快递 | Y68: JDAZ23788917109 | AB68: 147:谷* | AJ68: I568150018600 | AK68: 3787311554958066065 | AL68: 6924336297861152476 | AM68: X2501326322FXT | AP68: 儿童轻薄羽绒服 | AQ68: 橄榄绿;160 | AR68: 颜色分类:橄榄绿;尺码大小:160CM | AS68: 雪中飞 | AT68: 涛源 | AY68: 179 | AZ68: 86.7 | BA68: 普通商品资料成本价 | BB68: 1 | BD68: 1 | BE68: 179 | BF68: 179 | BG68: 86.7 | BH68: 86.7 | BI68: 92.3 | BJ68: 51.564% | BK68: 179 | BL68: 179 | BM68: 179 | BN68: 179 | BU68: 0 | BW68: 15 | BX68: 15 | BZ68: 0.506 | CA68: 0.506 | CB68: 头条放心购 | CC68: TOUTIAOFXG | CE68: 98.2 | CF68: =BD68-BP68 -> 1 | CG68: 179 | CH68: =_xlfn.XLOOKUP(AL68,抖音账单汇总!$A:$A,抖音账单汇总!$B:$B) -> 179
A69: 21058033 | B69: 小店,店铺新客,抖音,直播间,高频购买 | D69: 普通订单 | E69: 6924327987048905772 | G69: 已发货 | H69: 河北贝吉实业集团有限公司 | K69: 抖音-雪中飞德煌童装专卖店 | L69: 1@#ybInQcd5frFHstIlU7hUUcegJpxjjg3l+dCFQhia9zppSFi5RkbzSIOo0HwCoVnKinO8NjvK3kw= | M69: 13876164 | O69: hp8 【叙源 02-26 09:28】 | P69: 2026/2/11 20:03:02 | Q69: 2026/2/12 11:26:24 | R69: 2026/2/11 20:03:12 | S69: 2026/2/18 22:59:40 | T69: 2026/2/11 20:03:12 | U69: 江苏省 | V69: 扬州市 | W69: 广陵区 | X69: 京东快递 | Y69: JDAZ23788822490 | AB69: 147:钱* | AJ69: I568114898700 | AK69: 3787311554958066065 | AL69: 6924327987048905772 | AM69: X2501326322FXT | AP69: 儿童轻薄羽绒服 | AQ69: 新雾蓝;170 | AR69: 颜色分类:新雾蓝;尺码大小:170CM | AS69: 雪中飞 | AT69: 涛源 | AY69: 179 | AZ69: 86.7 | BA69: 普通商品资料成本价 | BB69: 1 | BD69: 1 | BE69: 179 | BF69: 179 | BG69: 86.7 | BH69: 86.7 | BI69: 92.3 | BJ69: 51.564% | BK69: 179 | BL69: 179 | BM69: 179 | BN69: 179 | BU69: 0 | BW69: 15 | BX69: 15 | BZ69: 0.537 | CA69: 0.537 | CB69: 头条放心购 | CC69: TOUTIAOFXG | CE69: 98.2 | CF69: =BD69-BP69 -> 1 | CG69: 179 | CH69: =_xlfn.XLOOKUP(AL69,抖音账单汇总!$A:$A,抖音账单汇总!$B:$B) -> 179
A70: 21057895 | B70: 小店,平台补贴,店铺新客,高频购买 | D70: 普通订单 | E70: 6950718452384732927 | G70: 已发货 | H70: 河北贝吉实业集团有限公司 | K70: 抖音-雪中飞德煌童装专卖店 | L70: 1@#6ueAF2cosAsi78pne+bWk+vbhVh+9NwViHvvHS1HYZ9eBeqbSZNw29kMC6+5DMUEnZle | M70: 13876056 | P70: 2026/2/11 19:51:44 | Q70: 2026/2/12 11:18:43 | R70: 2026/2/11 19:52:05 | S70: 2026/2/19 11:18:45 | T70: 2026/2/11 19:52:05 | U70: 江西省 | V70: 赣州市 | W70: 兴国县 | X70: 京东快递 | Y70: JDAZ23788822481 | AB70: 147:万* | AJ70: I568150018302 | AK70: 3787311554958066065 | AL70: 6950718452384732927 | AM70: X2501326322FXT | AP70: 儿童轻薄羽绒服 | AQ70: 橄榄绿;130 | AR70: 颜色分类:橄榄绿;尺码大小:130CM | AS70: 雪中飞 | AT70: 涛源 | AY70: 179 | AZ70: 86.7 | BA70: 普通商品资料成本价 | BB70: 1 | BD70: 1 | BE70: 179 | BF70: 179 | BG70: 86.7 | BH70: 86.7 | BI70: 92.3 | BJ70: 51.564% | BK70: 179 | BL70: 179 | BM70: 179 | BN70: 179 | BU70: 0 | BW70: 15 | BX70: 15 | BZ70: 0.419 | CA70: 0.419 | CB70: 头条放心购 | CC70: TOUTIAOFXG | CE70: 98.2 | CF70: =BD70-BP70 -> 1 | CG70: 179 | CH70: =_xlfn.XLOOKUP(AL70,抖音账单汇总!$A:$A,抖音账单汇总!$B:$B) -> 179
A71: 21057845 | B71: 小店,平台补贴,店铺新客,抖音,直播间,高频购买 | D71: 普通订单 | E71: 6924338517878864954 | G71: 已发货 | H71: 河北贝吉实业集团有限公司 | K71: 抖音-雪中飞德煌童装专卖店 | L71: 1@#hy34CuRaDZIlRAsN922veWrn8SA1G+84EzuYNCLVB3E4FY1xubmhkstV2crpAOS+0z01 | M71: 13876021 | P71: 2026/2/11 19:47:05 | Q71: 2026/2/12 10:55:02 | R71: 2026/2/11 19:47:06 | S71: 2026/2/19 10:55:04 | T71: 2026/2/11 19:47:06 | U71: 黑龙江省 | V71: 哈尔滨市 | W71: 道外区 | X71: 京东快递 | Y71: JDAZ23788917251 | AB71: 147:于* | AJ71: H493814417402 | AK71: 3787311554958066065 | AL71: 6924338517878864954 | AM71: X250138240FXT | AN71: 羽绒服 | AP71: 儿童轻薄羽绒服 | AQ71: 黑色;140 | AR71: 颜色分类:黑色（8240款）;尺码大小:140CM | AS71: 雪中飞 | AT71: 茸淳羽绒 | AW71: 每日加权 | AY71: 179 | AZ71: 87 | BA71: 普通商品资料成本价 | BB71: 1 | BD71: 1 | BE71: 159 | BF71: 159 | BG71: 87 | BH71: 87 | BI71: 72 | BJ71: 45.283% | BK71: 159 | BL71: 159 | BM71: 159 | BN71: 159 | BU71: 0 | BW71: 15 | BX71: 15 | BZ71: 0.4655 | CA71: 0.4655 | CB71: 头条放心购 | CC71: TOUTIAOFXG | CE71: 98.5 | CF71: =BD71-BP71 -> 1 | CG71: 159 | CH71: =_xlfn.XLOOKUP(AL71,抖音账单汇总!$A:$A,抖音账单汇总!$B:$B) -> 159
A72: 21057362 | B72: 小店,店铺新客,抖音,直播间,高频购买 | D72: 普通订单 | E72: 6924320930917678257 | G72: 已发货 | H72: 河北贝吉实业集团有限公司 | K72: 抖音-雪中飞德煌童装专卖店 | L72: 1@#nyjJIjaa6/vosI8XxLJSFDXFagRbNcKNJ64JpnQQGDJiVnhOPxRGQlO2iEzM3o/GqjbNSA== | M72: 13875660 | P72: 2026/2/11 18:59:06 | Q72: 2026/2/12 11:32:06 | R72: 2026/2/11 18:59:16 | S72: 2026/2/19 11:32:08 | T72: 2026/2/11 18:59:16 | U72: 湖北省 | V72: 仙桃市 | W72: 仙桃市 | X72: 京东快递 | Y72: JDAZ23788943316 | AB72: 147:马* | AJ72: H598714417140 | AK72: 3758813381755273379 | AL72: 6924320930917678257 | AM72: X250138648FXT | AN72: 轻薄羽绒服 | AP72: 儿童轻薄羽绒服 | AQ72: 黑色;150 | AR72: 颜色分类:黑色;尺码大小:150CM | AS72: 雪中飞 | AT72: 贝优 | AW72: 每日加权 | AY72: 179 | AZ72: 85.5 | BA72: 普通商品资料成本价 | BB72: 1 | BD72: 1 | BE72: 179 | BF72: 179 | BG72: 85.5 | BH72: 85.5 | BI72: 93.5 | BJ72: 52.235% | BK72: 179 | BL72: 179 | BM72: 179 | BN72: 179 | BU72: 0 | BW72: 15 | BX72: 15 | BZ72: 0.467 | CA72: 0.467 | CB72: 头条放心购 | CC72: TOUTIAOFXG | CE72: 97 | CF72: =BD72-BP72 -> 1 | CG72: 179 | CH72: =_xlfn.XLOOKUP(AL72,抖音账单汇总!$A:$A,抖音账单汇总!$B:$B) -> 179
A73: 21057354 | B73: 小店,平台补贴,店铺新客,抖音极速版,服务优先,高频购买 | D73: 普通订单 | E73: 6950716208191313029 | G73: 已发货 | H73: 河北贝吉实业集团有限公司 | K73: 抖音-雪中飞德煌童装专卖店 | L73: 1@#kTGzIL11uWIm3wiqRMQLVh89w47bVKL6/fO41nOWv/MZuNrffRFdW2qSNAoWXAIVj68yNdvzrzc= | M73: 13875557 | P73: 2026/2/11 18:43:01 | Q73: 2026/2/12 10:33:14 | R73: 2026/2/11 18:58:29 | S73: 2026/2/14 13:52:49 | T73: 2026/2/11 18:58:29 | U73: 湖南省 | V73: 长沙市 | W73: 岳麓区 | X73: 京东快递 | Y73: JDAZ23788792277 | AB73: 147:文* | AJ73: I568150018402 | AK73: 3787311554958066065 | AL73: 6950716208191313029 | AM73: X2501326322FXT | AP73: 儿童轻薄羽绒服 | AQ73: 橄榄绿;140 | AR73: 颜色分类:橄榄绿;尺码大小:140CM | AS73: 雪中飞 | AT73: 涛源 | AY73: 179 | AZ73: 86.7 | BA73: 普通商品资料成本价 | BB73: 1 | BD73: 1 | BE73: 179 | BF73: 179 | BG73: 86.7 | BH73: 86.7 | BI73: 92.3 | BJ73: 51.564% | BK73: 179 | BL73: 179 | BM73: 179 | BN73: 179 | BU73: 0 | BW73: 15 | BX73: 15 | BZ73: 0.456 | CA73: 0.456 | CB73: 头条放心购 | CC73: TOUTIAOFXG | CE73: 98.2 | CF73: =BD73-BP73 -> 1 | CG73: 179 | CH73: =_xlfn.XLOOKUP(AL73,抖音账单汇总!$A:$A,抖音账单汇总!$B:$B) -> 179
A74: 21057280 | B74: 小店,店铺老客,抖音,高频购买 | D74: 普通订单 | E74: 6924340382990695701 | G74: 已发货 | H74: 河北贝吉实业集团有限公司 | K74: 抖音-雪中飞德煌童装专卖店 | L74: 1@#1hiodCxLC+VnXaT5fQZq5vUo7woPbvW0r1rTUdytwZjZFjeUU4C+dk7T/3vluoNfX+hw | M74: 13759299 | P74: 2026/2/11 18:49:46 | Q74: 2026/2/12 10:59:15 | R74: 2026/2/11 18:49:50 | S74: 2026/2/19 10:59:17 | T74: 2026/2/11 18:49:50 | U74: 湖北省 | V74: 襄阳市 | W74: 枣阳市 | X74: 京东快递 | Y74: JDAZ23788901907 | AB74: 147:江* | AJ74: I568150018700 | AK74: 3787311554958066065 | AL74: 6924340382990695701 | AM74: X2501326322FXT | AP74: 儿童轻薄羽绒服 | AQ74: 橄榄绿;170 | AR74: 颜色分类:橄榄绿;尺码大小:170CM | AS74: 雪中飞 | AT74: 涛源 | AY74: 179 | AZ74: 86.7 | BA74: 普通商品资料成本价 | BB74: 1 | BD74: 1 | BE74: 179 | BF74: 179 | BG74: 86.7 | BH74: 86.7 | BI74: 92.3 | BJ74: 51.564% | BK74: 179 | BL74: 179 | BM74: 179 | BN74: 179 | BU74: 0 | BW74: 15 | BX74: 15 | BZ74: 0.537 | CA74: 0.537 | CB74: 头条放心购 | CC74: TOUTIAOFXG | CE74: 98.2 | CF74: =BD74-BP74 -> 1 | CG74: 179 | CH74: =_xlfn.XLOOKUP(AL74,抖音账单汇总!$A:$A,抖音账单汇总!$B:$B) -> 179
A75: 21057236 | B75: 小店,平台补贴,店铺新客,消费者催发货,直播间,高频购买 | D75: 普通订单 | E75: 6924336152318278928 | G75: 已发货 | H75: 河北贝吉实业集团有限公司 | K75: 抖音-雪中飞德煌童装专卖店 | L75: 1@#3B0rRkedjXXh0QJwznH7XuJtPWnEsAp1uDoHgX4QJ1HMm1wRySMNv+WXT4K17YvyVz0Z | M75: 13875563 | P75: 2026/2/11 18:44:46 | Q75: 2026/2/12 9:40:04 | R75: 2026/2/11 18:44:50 | S75: 2026/2/15 12:11:39 | T75: 2026/2/11 18:44:50 | U75: 云南省 | V75: 文山壮族苗族自治州 | W75: 马关县 | X75: 京东快递 | Y75: JDAZ23788879316 | AB75: 147:李* | AJ75: I568150018140 | AK75: 3787311554958066065 | AL75: 6924336152318278928 | AM75: X2501326322FXT | AP75: 儿童轻薄羽绒服 | AQ75: 橄榄绿;150 | AR75: 颜色分类:橄榄绿;尺码大小:150CM | AS75: 雪中飞 | AT75: 涛源 | AY75: 179 | AZ75: 86.7 | BA75: 普通商品资料成本价 | BB75: 1 | BD75: 1 | BE75: 179 | BF75: 179 | BG75: 86.7 | BH75: 86.7 | BI75: 92.3 | BJ75: 51.564% | BK75: 179 | BL75: 179 | BM75: 179 | BN75: 179 | BU75: 0 | BW75: 15 | BX75: 15 | BZ75: 0.481 | CA75: 0.481 | CB75: 头条放心购 | CC75: TOUTIAOFXG | CE75: 98.2 | CF75: =BD75-BP75 -> 1 | CG75: 179 | CH75: =_xlfn.XLOOKUP(AL75,抖音账单汇总!$A:$A,抖音账单汇总!$B:$B) -> 179
A76: 21057185 | B76: 小店,店铺新客,抖音,直播间 | D76: 普通订单 | E76: 6924323703722179910 | G76: 已发货 | H76: 河北贝吉实业集团有限公司 | K76: 抖音-雪中飞德煌童装专卖店 | L76: 1@#VuxooDT9Y/Y5qalqaOErxmqqnqLmuUHvN/2b53rLStmy9hi1WnY4IILQrTvorIfclcB59tYzhDY= | M76: 13875524 | P76: 2026/2/11 18:38:20 | Q76: 2026/2/12 9:42:41 | R76: 2026/2/11 18:38:29 | S76: 2026/2/19 9:42:43 | T76: 2026/2/11 18:38:29 | U76: 广西壮族自治区 | V76: 贵港市 | W76: 港北区 | X76: 京东快递 | Y76: JDAZ23788854098 | AB76: 147:周* | AJ76: I568150018600 | AK76: 3787311554958066065 | AL76: 6924323703722179910 | AM76: X2501326322FXT | AP76: 儿童轻薄羽绒服 | AQ76: 橄榄绿;160 | AR76: 颜色分类:橄榄绿;尺码大小:160CM | AS76: 雪中飞 | AT76: 涛源 | AY76: 179 | AZ76: 86.7 | BA76: 普通商品资料成本价 | BB76: 1 | BD76: 1 | BE76: 179 | BF76: 179 | BG76: 86.7 | BH76: 86.7 | BI76: 92.3 | BJ76: 51.564% | BK76: 179 | BL76: 179 | BM76: 179 | BN76: 179 | BU76: 0 | BW76: 15 | BX76: 15 | BZ76: 0.506 | CA76: 0.506 | CB76: 头条放心购 | CC76: TOUTIAOFXG | CE76: 98.2 | CF76: =BD76-BP76 -> 1 | CG76: 179 | CH76: =_xlfn.XLOOKUP(AL76,抖音账单汇总!$A:$A,抖音账单汇总!$B:$B) -> 179
A77: 21057041 | B77: 小店,店铺新客,抖音极速版,高频购买 | D77: 普通订单 | E77: 6924325626671365583 | G77: 已发货 | H77: 河北贝吉实业集团有限公司 | K77: 抖音-雪中飞德煌童装专卖店 | L77: 1@#JNsGYZGIoai6tv3H+Moi9NPRRJV9Z3RYfcwKiOvz93IaiEdkXODnzzCUwHNRM5s85JPg | M77: 13875409 | P77: 2026/2/11 18:20:09 | Q77: 2026/2/12 10:58:53 | R77: 2026/2/11 18:20:15 | S77: 2026/2/19 10:58:55 | T77: 2026/2/11 18:20:15 | U77: 河南省 | V77: 许昌市 | W77: 禹州市 | X77: 京东快递 | Y77: JDAZ23788744433 | AB77: 147:张* | AJ77: I568150018700 | AK77: 3787311554958066065 | AL77: 6924325626671365583 | AM77: X2501326322FXT | AP77: 儿童轻薄羽绒服 | AQ77: 橄榄绿;170 | AR77: 颜色分类:橄榄绿;尺码大小:170CM | AS77: 雪中飞 | AT77: 涛源 | AY77: 179 | AZ77: 86.7 | BA77: 普通商品资料成本价 | BB77: 1 | BD77: 1 | BE77: 179 | BF77: 179 | BG77: 86.7 | BH77: 86.7 | BI77: 92.3 | BJ77: 51.564% | BK77: 179 | BL77: 179 | BM77: 179 | BN77: 179 | BU77: 0 | BW77: 15 | BX77: 15 | BZ77: 0.537 | CA77: 0.537 | CB77: 头条放心购 | CC77: TOUTIAOFXG | CE77: 98.2 | CF77: =BD77-BP77 -> 1 | CG77: 179 | CH77: =_xlfn.XLOOKUP(AL77,抖音账单汇总!$A:$A,抖音账单汇总!$B:$B) -> 179
A78: 21056733 | B78: 小店,店铺新客,抖音,高频购买 | D78: 普通订单 | E78: 6924334346710581199 | G78: 已发货 | H78: 河北贝吉实业集团有限公司 | K78: 抖音-雪中飞德煌童装专卖店 | L78: 1@#p3OFCbEJVanDmtdfBIRXQnf2lP5zq4RpvW+jlFSlWQG4l9MXHsmgAkZn81GvDjpVR06N | M78: 13875179 | P78: 2026/2/11 17:49:51 | Q78: 2026/2/12 11:10:05 | R78: 2026/2/11 17:49:52 | S78: 2026/2/19 11:10:06 | T78: 2026/2/11 17:49:52 | U78: 江西省 | V78: 上饶市 | W78: 横峰县 | X78: 京东快递 | Y78: JDAZ23788906792 | AB78: 147:严* | AJ78: I568150074302 | AK78: 3779048132244013371 | AL78: 6924334346710581199 | AM78: X2501326322FXT | AP78: 儿童轻薄羽绒服 | AQ78: 绯红;130 | AR78: 颜色分类:绯红;尺码大小:130CM | AS78: 雪中飞 | AT78: 无唛尚品 | AY78: 179 | AZ78: 90 | BA78: 普通商品资料成本价 | BB78: 1 | BD78: 1 | BE78: 179 | BF78: 179 | BG78: 90 | BH78: 90 | BI78: 89 | BJ78: 49.721% | BK78: 179 | BL78: 179 | BM78: 179 | BN78: 179 | BU78: 0 | BW78: 15 | BX78: 15 | BZ78: 0.419 | CA78: 0.419 | CB78: 头条放心购 | CC78: TOUTIAOFXG | CE78: 101.5 | CF78: =BD78-BP78 -> 1 | CG78: 179 | CH78: =_xlfn.XLOOKUP(AL78,抖音账单汇总!$A:$A,抖音账单汇总!$B:$B) -> 179
A79: 21056542 | B79: 小店,店铺新客,抖音,直播间,高频购买 | D79: 普通订单 | E79: 6950709424565131019 | G79: 已发货 | H79: 河北贝吉实业集团有限公司 | K79: 抖音-雪中飞德煌童装专卖店 | L79: 1@#FvQM1LEspuyVkb08/Goo5cPOYWRKGjOSwPHWy6aSyBOYo/VP4ZBLfc6/ClffzTpu57ey | M79: 13875028 | P79: 2026/2/11 17:30:48 | Q79: 2026/2/12 9:39:54 | R79: 2026/2/11 17:30:52 | S79: 2026/2/19 9:39:57 | T79: 2026/2/11 17:30:52 | U79: 福建省 | V79: 莆田市 | W79: 荔城区 | X79: 京东快递 | Y79: JDAZ23788854350 | AB79: 147:林* | AJ79: I568150018140 | AK79: 3787311554958066065 | AL79: 6950709424565131019 | AM79: X2501326322FXT | AP79: 儿童轻薄羽绒服 | AQ79: 橄榄绿;150 | AR79: 颜色分类:橄榄绿;尺码大小:150CM | AS79: 雪中飞 | AT79: 涛源 | AY79: 179 | AZ79: 86.7 | BA79: 普通商品资料成本价 | BB79: 1 | BD79: 1 | BE79: 179 | BF79: 179 | BG79: 86.7 | BH79: 86.7 | BI79: 92.3 | BJ79: 51.564% | BK79: 179 | BL79: 179 | BM79: 179 | BN79: 179 | BU79: 0 | BW79: 15 | BX79: 15 | BZ79: 0.481 | CA79: 0.481 | CB79: 头条放心购 | CC79: TOUTIAOFXG | CE79: 98.2 | CF79: =BD79-BP79 -> 1 | CG79: 179 | CH79: =_xlfn.XLOOKUP(AL79,抖音账单汇总!$A:$A,抖音账单汇总!$B:$B) -> 179
A80: 21056463 | B80: 小店,店铺新客,抖音,直播间,高频购买 | D80: 普通订单 | E80: 6924327836630678905 | G80: 已发货 | H80: 河北贝吉实业集团有限公司 | K80: 抖音-雪中飞德煌童装专卖店 | L80: 1@#wBTLPLw5WsQ2TYCbVGC/vWp1eXhUUkEemVhsiHaQQQd0McB2HBHTxPh82vmKzmCnyimzVw== | M80: 13874972 | P80: 2026/2/11 17:23:37 | Q80: 2026/2/12 9:39:49 | R80: 2026/2/11 17:23:38 | S80: 2026/2/19 9:39:50 | T80: 2026/2/11 17:23:38 | U80: 山东省 | V80: 济南市 | W80: 历城区 | X80: 京东快递 | Y80: JDAZ23788876650 | AB80: 147:杨* | AJ80: I568150018140 | AK80: 3787311554958066065 | AL80: 6924327836630678905 | AM80: X2501326322FXT | AP80: 儿童轻薄羽绒服 | AQ80: 橄榄绿;150 | AR80: 颜色分类:橄榄绿;尺码大小:150CM | AS80: 雪中飞 | AT80: 涛源 | AY80: 179 | AZ80: 86.7 | BA80: 普通商品资料成本价 | BB80: 1 | BD80: 1 | BE80: 179 | BF80: 179 | BG80: 86.7 | BH80: 86.7 | BI80: 92.3 | BJ80: 51.564% | BK80: 179 | BL80: 179 | BM80: 179 | BN80: 179 | BU80: 0 | BW80: 15 | BX80: 15 | BZ80: 0.481 | CA80: 0.481 | CB80: 头条放心购 | CC80: TOUTIAOFXG | CE80: 98.2 | CF80: =BD80-BP80 -> 1 | CG80: 179 | CH80: =_xlfn.XLOOKUP(AL80,抖音账单汇总!$A:$A,抖音账单汇总!$B:$B) -> 179
A81: 21056229 | B81: 小店,平台补贴,店铺新客,抖音 | D81: 普通订单 | E81: 6950705018503435434 | G81: 已发货 | H81: 河北贝吉实业集团有限公司 | K81: 抖音-雪中飞德煌童装专卖店 | L81: 1@#/MQq6hbiNqT0v9sNvezFPplHerx6PpCMd6eo1HJJ8phmGI8EdFG+eKDTxnkVkSL2WdvMIw== | M81: 13874827 | P81: 2026/2/11 17:02:01 | Q81: 2026/2/11 17:37:58 | R81: 2026/2/11 17:02:03 | S81: 2026/2/18 17:37:59 | T81: 2026/2/11 17:02:03 | U81: 湖南省 | V81: 永州市 | W81: 祁阳市 | X81: 京东快递 | Y81: JDAZ23777565650 | AB81: 147:天* | AJ81: I568114898302 | AK81: 3779048132244013371 | AL81: 6950705018503435434 | AM81: X2501326322FXT | AP81: 儿童轻薄羽绒服 | AQ81: 新雾蓝;130 | AR81: 颜色分类:新雾蓝;尺码大小:130CM | AS81: 雪中飞 | AT81: 涛源 | AY81: 179 | AZ81: 86.7 | BA81: 普通商品资料成本价 | BB81: 1 | BD81: 1 | BE81: 179 | BF81: 179 | BG81: 86.7 | BH81: 86.7 | BI81: 92.3 | BJ81: 51.564% | BK81: 179 | BL81: 179 | BM81: 179 | BN81: 179 | BU81: 0 | BW81: 15 | BX81: 15 | BZ81: 0.419 | CA81: 0.419 | CB81: 头条放心购 | CC81: TOUTIAOFXG | CE81: 98.2 | CF81: =BD81-BP81 -> 1 | CG81: 179 | CH81: =_xlfn.XLOOKUP(AL81,抖音账单汇总!$A:$A,抖音账单汇总!$B:$B) -> 179
A82: 21056184 | B82: 小店,店铺老客,抖音,极速发货 | D82: 普通订单 | E82: 6924336038742162437 | G82: 已发货 | H82: 河北贝吉实业集团有限公司 | K82: 抖音-雪中飞德煌童装专卖店 | L82: 1@#4diiN4QtEOXhku9FwC71PaXaa1CJm8v9zTNI/ikn4Mor5GeTcoCGXeuDQrLfDn03PLO1 | M82: 13810753 | P82: 2026/2/11 16:58:23 | Q82: 2026/2/11 17:31:50 | R82: 2026/2/11 16:58:48 | S82: 2026/2/18 17:31:50 | T82: 2026/2/11 16:58:48 | U82: 重庆 | V82: 重庆市 | W82: 潼南区 | X82: 京东快递 | Y82: JDAZ23777637488 | AB82: 147:汪* | AJ82: I568150018700 | AK82: 3787311554958066065 | AL82: 6924336038742162437 | AM82: X2501326322FXT | AP82: 儿童轻薄羽绒服 | AQ82: 橄榄绿;170 | AR82: 颜色分类:橄榄绿;尺码大小:170CM | AS82: 雪中飞 | AT82: 涛源 | AY82: 179 | AZ82: 86.7 | BA82: 普通商品资料成本价 | BB82: 1 | BD82: 1 | BE82: 179 | BF82: 179 | BG82: 86.7 | BH82: 86.7 | BI82: 92.3 | BJ82: 51.564% | BK82: 179 | BL82: 179 | BM82: 179 | BN82: 179 | BU82: 0 | BW82: 15 | BX82: 15 | BZ82: 0.537 | CA82: 0.537 | CB82: 头条放心购 | CC82: TOUTIAOFXG | CE82: 98.2 | CF82: =BD82-BP82 -> 1 | CG82: 179 | CH82: =_xlfn.XLOOKUP(AL82,抖音账单汇总!$A:$A,抖音账单汇总!$B:$B) -> 179
A83: 20147863 | B83: 优先发货,发货后售后,小店,店铺新客,抖音,服务优先,直播间 | C83: 1226130425 | D83: 普通订单 | E83: 6923706623434718909 | G83: 已发货 | H83: 河北贝吉实业集团有限公司 | K83: 抖音-雪中飞德煌童装专卖店 | L83: 1@#myO5PCCM7KtWPra5AEvzT5JNyBXy3vgIhPOah3zFh7pPysy5qdaKxwGYNQfb0nnOolhhrCBvgiM= | M83: 13207929 | O83: cp8无人接听，16点梦函,(收) 颜色分类:蝶恋紫;尺码大小:160cmI568114919600*1#,(收) 颜色分类:藏青色;尺码大小:150cmH626415547140*1#,换货(20634124)# | P83: 2026/1/18 16:08:29 | Q83: 2026/1/19 9:34:36 | R83: 2026/1/18 16:08:36 | S83: 2026/1/25 17:18:02 | T83: 2026/1/18 16:08:36 | U83: 湖北省 | V83: 襄阳市 | W83: 樊城区 | X83: 圆通速递 | Y83: YT0007237198710 | Z83: 圆通快递 | AA83: YT2581488885240 | AB83: 147:马* | AC83: 2026/1/25 18:53:35 | AD83: 2026/1/28 10:59:01 | AE83: 2026-01-28 10:58:54 | AF83: 19800025 | AG83: 河北贝吉实业集团有限公司 | AH83: 普通退货 | AI83: 7天无理由退款 | AJ83: I568114919600 | AK83: 3787311554958066065 | AL83: 6923706623434718909 | AM83: X2501326322FXT | AN83: 轻薄羽绒服 | AP83: 儿童轻薄羽绒服 | AQ83: 香芋紫;160 | AR83: 颜色分类:蝶恋紫;尺码大小:160CM | AS83: 雪中飞 | AT83: 涛源 | AY83: 179 | AZ83: 86.7 | BA83: 普通商品资料成本价 | BB83: 1 | BD83: 1 | BE83: 179 | BF83: 179 | BG83: 86.7 | BH83: 86.7 | BI83: 92.3 | BJ83: 51.564% | BK83: 378 | BL83: 378 | BM83: 179 | BN83: 179 | BO83: 1 | BP83: 1 | BQ83: 179 | BR83: 86.7 | BS83: 86.7 | BT83: 179 | BU83: 0 | BW83: 5.6 | BX83: 2.65 | BZ83: 1.085 | CA83: 1.085 | CB83: 头条放心购 | CC83: TOUTIAOFXG | CE83: 98.2 | CF83: =BD83-BP83 -> 0 | CG83: 0 | CH83: =_xlfn.XLOOKUP(AL83,抖音账单汇总!$A:$A,抖音账单汇总!$B:$B) -> 199
A84: 21055840 | B84: 小店,平台补贴,店铺新客,直播间,高频购买 | D84: 普通订单 | E84: 6924320778508533172 | G84: 已发货 | H84: 河北贝吉实业集团有限公司 | K84: 抖音-雪中飞德煌童装专卖店 | L84: 1@#5k0FQOsCK0vH4Q/s1UidZIxTe2autU2TE/PrxGYbv8jVl3Xs3PMfjRUTFrildY0ICFc4 | M84: 13874548 | P84: 2026/2/11 16:30:27 | Q84: 2026/2/11 17:41:45 | R84: 2026/2/11 16:30:34 | S84: 2026/2/18 17:41:47 | T84: 2026/2/11 16:30:34 | U84: 广东省 | V84: 东莞市 | W84: 东莞市 | X84: 京东快递 | Y84: JDAZ23777510635 | AB84: 147:钟* | AJ84: I568150018252 | AK84: 3787311554958066065 | AL84: 6924320778508533172 | AM84: X2501326322FXT | AP84: 儿童轻薄羽绒服 | AQ84: 橄榄绿;110 | AR84: 颜色分类:橄榄绿;尺码大小:110CM | AS84: 雪中飞 | AT84: 涛源 | AY84: 179 | AZ84: 86.7 | BA84: 普通商品资料成本价 | BB84: 1 | BD84: 1 | BE84: 179 | BF84: 179 | BG84: 86.7 | BH84: 86.7 | BI84: 92.3 | BJ84: 51.564% | BK84: 179 | BL84: 179 | BM84: 179 | BN84: 179 | BU84: 0 | BW84: 15 | BX84: 15 | BZ84: 0.36 | CA84: 0.36 | CB84: 头条放心购 | CC84: TOUTIAOFXG | CE84: 98.2 | CF84: =BD84-BP84 -> 1 | CG84: 179 | CH84: =_xlfn.XLOOKUP(AL84,抖音账单汇总!$A:$A,抖音账单汇总!$B:$B) -> 179
A85: 21055713 | B85: 小店,店铺新客,抖音,极速发货,直播间 | D85: 普通订单 | E85: 6950722647426536896 | G85: 已发货 | H85: 河北贝吉实业集团有限公司 | K85: 抖音-雪中飞德煌童装专卖店 | L85: 1@#rp+/hYkfPWmNldcGmh1weDtj3U+nR28f5T8g1W/GLCBapdr53a5ha8TK8ZirTdFGXpn3 | M85: 13874462 | P85: 2026/2/11 16:21:03 | Q85: 2026/2/11 17:31:47 | R85: 2026/2/11 16:21:04 | S85: 2026/2/18 17:31:50 | T85: 2026/2/11 16:21:04 | U85: 安徽省 | V85: 合肥市 | W85: 庐江县 | X85: 京东快递 | Y85: JDAZ23777575101 | AB85: 147:张* | AJ85: I568150018700 | AK85: 3787311554958066065 | AL85: 6950722647426536896 | AM85: X2501326322FXT | AP85: 儿童轻薄羽绒服 | AQ85: 橄榄绿;170 | AR85: 颜色分类:橄榄绿;尺码大小:170CM | AS85: 雪中飞 | AT85: 涛源 | AY85: 179 | AZ85: 86.7 | BA85: 普通商品资料成本价 | BB85: 1 | BD85: 1 | BE85: 179 | BF85: 179 | BG85: 86.7 | BH85: 86.7 | BI85: 92.3 | BJ85: 51.564% | BK85: 179 | BL85: 179 | BM85: 179 | BN85: 179 | BU85: 0 | BW85: 15 | BX85: 15 | BZ85: 0.537 | CA85: 0.537 | CB85: 头条放心购 | CC85: TOUTIAOFXG | CE85: 98.2 | CF85: =BD85-BP85 -> 1 | CG85: 179 | CH85: =_xlfn.XLOOKUP(AL85,抖音账单汇总!$A:$A,抖音账单汇总!$B:$B) -> 179
A86: 21055637 | B86: 小店,店铺新客,抖音极速版,极速发货,直播间,高频购买 | D86: 普通订单 | E86: 6924325430163963823 | G86: 已发货 | H86: 河北贝吉实业集团有限公司 | K86: 抖音-雪中飞德煌童装专卖店 | L86: 1@#FbxiMk6icWS50JthvCOtuQxnkTLo+B/FnowEZWjzpoiExakYh5ummZe2idmkZuet6K93cGBwqAg= | M86: 13874405 | P86: 2026/2/11 16:15:15 | Q86: 2026/2/11 17:37:46 | R86: 2026/2/11 16:15:30 | S86: 2026/2/18 17:37:48 | T86: 2026/2/11 16:15:30 | U86: 云南省 | V86: 昭通市 | W86: 彝良县 | X86: 京东快递 | Y86: JDAZ23777510652 | AB86: 147:吴* | AJ86: I568150018302 | AK86: 3787311554958066065 | AL86: 6924325430163963823 | AM86: X2501326322FXT | AP86: 儿童轻薄羽绒服 | AQ86: 橄榄绿;130 | AR86: 颜色分类:橄榄绿;尺码大小:130CM | AS86: 雪中飞 | AT86: 涛源 | AY86: 179 | AZ86: 86.7 | BA86: 普通商品资料成本价 | BB86: 1 | BD86: 1 | BE86: 179 | BF86: 179 | BG86: 86.7 | BH86: 86.7 | BI86: 92.3 | BJ86: 51.564% | BK86: 179 | BL86: 179 | BM86: 179 | BN86: 179 | BU86: 0 | BW86: 15 | BX86: 15 | BZ86: 0.419 | CA86: 0.419 | CB86: 头条放心购 | CC86: TOUTIAOFXG | CE86: 98.2 | CF86: =BD86-BP86 -> 1 | CG86: 179 | CH86: =_xlfn.XLOOKUP(AL86,抖音账单汇总!$A:$A,抖音账单汇总!$B:$B) -> 179
A87: 21055618 | B87: 小店,平台补贴,店铺新客,抖音极速版,极速发货,高频购买 | D87: 普通订单 | E87: 6950718192440251753 | G87: 已发货 | H87: 河北贝吉实业集团有限公司 | K87: 抖音-雪中飞德煌童装专卖店 | L87: 1@#F6OY1gTbdu4W1dQ+PS5ss4On1y5XvGa/D+OTQfeRxvKJ1ekotPvAo/I5Toe3f4tQQuJxaNTlJYc= | M87: 13874388 | P87: 2026/2/11 16:14:22 | Q87: 2026/2/11 17:31:10 | R87: 2026/2/11 16:14:28 | S87: 2026/2/18 17:31:13 | T87: 2026/2/11 16:14:28 | U87: 江苏省 | V87: 南京市 | W87: 鼓楼区 | X87: 京东快递 | Y87: JDAZ23777579940 | AB87: 147:灵* | AJ87: I568114898600 | AK87: 3787311554958066065 | AL87: 6950718192440251753 | AM87: X2501326322FXT | AP87: 儿童轻薄羽绒服 | AQ87: 新雾蓝;160 | AR87: 颜色分类:新雾蓝;尺码大小:160CM | AS87: 雪中飞 | AT87: 涛源 | AY87: 179 | AZ87: 86.7 | BA87: 普通商品资料成本价 | BB87: 1 | BD87: 1 | BE87: 179 | BF87: 179 | BG87: 86.7 | BH87: 86.7 | BI87: 92.3 | BJ87: 51.564% | BK87: 179 | BL87: 179 | BM87: 179 | BN87: 179 | BU87: 0 | BW87: 15 | BX87: 15 | BZ87: 0.506 | CA87: 0.506 | CB87: 头条放心购 | CC87: TOUTIAOFXG | CE87: 98.2 | CF87: =BD87-BP87 -> 1 | CG87: 179 | CH87: =_xlfn.XLOOKUP(AL87,抖音账单汇总!$A:$A,抖音账单汇总!$B:$B) -> 179
A88: 21054706 | B88: 小店,店铺老客,抖音,高频购买 | D88: 普通订单 | E88: 6950702845740652454 | G88: 已发货 | H88: 河北贝吉实业集团有限公司 | K88: 抖音-雪中飞德煌童装专卖店 | L88: 1@#AbrJGYjHDghW9lgoSTF7ZLXaZF7HW5LhT9KA/hJr5swpvcEd1E/bdHFOlrH2aLQje/Cq | M88: 13801107 | P88: 2026/2/11 14:56:23 | Q88: 2026/2/11 16:51:24 | R88: 2026/2/11 14:56:32 | S88: 2026/2/18 16:51:26 | T88: 2026/2/11 14:56:32 | U88: 江西省 | V88: 景德镇市 | W88: 珠山区 | X88: 京东快递 | Y88: JDAZ23776038119 | AB88: 147:于* | AJ88: I568150018700 | AK88: 3787311554958066065 | AL88: 6950702845740652454 | AM88: X2501326322FXT | AP88: 儿童轻薄羽绒服 | AQ88: 橄榄绿;170 | AR88: 颜色分类:橄榄绿;尺码大小:170CM | AS88: 雪中飞 | AT88: 涛源 | AY88: 179 | AZ88: 86.7 | BA88: 普通商品资料成本价 | BB88: 1 | BD88: 1 | BE88: 179 | BF88: 179 | BG88: 86.7 | BH88: 86.7 | BI88: 92.3 | BJ88: 51.564% | BK88: 179 | BL88: 179 | BM88: 179 | BN88: 179 | BU88: 0 | BW88: 15 | BX88: 15 | BZ88: 0.537 | CA88: 0.537 | CB88: 头条放心购 | CC88: TOUTIAOFXG | CE88: 98.2 | CF88: =BD88-BP88 -> 1 | CG88: 179 | CH88: =_xlfn.XLOOKUP(AL88,抖音账单汇总!$A:$A,抖音账单汇总!$B:$B) -> 179
A89: 21054660 | B89: 小店,平台补贴,店铺新客,抖音,直播间,线上修改地址,高频购买 | D89: 普通订单 | E89: 6924320715369316164 | G89: 已发货 | H89: 河北贝吉实业集团有限公司 | K89: 抖音-雪中飞德煌童装专卖店 | L89: 1@#7X18HWNJZY6sYCbSo3MMMj3YBUp24VoQjvpZFAG9QudxezZC8x478JJhD5ea7LMii1qMSw== | M89: 13873706 | P89: 2026/2/11 14:53:12 | Q89: 2026/2/11 16:44:26 | R89: 2026/2/11 14:53:13 | S89: 2026/2/18 16:44:29 | T89: 2026/2/11 14:53:13 | U89: 湖北省 | V89: 仙桃市 | W89: 仙桃市 | X89: 京东快递 | Y89: JDAZ23775991693 | AB89: 147:小* | AJ89: I568150018302 | AK89: 3787311554958066065 | AL89: 6924320715369316164 | AM89: X2501326322FXT | AP89: 儿童轻薄羽绒服 | AQ89: 橄榄绿;130 | AR89: 颜色分类:橄榄绿;尺码大小:130CM | AS89: 雪中飞 | AT89: 涛源 | AY89: 179 | AZ89: 86.7 | BA89: 普通商品资料成本价 | BB89: 1 | BD89: 1 | BE89: 179 | BF89: 179 | BG89: 86.7 | BH89: 86.7 | BI89: 92.3 | BJ89: 51.564% | BK89: 179 | BL89: 179 | BM89: 179 | BN89: 179 | BU89: 0 | BW89: 15 | BX89: 15 | BZ89: 0.419 | CA89: 0.419 | CB89: 头条放心购 | CC89: TOUTIAOFXG | CE89: 98.2 | CF89: =BD89-BP89 -> 1 | CG89: 179 | CH89: =_xlfn.XLOOKUP(AL89,抖音账单汇总!$A:$A,抖音账单汇总!$B:$B) -> 179
A90: 21054313 | B90: 小店,店铺老客,抖音,极速发货,直播间,高频购买 | D90: 普通订单 | E90: 6924331896433442174 | G90: 已发货 | H90: 河北贝吉实业集团有限公司 | K90: 抖音-雪中飞德煌童装专卖店 | L90: 1@#sgGR/kklsr9g9iqcx+FSz0HKsbqoxh4f1lXJADVGGgyqv+VH1fbA8EiNkM+h0X/uVTny | M90: 13872769 | P90: 2026/2/11 14:24:10 | Q90: 2026/2/11 14:50:49 | R90: 2026/2/11 14:24:18 | S90: 2026/2/18 14:50:51 | T90: 2026/2/11 14:24:18 | U90: 天津 | V90: 天津市 | W90: 河西区 | X90: 京东快递 | Y90: JDAZ23772766778 | AB90: 147:王* | AJ90: I568150018140 | AK90: 3787311554958066065 | AL90: 6924331896433442174 | AM90: X2501326322FXT | AP90: 儿童轻薄羽绒服 | AQ90: 橄榄绿;150 | AR90: 颜色分类:橄榄绿;尺码大小:150CM | AS90: 雪中飞 | AT90: 涛源 | AY90: 179 | AZ90: 86.7 | BA90: 普通商品资料成本价 | BB90: 1 | BD90: 1 | BE90: 179 | BF90: 179 | BG90: 86.7 | BH90: 86.7 | BI90: 92.3 | BJ90: 51.564% | BK90: 179 | BL90: 179 | BM90: 179 | BN90: 179 | BU90: 0 | BW90: 15 | BX90: 15 | BZ90: 0.481 | CA90: 0.481 | CB90: 头条放心购 | CC90: TOUTIAOFXG | CE90: 98.2 | CF90: =BD90-BP90 -> 1 | CG90: 179 | CH90: =_xlfn.XLOOKUP(AL90,抖音账单汇总!$A:$A,抖音账单汇总!$B:$B) -> 179
A91: 21053901 | B91: 小店,店铺新客,抖音,极速发货,直播间,高频购买 | D91: 普通订单 | E91: 6924318817809432132 | G91: 已发货 | H91: 河北贝吉实业集团有限公司 | K91: 抖音-雪中飞德煌童装专卖店 | L91: 1@#YG4HJfj8MtroF3MdvfNQrs6P4Qztso3CyzLTK2PcDOax1EbwQY6Ii2Lac2TgAc540Pig | M91: 13873184 | P91: 2026/2/11 13:55:15 | Q91: 2026/2/11 15:02:41 | R91: 2026/2/11 13:55:21 | S91: 2026/2/13 20:21:16 | T91: 2026/2/11 13:55:21 | U91: 江苏省 | V91: 南京市 | W91: 鼓楼区 | X91: 京东快递 | Y91: JDAZ23772761981 | AB91: 147:赵* | AJ91: I568150018164 | AK91: 3787311554958066065 | AL91: 6924318817809432132 | AM91: X2501326322FXT | AP91: 儿童轻薄羽绒服 | AQ91: 橄榄绿;120 | AR91: 颜色分类:橄榄绿;尺码大小:120CM | AS91: 雪中飞 | AT91: 涛源 | AY91: 179 | AZ91: 86.7 | BA91: 普通商品资料成本价 | BB91: 1 | BD91: 1 | BE91: 179 | BF91: 179 | BG91: 86.7 | BH91: 86.7 | BI91: 92.3 | BJ91: 51.564% | BK91: 179 | BL91: 179 | BM91: 179 | BN91: 179 | BU91: 0 | BW91: 15 | BX91: 15 | BZ91: 0.413 | CA91: 0.413 | CB91: 头条放心购 | CC91: TOUTIAOFXG | CE91: 98.2 | CF91: =BD91-BP91 -> 1 | CG91: 179 | CH91: =_xlfn.XLOOKUP(AL91,抖音账单汇总!$A:$A,抖音账单汇总!$B:$B) -> 179
A92: 21053826 | B92: 小店,平台补贴,店铺新客,高频购买 | D92: 普通订单 | E92: 6950718105125721164 | G92: 已发货 | H92: 河北贝吉实业集团有限公司 | K92: 抖音-雪中飞德煌童装专卖店 | L92: 1@#LMHhNvn+VUBNwgKsz+Nj0be2st121qB8uVkmUxlUhPIPLwpWEBfX194TUH/NW8ACuvwARQ== | M92: 13873127 | P92: 2026/2/11 13:49:55 | Q92: 2026/2/11 14:56:24 | R92: 2026/2/11 13:50:06 | S92: 2026/2/18 14:56:26 | T92: 2026/2/11 13:50:06 | U92: 湖北省 | V92: 襄阳市 | W92: 枣阳市 | X92: 京东快递 | Y92: JDAZ23772730358 | AB92: 147:沈* | AJ92: I568114898600 | AK92: 3779048132244013371 | AL92: 6950718105125721164 | AM92: X2501326322FXT | AP92: 儿童轻薄羽绒服 | AQ92: 新雾蓝;160 | AR92: 颜色分类:新雾蓝;尺码大小:160CM | AS92: 雪中飞 | AT92: 涛源 | AY92: 179 | AZ92: 86.7 | BA92: 普通商品资料成本价 | BB92: 1 | BD92: 1 | BE92: 179 | BF92: 179 | BG92: 86.7 | BH92: 86.7 | BI92: 92.3 | BJ92: 51.564% | BK92: 179 | BL92: 179 | BM92: 179 | BN92: 179 | BU92: 0 | BW92: 15 | BX92: 15 | BZ92: 0.506 | CA92: 0.506 | CB92: 头条放心购 | CC92: TOUTIAOFXG | CE92: 98.2 | CF92: =BD92-BP92 -> 1 | CG92: 179 | CH92: =_xlfn.XLOOKUP(AL92,抖音账单汇总!$A:$A,抖音账单汇总!$B:$B) -> 179
A93: 21053640 | B93: 小店,店铺新客,抖音,极速发货,直播间,高频购买 | D93: 普通订单 | E93: 6924338014380457284 | G93: 已发货 | H93: 河北贝吉实业集团有限公司 | K93: 抖音-雪中飞德煌童装专卖店 | L93: 1@#VqFjIuro2F7HalMrCJtQy7YCaEFViXfoegJhcG7nAPwKjsjrH9umkOmKiMwOaBjnK6hS5QIZtmk= | M93: 13872984 | P93: 2026/2/11 13:36:05 | Q93: 2026/2/11 15:02:05 | R93: 2026/2/11 13:36:10 | S93: 2026/2/18 15:02:07 | T93: 2026/2/11 13:36:10 | U93: 重庆 | V93: 重庆市 | W93: 九龙坡区 | X93: 京东快递 | Y93: JDAZ23772761990 | AB93: 147:曾* | AJ93: H626414417252 | AK93: 3787311554958066065 | AL93: 6924338014380457284 | AM93: X250138238FXT | AN93: 轻薄羽绒服 | AP93: 儿童轻薄羽绒服 | AQ93: 黑色;110 | AR93: 颜色分类:黑色（8238款）;尺码大小:110CM | AS93: 雪中飞 | AT93: 茸淳羽绒 | AW93: 每日加权 | AY93: 199 | AZ93: 105.3 | BA93: 普通商品资料成本价 | BB93: 1 | BD93: 1 | BE93: 199 | BF93: 199 | BG93: 105.3 | BH93: 105.3 | BI93: 93.7 | BJ93: 47.085% | BK93: 199 | BL93: 199 | BM93: 199 | BN93: 199 | BU93: 0 | BW93: 15 | BX93: 15 | BZ93: 0.449 | CA93: 0.449 | CB93: 头条放心购 | CC93: TOUTIAOFXG | CE93: 116.8 | CF93: =BD93-BP93 -> 1 | CG93: 199 | CH93: =_xlfn.XLOOKUP(AL93,抖音账单汇总!$A:$A,抖音账单汇总!$B:$B) -> 199
A94: 21053518 | B94: 小店,平台补贴,店铺新客,高频购买 | D94: 普通订单 | E94: 6950724761460152024 | G94: 已发货 | H94: 河北贝吉实业集团有限公司 | K94: 抖音-雪中飞德煌童装专卖店 | L94: 1@#n6PVNzHaP+wAGhQMWm1g60BaAYEXSbQzMo0DJNL9FUPLhxzAilcw25wLnVmB86jDBBkMzQ== | M94: 13872907 | P94: 2026/2/11 13:26:52 | Q94: 2026/2/11 14:56:06 | R94: 2026/2/11 13:27:09 | S94: 2026/2/18 14:56:08 | T94: 2026/2/11 13:27:09 | U94: 江苏省 | V94: 徐州市 | W94: 新沂市 | X94: 京东快递 | Y94: JDAZ23772696021 | AB94: 147:杨* | AJ94: I568114898600 | AK94: 3779048132244013371 | AL94: 6950724761460152024 | AM94: X2501326322FXT | AP94: 儿童轻薄羽绒服 | AQ94: 新雾蓝;160 | AR94: 颜色分类:新雾蓝;尺码大小:160CM | AS94: 雪中飞 | AT94: 涛源 | AY94: 179 | AZ94: 86.7 | BA94: 普通商品资料成本价 | BB94: 1 | BD94: 1 | BE94: 179 | BF94: 179 | BG94: 86.7 | BH94: 86.7 | BI94: 92.3 | BJ94: 51.564% | BK94: 179 | BL94: 179 | BM94: 179 | BN94: 179 | BU94: 0 | BW94: 15 | BX94: 15 | BZ94: 0.506 | CA94: 0.506 | CB94: 头条放心购 | CC94: TOUTIAOFXG | CE94: 98.2 | CF94: =BD94-BP94 -> 1 | CG94: 179 | CH94: =_xlfn.XLOOKUP(AL94,抖音账单汇总!$A:$A,抖音账单汇总!$B:$B) -> 179
A95: 21053162 | B95: 小店,平台补贴,店铺新客,抖音,服务优先,极速发货,消费者催发货 | D95: 普通订单 | E95: 6950702737305179309 | G95: 已发货 | H95: 河北贝吉实业集团有限公司 | K95: 抖音-雪中飞德煌童装专卖店 | L95: 1@#Fvj1ZwRLo79elAQvv1cn3DL6weKOvzlrApH+IuQ4e+mXhGu/6YMbAGM1tqujl8WIx3Ge | M95: 13872670 | P95: 2026/2/11 12:59:31 | Q95: 2026/2/11 14:51:22 | R95: 2026/2/11 12:59:43 | S95: 2026/2/18 14:51:23 | T95: 2026/2/11 12:59:43 | U95: 山东省 | V95: 日照市 | W95: 东港区 | X95: 京东快递 | Y95: JDAZ23772747312 | AB95: 147:韩* | AJ95: I568150018600 | AK95: 3787311554958066065 | AL95: 6950702737305179309 | AM95: X2501326322FXT | AP95: 儿童轻薄羽绒服 | AQ95: 橄榄绿;160 | AR95: 颜色分类:橄榄绿;尺码大小:160CM | AS95: 雪中飞 | AT95: 涛源 | AY95: 179 | AZ95: 86.7 | BA95: 普通商品资料成本价 | BB95: 1 | BD95: 1 | BE95: 179 | BF95: 179 | BG95: 86.7 | BH95: 86.7 | BI95: 92.3 | BJ95: 51.564% | BK95: 179 | BL95: 179 | BM95: 179 | BN95: 179 | BU95: 0 | BW95: 15 | BX95: 15 | BZ95: 0.506 | CA95: 0.506 | CB95: 头条放心购 | CC95: TOUTIAOFXG | CE95: 98.2 | CF95: =BD95-BP95 -> 1 | CG95: 179 | CH95: =_xlfn.XLOOKUP(AL95,抖音账单汇总!$A:$A,抖音账单汇总!$B:$B) -> 179
A96: 21053134 | B96: 小店,店铺新客,抖音,极速发货,直播间,高频购买 | D96: 普通订单 | E96: 6924335706295270894 | G96: 已发货 | H96: 河北贝吉实业集团有限公司 | K96: 抖音-雪中飞德煌童装专卖店 | L96: 1@#+ygaaessIY0ibKY9AiFsJ8Y79bk7I85swbbvnyaKRIxV+7xhQiGaR8B2wFYZ+2M7T1Qw3HiUas0= | M96: 13872650 | P96: 2026/2/11 12:57:10 | Q96: 2026/2/11 14:51:19 | R96: 2026/2/11 12:57:15 | S96: 2026/2/18 14:51:22 | T96: 2026/2/11 12:57:15 | U96: 湖北省 | V96: 武汉市 | W96: 青山区 | X96: 京东快递 | Y96: JDAZ23772679425 | AB96: 147:刘* | AJ96: I568150018600 | AK96: 3787311554958066065 | AL96: 6924335706295270894 | AM96: X2501326322FXT | AP96: 儿童轻薄羽绒服 | AQ96: 橄榄绿;160 | AR96: 颜色分类:橄榄绿;尺码大小:160CM | AS96: 雪中飞 | AT96: 涛源 | AY96: 179 | AZ96: 86.7 | BA96: 普通商品资料成本价 | BB96: 1 | BD96: 1 | BE96: 179 | BF96: 179 | BG96: 86.7 | BH96: 86.7 | BI96: 92.3 | BJ96: 51.564% | BK96: 179 | BL96: 179 | BM96: 179 | BN96: 179 | BU96: 0 | BW96: 15 | BX96: 15 | BZ96: 0.506 | CA96: 0.506 | CB96: 头条放心购 | CC96: TOUTIAOFXG | CE96: 98.2 | CF96: =BD96-BP96 -> 1 | CG96: 179 | CH96: =_xlfn.XLOOKUP(AL96,抖音账单汇总!$A:$A,抖音账单汇总!$B:$B) -> 179
A97: 21053092 | B97: 小店,平台补贴,店铺新客,抖音,极速发货,直播间,线上修改地址,高频购买 | D97: 普通订单 | E97: 6924327524338204219 | G97: 已发货 | H97: 河北贝吉实业集团有限公司 | K97: 抖音-雪中飞德煌童装专卖店 | L97: 1@#cAES2i/YESm7FuSJSqUl49wGWuOwtAXwSZ4bBKOoHe4YKo8RYCVjL2pKMZexcflsIw0i7lEmo24= | M97: 13872617 | P97: 2026/2/11 12:53:39 | Q97: 2026/2/11 14:54:05 | R97: 2026/2/11 12:53:44 | S97: 2026/2/18 14:54:07 | T97: 2026/2/11 12:53:44 | U97: 江西省 | V97: 赣州市 | W97: 于都县 | X97: 京东快递 | Y97: JDAZ23772762145 | AB97: 147:玲* | AJ97: I568114898700 | AK97: 3787311554958066065 | AL97: 6924327524338204219 | AM97: X2501326322FXT | AP97: 儿童轻薄羽绒服 | AQ97: 新雾蓝;170 | AR97: 颜色分类:新雾蓝;尺码大小:170CM | AS97: 雪中飞 | AT97: 涛源 | AY97: 179 | AZ97: 86.7 | BA97: 普通商品资料成本价 | BB97: 1 | BD97: 1 | BE97: 179 | BF97: 179 | BG97: 86.7 | BH97: 86.7 | BI97: 92.3 | BJ97: 51.564% | BK97: 179 | BL97: 179 | BM97: 179 | BN97: 179 | BU97: 0 | BW97: 15 | BX97: 15 | BZ97: 0.537 | CA97: 0.537 | CB97: 头条放心购 | CC97: TOUTIAOFXG | CE97: 98.2 | CF97: =BD97-BP97 -> 1 | CG97: 179 | CH97: =_xlfn.XLOOKUP(AL97,抖音账单汇总!$A:$A,抖音账单汇总!$B:$B) -> 179
A98: 21052521 | B98: 小店,店铺新客,抖音,极速发货,线上修改地址,高频购买 | D98: 普通订单 | E98: 6950704750526338053 | G98: 已发货 | H98: 河北贝吉实业集团有限公司 | K98: 抖音-雪中飞德煌童装专卖店 | L98: 1@#W3RBQKS17bCFFY44Ka5UQp9VKKDtQMvPuIqNmOZdfzy97DAJmJA197d2TkGZSd1gErTf | M98: 13872186 | P98: 2026/2/11 12:09:27 | Q98: 2026/2/11 15:02:17 | R98: 2026/2/11 12:09:31 | S98: 2026/2/18 15:02:18 | T98: 2026/2/11 12:09:31 | U98: 江苏省 | V98: 南通市 | W98: 海安市 | X98: 京东快递 | Y98: JDAZ23772762218 | AB98: 147:花* | AJ98: I568114898164 | AK98: 3787311554958066065 | AL98: 6950704750526338053 | AM98: X2501326322FXT | AP98: 儿童轻薄羽绒服 | AQ98: 新雾蓝;120 | AR98: 颜色分类:新雾蓝;尺码大小:120CM | AS98: 雪中飞 | AT98: 涛源 | AY98: 179 | AZ98: 86.7 | BA98: 普通商品资料成本价 | BB98: 1 | BD98: 1 | BE98: 179 | BF98: 179 | BG98: 86.7 | BH98: 86.7 | BI98: 92.3 | BJ98: 51.564% | BK98: 179 | BL98: 179 | BM98: 179 | BN98: 179 | BU98: 0 | BW98: 15 | BX98: 15 | BZ98: 0.413 | CA98: 0.413 | CB98: 头条放心购 | CC98: TOUTIAOFXG | CE98: 98.2 | CF98: =BD98-BP98 -> 1 | CG98: 179 | CH98: =_xlfn.XLOOKUP(AL98,抖音账单汇总!$A:$A,抖音账单汇总!$B:$B) -> 179
A99: 21052379 | B99: 发货后售后,小店,平台补贴,店铺新客,极速发货,直播间,高频购买 | D99: 普通订单 | E99: 6950709155812022117 | G99: 已发货 | H99: 河北贝吉实业集团有限公司 | K99: 抖音-雪中飞德煌童装专卖店 | L99: 1@#+FzbSqorEn4eT1wPqOp+QACMeOtoVsrD08oChAmIqYCUymgr81vlPOWLOARnQkM5HtXY | M99: 13872070 | O99: (收) 颜色分类:橄榄绿;尺码大小:130cmI568150018302*1# | P99: 2026/2/11 11:57:08 | Q99: 2026/2/11 15:02:32 | R99: 2026/2/11 11:57:24 | S99: 2026/2/18 15:02:34 | T99: 2026/2/11 11:57:24 | U99: 四川省 | V99: 宜宾市 | W99: 珙县 | X99: 京东快递 | Y99: JDAZ23772747375 | AB99: 147:李* | AJ99: I568150018302 | AK99: 3787311554958066065 | AL99: 6950709155812022117 | AM99: X2501326322FXT | AP99: 儿童轻薄羽绒服 | AQ99: 橄榄绿;130 | AR99: 颜色分类:橄榄绿;尺码大小:130CM | AS99: 雪中飞 | AT99: 涛源 | AY99: 179 | AZ99: 86.7 | BA99: 普通商品资料成本价 | BB99: 1 | BD99: 1 | BE99: 179 | BF99: 179 | BG99: 86.7 | BH99: 86.7 | BI99: 92.3 | BJ99: 51.564% | BK99: 179 | BL99: 179 | BM99: 179 | BN99: 179 | BU99: 0 | BW99: 15 | BX99: 15 | BZ99: 0.419 | CA99: 0.419 | CB99: 头条放心购 | CC99: TOUTIAOFXG | CE99: 98.2 | CF99: =BD99-BP99 -> 1 | CG99: 179 | CH99: =_xlfn.XLOOKUP(AL99,抖音账单汇总!$A:$A,抖音账单汇总!$B:$B) -> 179
A100: 21052368 | B100: 小店,店铺新客,抖音,极速发货 | D100: 普通订单 | E100: 6950715891834426624 | G100: 已发货 | H100: 河北贝吉实业集团有限公司 | K100: 抖音-雪中飞德煌童装专卖店 | L100: 1@#s1iNVodJW2iqPHXpqRsuWgtNsB+S2d990rsaY466pkvYObiCBlXg2uvPR17f+8JLtv7t | M100: 13872062 | P100: 2026/2/11 11:56:30 | Q100: 2026/2/11 14:50:23 | R100: 2026/2/11 11:56:37 | S100: 2026/2/18 14:50:27 | T100: 2026/2/11 11:56:37 | U100: 四川省 | V100: 广元市 | W100: 旺苍县 | X100: 京东快递 | Y100: JDAZ23772762136 | AB100: 147:马* | AJ100: I568150018140 | AK100: 3787311554958066065 | AL100: 6950715891834426624 | AM100: X2501326322FXT | AP100: 儿童轻薄羽绒服 | AQ100: 橄榄绿;150 | AR100: 颜色分类:橄榄绿;尺码大小:150CM | AS100: 雪中飞 | AT100: 涛源 | AY100: 179 | AZ100: 86.7 | BA100: 普通商品资料成本价 | BB100: 1 | BD100: 1 | BE100: 179 | BF100: 179 | BG100: 86.7 | BH100: 86.7 | BI100: 92.3 | BJ100: 51.564% | BK100: 179 | BL100: 179 | BM100: 179 | BN100: 179 | BU100: 0 | BW100: 15 | BX100: 15 | BZ100: 0.481 | CA100: 0.481 | CB100: 头条放心购 | CC100: TOUTIAOFXG | CE100: 98.2 | CF100: =BD100-BP100 -> 1 | CG100: 179 | CH100: =_xlfn.XLOOKUP(AL100,抖音账单汇总!$A:$A,抖音账单汇总!$B:$B) -> 179
...
